AZ8/WB.v
module WB (dst_addr_i,
           data_i,
           clk,
           dst_addr_o,
           data_o,
           w_en);
    
    parameter ADDR_LEN  = 5;
    parameter WORD_SIZE = 32;
    
    input [ADDR_LEN-1:0]dst_addr_i;
    input [WORD_SIZE-1:0]data_i;
    input clk;
    
    output [ADDR_LEN-1:0]dst_addr_o;
    output [WORD_SIZE-1:0]data_o;
    output w_en;
    
    reg [ADDR_LEN-1:0]dst_addr_out;
    reg [WORD_SIZE-1:0]data_out;
    reg memory_write_mod;
    
    assign dst_addr_o = dst_addr_out;
    assign data_o     = data_out;
    assign w_en       = memory_write_mod;
    
    always @(*)
    begin
        dst_addr_out     <= dst_addr_i;
        data_out         <= data_i;
        memory_write_mod <= !clk;
    end
    
    // always @(posedge clk)
    //     memory_write_mod <= 0;
    
    initial
        $monitor($time, "\t [WB] dst_addr_i = %d, data_i = %b, dst_addr_o = %d, data_o = %b, w_en = %b", dst_addr_i, data_i, dst_addr_o, data_o, w_en);
    
endmodule

AZ8/add_sub_comp.v
module AS_C (a,
             b,
             asn,
             res);
    
    parameter PART_LEN = 8;
    input asn;
    input signed [2*PART_LEN-1:0] a,b;
    output signed [2*PART_LEN-1:0]res;
    
    
    wire signed [PART_LEN-1:0]ra = a[2*PART_LEN-1:PART_LEN];
    wire signed [PART_LEN-1:0]rb = b[2*PART_LEN-1:PART_LEN];
    
    wire signed [PART_LEN-1:0]ia = a[PART_LEN-1:0];
    wire signed [PART_LEN-1:0]ib = b[PART_LEN-1:0];
    
    wire signed [PART_LEN:0]rr = (asn) ? ra + rb : ra - rb;
    wire signed [PART_LEN:0]ir = (asn) ? ia + ib : ia - ib;
    
    assign res = { rr[PART_LEN-1:0],ir[PART_LEN-1:0] };
        
    
endmodule

AZ8/mul_comp.v
module MUL_C(a,
             b,
             res);
    
    parameter PART_LEN = 8;
    input signed [2*PART_LEN-1:0] a,b;
    output signed [2*PART_LEN-1:0]res;
    
    
    wire signed [PART_LEN-1:0]ra = a[2*PART_LEN-1:PART_LEN];
    wire signed [PART_LEN-1:0]rb = b[2*PART_LEN-1:PART_LEN];
    
    wire signed [PART_LEN-1:0]ia = a[PART_LEN-1:0];
    wire signed [PART_LEN-1:0]ib = b[PART_LEN-1:0];
    
    wire signed [PART_LEN:0]rr = ra*rb - ia*ib;
    wire signed [PART_LEN:0]ir = ra*ib + rb*ia;
    
    assign res = {rr[PART_LEN-1:0], ir[PART_LEN-1:0]};
    
endmodule

AZ8/ALU.v
`define OPP_ASN 1
`define OPP_MUL 0

module ALU (clk,
            a,
            b,
            res,
            control_sig);
    parameter PART_LEN = 8;
    
    input [2*PART_LEN-1:0]a,b;
    output reg [2*PART_LEN-1:0]res;
    input clk,rstn;
    input [1:0]control_sig;
    
    
    wire asn = control_sig[0];
    wire opp = control_sig[1];
    
    wire [2*PART_LEN-1:0]res_as,res_mul;
    wire rstn = opp&asn;
    
    MUL_C #(.PART_LEN(PART_LEN))mulc(
    .a(a),
    .b(b),
    .res(res_as)
    );
    
    AS_C #(.PART_LEN(PART_LEN)) asc(
    .a(a),
    .b(b),
    .asn(asn),
    .res(res_mul));
    
    
    always @(posedge clk or negedge rstn)
    begin
        if (!rstn) begin
            res <= 0;
            end else begin
            case (opp)
                `OPP_ASN:
                res <= res_as;
                `OPP_MUL:
                res <= res_mul;
            endcase
            $display($time, "\t a=%b, b=%b, res = %b", a, b, res);
        end
    end
    
endmodule

AZ8/mem.v
module MEMORY_UNIT (r_addr1,
                    r_addr2,
                    w_addr,
                    r_en,
                    w_en,
                    data_out1,
                    data_out2,
                    data_in,
                    clk);
    
    parameter ADDR_LEN  = 5;
    parameter WORD_SIZE = 32;
    parameter MEM_SIZE  = 32;
    
    
    input [ADDR_LEN-1:0]r_addr1,r_addr2,w_addr;
    input r_en,w_en,clk;
    
    input [WORD_SIZE-1:0]data_in;
    output [WORD_SIZE-1:0]data_out1,data_out2;
    
    reg [WORD_SIZE-1:0] mem [MEM_SIZE-1:0];
    
    reg [WORD_SIZE-1:0] data_o1,data_o2;
    
    
    assign data_out1 = (r_en) ? mem[r_addr1] : data_out1;
    assign data_out2 = (r_en) ? mem[r_addr2] : data_out2;
    
    always @(posedge w_en)
    begin
        if (w_en) begin
            mem[w_addr] <= data_in;
        end
    end
    
endmodule

AZ8/ID.v
module ID (clk,
           inst,
           rstn,
           oper1,
           oper2,
           dest,
           alu_sig,
           mem_read);
    
    parameter INST_LEN  = 17;
    parameter WORD_SIZE = 32;
    parameter MEM_SIZE  = 32;
    parameter ADDR_LEN  = 5;
    
    input clk, rstn;
    input [INST_LEN-1:0] inst;
    output reg mem_read;
    output [ADDR_LEN-1:0] oper1, oper2, dest;
    output [1:0] alu_sig;
    
    assign alu_sig = inst[INST_LEN-1 : INST_LEN-2];
    assign oper1   = inst[3*ADDR_LEN-1 : 2*ADDR_LEN];
    assign oper2   = inst[2*ADDR_LEN-1 : ADDR_LEN];
    assign dest    = inst[ADDR_LEN-1 : 0];
    
    
    always @(posedge clk or negedge rstn) begin
        if (!rstn) begin
            // alu_sig  = 0;
            // oper1    = 0;
            // oper2    = 0;
            // dest     = 0;
            mem_read = 0;
        end
        else begin
            // alu_sig  = inst[INST_LEN-1 : INST_LEN-2];
            // oper1    = inst[3*ADDR_LEN-1 : 2*ADDR_LEN];
            // oper2    = inst[2*ADDR_LEN-1 : ADDR_LEN];
            // dest     = inst[ADDR_LEN-1 : 0];
            mem_read = 1;
            
            $display($time, "\t inst = %b, oper1 = %b, oper2 = %b, dest = %b, mem_read = %b, alu_sig = %b",inst, oper1, oper2, dest, mem_read, alu_sig);
        end
    end
    
    always @(negedge clk) begin
        if (!rstn) begin
            // alu_sig = 0;
            // oper1   = 0;
            // oper2   = 0;
            // dest    = 0;
        end
        mem_read = 0;
    end
    
endmodule

AZ8/IF.v
module IF (clk,
           rstn,
           inst);
    parameter INST_CAP = 5;
    parameter INST_LEN = 17;
    
    input clk, rstn;
    output reg[INST_LEN-1:0] inst;
    
    reg [INST_LEN-1:0] inst_mem [INST_CAP-1:0];
    reg[$clog2(INST_CAP):0] pc;
    
    always @(posedge clk or negedge rstn) begin
        if (!rstn) begin
            pc = 0;
        end
        else begin
            if (pc < INST_CAP) begin
                $display($time, "\t inst(%d):%b", pc, inst_mem[pc]);
                inst = inst_mem[pc];
                pc   = pc + 1;
            end
        end
    end
    
endmodule

AZ8/pipeline_processor.v
module PIPELINE(clk,
                rstn);
    
    parameter PART_LEN  = 16;
    parameter WORD_SIZE = 32;
    parameter ADDR_LEN  = 5;
    parameter MEM_SIZE  = 32;
    parameter INST_LEN  = 17;
    parameter INST_CAP  = 5;
    
    input clk, rstn;
    wire w_en, r_en;
    wire [INST_LEN-1:0] inst;
    wire [ADDR_LEN-1:0] r_addr1, r_addr2, w_addr, id_dest_addr;
    wire [1:0] alu_sig;
    wire [WORD_SIZE-1:0] res, wb_data_out, data_out1, data_out2;
    reg [ADDR_LEN-1:0] dst_addr_buffer, dst_addr;
    
    always @(posedge clk)
    begin
        dst_addr_buffer <= id_dest_addr;
        dst_addr        <= dst_addr_buffer;
    end
    
    IF #(.INST_LEN(INST_LEN), .INST_CAP(INST_CAP)) ifm (
    .clk(clk),
    .rstn(rstn),
    .inst(inst)
    );
    
    ID #(.INST_LEN(INST_LEN), .MEM_SIZE(MEM_SIZE), .WORD_SIZE(WORD_SIZE), .ADDR_LEN(ADDR_LEN)) idm (
    .clk(clk),
    .inst(inst),
    .rstn(rstn),
    .oper1(r_addr1),
    .oper2(r_addr2),
    .dest(id_dest_addr),
    .mem_read(r_en),
    .alu_sig(alu_sig)
    );
    
    MEMORY_UNIT #(.ADDR_LEN(ADDR_LEN),.WORD_SIZE(WORD_SIZE),.MEM_SIZE(MEM_SIZE))memory(
    .r_addr1(r_addr1),
    .r_addr2(r_addr2),
    .w_addr(w_addr),
    .w_en(w_en),
    .r_en(r_en),
    .data_out1(data_out1),
    .data_out2(data_out2),
    .data_in(wb_data_out),
    .clk(clk));
    
    ALU #(.PART_LEN(PART_LEN))alu (
    .clk(clk),
    .a(data_out1),
    .b(data_out2),
    .res(res),
    .control_sig(alu_sig)
    );
    
    WB #(.ADDR_LEN(ADDR_LEN),.WORD_SIZE(WORD_SIZE))wbm(
    .dst_addr_i(dst_addr),
    .data_i(res),
    .clk(clk),
    .dst_addr_o(w_addr),
    .data_o(wb_data_out),
    .w_en(w_en)
    );
    
endmodule

AZ8/testbench.v
module testbench();
    
    parameter PART_LEN  = 16;
    parameter WORD_SIZE = 32;
    parameter ADDR_LEN  = 5;
    parameter MEM_SIZE  = 32;
    parameter INST_LEN  = 17;
    parameter INST_CAP  = 5;
    parameter clk_c     = 10;
    
    reg clk, rstn;
    
    PIPELINE #(
    .PART_LEN(PART_LEN),
    .WORD_SIZE(WORD_SIZE),
    .ADDR_LEN(ADDR_LEN),
    .MEM_SIZE(MEM_SIZE),
    .INST_LEN(INST_LEN),
    .INST_CAP(INST_CAP)
    ) pipe (
    clk,
    rstn
    );
    
    
    initial begin
        $dumpfile("report/waveform.vcd");
        $dumpvars(0,pipe);
    end
    
    initial begin
        clk         = 0;
        forever clk = #(clk_c/2) ~clk;
    end
    
    initial begin
        $readmemb("memory.mem", pipe.memory.mem, 0, MEM_SIZE-1);
        $readmemb("inst_test1.mem", pipe.ifm.inst_mem, 0, INST_CAP-1);
    end
    
    initial begin
        rstn = 0;
        #clk_c
        rstn = 1;
        #(10*clk_c);
        $writememb("report/result.mem", pipe.memory.mem);
        $finish;
    end
    
    // initial
        // $monitor($time, "\t pipe.memory.mem[0]=%b",pipe.memory.mem[0]);
    
endmodule

AZ8/report/waveform.vcd
$date
	Wed May  5 16:41:01 2021
$end
$version
	Icarus Verilog
$end
$timescale
	1s
$end
$scope module testbench $end
$scope module pipe $end
$var wire 1 ! clk $end
$var wire 1 " rstn $end
$var wire 32 # wb_data_out [31:0] $end
$var wire 1 $ w_en $end
$var wire 5 % w_addr [4:0] $end
$var wire 32 & res [31:0] $end
$var wire 1 ' r_en $end
$var wire 5 ( r_addr2 [4:0] $end
$var wire 5 ) r_addr1 [4:0] $end
$var wire 17 * inst [16:0] $end
$var wire 5 + id_dest_addr [4:0] $end
$var wire 32 , data_out2 [31:0] $end
$var wire 32 - data_out1 [31:0] $end
$var wire 2 . alu_sig [1:0] $end
$var reg 5 / dst_addr [4:0] $end
$var reg 5 0 dst_addr_buffer [4:0] $end
$scope module alu $end
$var wire 1 ! clk $end
$var wire 1 1 rstn $end
$var wire 32 2 res_mul [31:0] $end
$var wire 32 3 res_as [31:0] $end
$var wire 1 4 opp $end
$var wire 2 5 control_sig [1:0] $end
$var wire 32 6 b [31:0] $end
$var wire 1 7 asn $end
$var wire 32 8 a [31:0] $end
$var reg 32 9 res [31:0] $end
$scope module asc $end
$var wire 1 7 asn $end
$var wire 17 : rr [16:0] $end
$var wire 32 ; res [31:0] $end
$var wire 16 < rb [15:0] $end
$var wire 16 = ra [15:0] $end
$var wire 17 > ir [16:0] $end
$var wire 16 ? ib [15:0] $end
$var wire 16 @ ia [15:0] $end
$var wire 32 A b [31:0] $end
$var wire 32 B a [31:0] $end
$upscope $end
$scope module mulc $end
$var wire 17 C rr [16:0] $end
$var wire 32 D res [31:0] $end
$var wire 16 E rb [15:0] $end
$var wire 16 F ra [15:0] $end
$var wire 17 G ir [16:0] $end
$var wire 16 H ib [15:0] $end
$var wire 16 I ia [15:0] $end
$var wire 32 J b [31:0] $end
$var wire 32 K a [31:0] $end
$upscope $end
$upscope $end
$scope module idm $end
$var wire 1 ! clk $end
$var wire 1 " rstn $end
$var wire 5 L oper2 [4:0] $end
$var wire 5 M oper1 [4:0] $end
$var wire 17 N inst [16:0] $end
$var wire 5 O dest [4:0] $end
$var wire 2 P alu_sig [1:0] $end
$var reg 1 ' mem_read $end
$upscope $end
$scope module ifm $end
$var wire 1 ! clk $end
$var wire 1 " rstn $end
$var reg 17 Q inst [16:0] $end
$var reg 4 R pc [3:0] $end
$upscope $end
$scope module memory $end
$var wire 1 ! clk $end
$var wire 5 S r_addr1 [4:0] $end
$var wire 5 T r_addr2 [4:0] $end
$var wire 1 ' r_en $end
$var wire 1 $ w_en $end
$var wire 5 U w_addr [4:0] $end
$var wire 32 V data_out2 [31:0] $end
$var wire 32 W data_out1 [31:0] $end
$var wire 32 X data_in [31:0] $end
$upscope $end
$scope module wbm $end
$var wire 1 ! clk $end
$var wire 32 Y data_i [31:0] $end
$var wire 32 Z data_o [31:0] $end
$var wire 5 [ dst_addr_i [4:0] $end
$var wire 5 \ dst_addr_o [4:0] $end
$var wire 1 $ w_en $end
$var reg 32 ] data_out [31:0] $end
$var reg 5 ^ dst_addr_out [4:0] $end
$var reg 1 _ memory_write_mod $end
$upscope $end
$upscope $end
$upscope $end
$enddefinitions $end
#0
$dumpvars
1_
bx ^
bx ]
bx \
bx [
bx Z
bx Y
bx X
bx W
bx V
bx U
bx T
bx S
b0 R
bx Q
bx P
bx O
bx N
bx M
bx L
bx K
bx J
bx I
bx H
bx G
bx F
bx E
bx D
bx C
bx B
bx A
bx @
bx ?
bx >
bx =
bx <
bx ;
bx :
bx 9
bx 8
x7
bx 6
bx 5
x4
bx 3
bx 2
x1
bx 0
bx /
bx .
bx -
bx ,
bx +
bx *
bx )
bx (
0'
bx &
bx %
1$
bx #
0"
0!
$end
#5
0$
0_
1!
#10
1$
1_
0!
1"
#15
b0 &
b0 9
b0 Y
0$
0_
b1000000000000000100 2
b1000000000000000100 ;
b1000 3
b1000 D
b100 >
b100 :
b0 C
b1000 G
b10 H
b10 E
b10 ?
b10 <
b10 I
b10 F
b10 @
b10 =
01
b100000000000000010 ,
b100000000000000010 6
b100000000000000010 A
b100000000000000010 J
b100000000000000010 V
b100000000000000010 -
b100000000000000010 8
b100000000000000010 B
b100000000000000010 K
b100000000000000010 W
04
17
b1 +
b1 O
b1 (
b1 L
b1 T
b1 )
b1 M
b1 S
b1 .
b1 5
b1 P
b1 R
b1000010000100001 *
b1000010000100001 N
b1000010000100001 Q
1'
1!
#20
1$
1_
b0 #
b0 X
b0 Z
b0 ]
0'
0!
#25
0$
0_
b1 0
b0 2
b0 ;
b111000010 3
b111000010 D
b0 :
b0 >
b1111 I
b1111 F
b1111 @
b1111 =
b1111 H
b0 C
b111000010 G
b1111 E
b1111 ?
b1111 <
07
b11110000000000001111 -
b11110000000000001111 8
b11110000000000001111 B
b11110000000000001111 K
b11110000000000001111 W
b11110000000000001111 ,
b11110000000000001111 6
b11110000000000001111 A
b11110000000000001111 J
b11110000000000001111 V
b0 +
b0 O
b0 (
b0 L
b0 T
b0 )
b0 M
b0 S
b0 .
b0 5
b0 P
1'
b10 R
b0 *
b0 N
b0 Q
1!
#30
1$
1_
0'
0!
#35
b1 /
b1 [
b0 0
0$
0_
b11 R
1'
1!
#40
1$
1_
b1 %
b1 U
b1 \
b1 ^
0'
0!
#45
0$
0_
b0 /
b0 [
1'
b100 R
1!
#50
1$
1_
b0 %
b0 U
b0 \
b0 ^
0'
0!
#55
0$
0_
b0 3
b0 D
b0 I
b0 F
b0 @
b0 =
b0 H
b0 C
b0 G
b0 E
b0 ?
b0 <
b0 -
b0 8
b0 B
b0 K
b0 W
b0 ,
b0 6
b0 A
b0 J
b0 V
b101 R
1'
1!
#60
1$
1_
0'
0!
#65
0$
0_
1'
1!
#70
1$
1_
0'
0!
#75
0$
0_
1'
1!
#80
1$
1_
0'
0!
#85
0$
0_
1'
1!
#90
1$
1_
0'
0!
#95
0$
0_
1'
1!
#100
1$
1_
0'
0!
#105
0$
0_
1'
1!
#110
1$
1_
0'
0!
