AZ8/WB.v
module WB (dst_addr_i,
           data_i,
           clk,
           dst_addr_o,
           data_o,
           w_en);
    
    parameter ADDR_LEN  = 5;
    parameter WORD_SIZE = 32;
    
    input [ADDR_LEN-1:0]dst_addr_i;
    input [WORD_SIZE-1:0]data_i;
    input clk;
    
    output [ADDR_LEN-1:0]dst_addr_o;
    output [WORD_SIZE-1:0]data_o;
    output w_en;
    
    reg [ADDR_LEN-1:0]dst_addr_out;
    reg [WORD_SIZE-1:0]data_out;
    reg memory_write_mod;
    
    assign dst_addr_o = dst_addr_out;
    assign data_o     = data_out;
    assign w_en       = memory_write_mod;
    
    always @(*)
    begin
        dst_addr_out     <= dst_addr_i;
        data_out         <= data_i;
        memory_write_mod <= !clk;
    end
    
    // always @(posedge clk)
    //     memory_write_mod <= 0;
    
    initial
        $monitor($time, "\t [WB] dst_addr_i = %d, data_i = %b, dst_addr_o = %d, data_o = %b, w_en = %b", dst_addr_i, data_i, dst_addr_o, data_o, w_en);
    
endmodule

AZ8/add_sub_comp.v
module AS_C (a,
             b,
             asn,
             res);
    
    parameter PART_LEN = 8;
    input asn;
    input signed [2*PART_LEN-1:0] a,b;
    output signed [2*PART_LEN-1:0]res;
    
    
    wire signed [PART_LEN-1:0]ra = a[2*PART_LEN-1:PART_LEN];
    wire signed [PART_LEN-1:0]rb = b[2*PART_LEN-1:PART_LEN];
    
    wire signed [PART_LEN-1:0]ia = a[PART_LEN-1:0];
    wire signed [PART_LEN-1:0]ib = b[PART_LEN-1:0];
    
    wire signed [PART_LEN:0]rr = (asn) ? ra + rb : ra - rb;
    wire signed [PART_LEN:0]ir = (asn) ? ia + ib : ia - ib;
    
    assign res = { rr[PART_LEN-1:0],ir[PART_LEN-1:0] };
        
    
endmodule

AZ8/mul_comp.v
module MUL_C(a,
             b,
             res);
    
    parameter PART_LEN = 8;
    input signed [2*PART_LEN-1:0] a,b;
    output signed [2*PART_LEN-1:0]res;
    
    
    wire signed [PART_LEN-1:0]ra = a[2*PART_LEN-1:PART_LEN];
    wire signed [PART_LEN-1:0]rb = b[2*PART_LEN-1:PART_LEN];
    
    wire signed [PART_LEN-1:0]ia = a[PART_LEN-1:0];
    wire signed [PART_LEN-1:0]ib = b[PART_LEN-1:0];
    
    wire signed [PART_LEN:0]rr = ra*rb - ia*ib;
    wire signed [PART_LEN:0]ir = ra*ib + rb*ia;
    
    assign res = {rr[PART_LEN-1:0], ir[PART_LEN-1:0]};
    
endmodule

AZ8/ALU.v
`define OPP_ASN 1
`define OPP_MUL 0

module ALU (clk,
            a,
            b,
            res,
            control_sig);
    
    parameter PART_LEN = 8;
    
    input [2*PART_LEN-1:0]a,b;
    output [2*PART_LEN-1:0]res;
    input clk,rstn;
    input [1:0]control_sig;
    
    
    wire asn = control_sig[0];
    wire opp = control_sig[1];
    
    wire [2*PART_LEN-1:0]res_as,res_mul;
    wire rstn = opp&asn;
    
    MUL_C #(.PART_LEN(PART_LEN))mulc(
    .a(a),
    .b(b),
    .res(res_as)
    );
    
    AS_C #(.PART_LEN(PART_LEN)) asc(
    .a(a),
    .b(b),
    .asn(asn),
    .res(res_mul));
    
    assign res = (opp == `OPP_ASN) ? res_as: res_mul;
    
    // always @(*)
    // begin
    //     if (!rstn) begin
    //         res <= 0;
    //         end else begin
    //         case (opp)
    //             `OPP_ASN:
    //             res <= res_as;
    //             `OPP_MUL:
    //             res <= res_mul;
    //         endcase
    //     end
    // end
    
    initial
        $monitor($time, "\t [ALU] a = %b, b = %b, control = %b, res = %b", a, b, control_sig, res);
    
endmodule

AZ8/mem.v
module MEMORY_UNIT (r_addr1,
                    r_addr2,
                    w_addr,
                    r_en,
                    w_en,
                    data_out1,
                    data_out2,
                    data_in,
                    clk);
    
    parameter ADDR_LEN  = 5;
    parameter WORD_SIZE = 32;
    parameter MEM_SIZE  = 32;
    
    
    input [ADDR_LEN-1:0]r_addr1,r_addr2,w_addr;
    input r_en,w_en,clk;
    
    input [WORD_SIZE-1:0]data_in;
    output reg [WORD_SIZE-1:0]data_out1,data_out2;
    
    reg [WORD_SIZE-1:0] mem [MEM_SIZE-1:0];
    
    reg [WORD_SIZE-1:0] data_o1,data_o2;
    
    always @(*)
    begin
        if (r_en) begin
            data_out1 <= mem[r_addr1];
            data_out2 <= mem[r_addr2];
        end
        if (w_en) begin
            mem[w_addr] <= data_in;
        end
        $display($time, "\t [MEM] r_en = %b, r_addr1 = %d, r_addr2 = %d, w_addr = %d, w_en = %b, data_in = %b, data_out1 = %b, data_out2 = %b", r_en, r_addr1, r_addr2, w_addr, w_en, data_in, data_out1, data_out2);
    end
    
endmodule

AZ8/ID.v
module ID (clk,
           inst,
           rstn,
           oper1,
           oper2,
           dest,
           alu_sig,
           mem_read);
    
    parameter INST_LEN  = 17;
    parameter WORD_SIZE = 32;
    parameter MEM_SIZE  = 32;
    parameter ADDR_LEN  = 5;
    
    input clk, rstn;
    input [INST_LEN-1:0] inst;
    output mem_read;
    output [ADDR_LEN-1:0] oper1, oper2, dest;
    output [1:0] alu_sig;
    
    assign alu_sig  = inst[INST_LEN-1 : INST_LEN-2];
    assign oper1    = inst[3*ADDR_LEN-1 : 2*ADDR_LEN];
    assign oper2    = inst[2*ADDR_LEN-1 : ADDR_LEN];
    assign dest     = inst[ADDR_LEN-1 : 0];
    assign mem_read = clk;
    // always @(posedge clk) begin
    // end
    
    always @(posedge clk or negedge rstn) begin
        // if (!rstn) begin
        //     alu_sig  <= 0;
        //     oper1    <= 0;
        //     oper2    <= 0;
        //     dest     <= 0;
        //     mem_read <= 0;
        // end
        // else begin
        //     alu_sig  <= inst[INST_LEN-1 : INST_LEN-2];
        //     oper1    <= inst[3*ADDR_LEN-1 : 2*ADDR_LEN];
        //     oper2    <= inst[2*ADDR_LEN-1 : ADDR_LEN];
        //     dest     <= inst[ADDR_LEN-1 : 0];
        //     mem_read <= 1;
        $display($time, "\t [ID] inst = %b, oper1 = %b, oper2 = %b, dest = %b, mem_read = %b, alu_sig = %b",inst, oper1, oper2, dest, mem_read, alu_sig);
        // end
    end
    
    always @(negedge clk) begin
        // if (!rstn) begin
        //     alu_sig <= 0;
        //     oper1   <= 0;
        //     oper2   <= 0;
        //     dest    <= 0;
        // end
        // mem_read <= 0;
        // $display($time, "\t [ID] inst = %b, oper1 = %b, oper2 = %b, dest = %b, mem_read = %b, alu_sig = %b",inst, oper1, oper2, dest, mem_read, alu_sig);
    end
    
    // initial
    //     $monitor($time, "\t [ID] clk = %b, inst = %b, oper1 = %b, oper2 = %b, dest = %b, mem_read = %b, alu_sig = %b" , clk, inst, oper1, oper2, dest, mem_read, alu_sig);
    
    
endmodule

AZ8/IF.v
module IF (clk,
           rstn,
           inst);
    
    parameter INST_CAP = 5;
    parameter INST_LEN = 17;
    
    input clk, rstn;
    output reg[INST_LEN-1:0] inst;
    
    reg [INST_LEN-1:0] inst_mem [INST_CAP-1:0];
    reg[$clog2(INST_CAP):0] pc;
    
    always @(posedge clk or negedge rstn) begin
        if (!rstn) begin
            pc <= 0;
        end
        else begin
            if (pc < INST_CAP) begin
                $display($time, "\t [IF] inst[%d]:%b", pc, inst_mem[pc]);
                inst <= inst_mem[pc];
                pc   <= pc + 1;
            end
        end
    end
    
endmodule

AZ8/pipeline_processor.v
module PIPELINE(clk,
                rstn);
    
    parameter PART_LEN  = 16;
    parameter WORD_SIZE = 32;
    parameter ADDR_LEN  = 5;
    parameter MEM_SIZE  = 32;
    parameter INST_LEN  = 17;
    parameter INST_CAP  = 5;
    
    input clk, rstn;
    wire w_en, r_en;
    wire [INST_LEN-1:0] inst;
    wire [ADDR_LEN-1:0] r_addr1, r_addr2, w_addr, id_dest_addr;
    wire [1:0] alu_sig;
    wire [WORD_SIZE-1:0] res, wb_data_out, data_out1, data_out2;
    
    reg id_mem_r_en, wb_mem_w_en;
    reg [1:0] id_alu_sig, alu_sig_buff;
    reg [ADDR_LEN-1:0] dst_addr_buff, dst_addr, id_mem_r_addr1, id_mem_r_addr2, wb_mem_w_addr;
    reg [WORD_SIZE-1:0] alu_wb_buff_res, wb_mem_data_out, mem_alu_data_out1, mem_alu_data_out2;
    reg [INST_LEN-1:0] if_id_buff_inst;
    
    always @(posedge clk)
    begin
        dst_addr_buff <= id_dest_addr;
        dst_addr      <= dst_addr_buff;
        
        if_id_buff_inst   <= inst;
        id_mem_r_addr1    <= r_addr1;
        id_mem_r_addr2    <= r_addr2;
        id_mem_r_en       <= r_en;
        alu_sig_buff      <= alu_sig;
        id_alu_sig        <= alu_sig_buff;
        mem_alu_data_out1 <= data_out1;
        mem_alu_data_out2 <= data_out2;
        alu_wb_buff_res   <= res;
        wb_mem_w_addr     <= w_addr;
        wb_mem_w_en       <= w_en;
        wb_mem_data_out   <= wb_data_out;
        
    end
    
    IF #(.INST_LEN(INST_LEN), .INST_CAP(INST_CAP)) ifm (
    .clk(clk),
    .rstn(rstn),
    .inst(inst)
    );
    
    ID #(.INST_LEN(INST_LEN), .MEM_SIZE(MEM_SIZE), .WORD_SIZE(WORD_SIZE), .ADDR_LEN(ADDR_LEN)) idm (
    .clk(clk),
    .inst(if_id_buff_inst),
    .rstn(rstn),
    .oper1(r_addr1),
    .oper2(r_addr2),
    .dest(id_dest_addr),
    .mem_read(r_en),
    .alu_sig(alu_sig)
    );
    
    MEMORY_UNIT #(.ADDR_LEN(ADDR_LEN),.WORD_SIZE(WORD_SIZE),.MEM_SIZE(MEM_SIZE))memory(
    .r_addr1(id_mem_r_addr1),
    .r_addr2(id_mem_r_addr2),
    .w_addr(w_addr),
    .w_en(w_en),
    .r_en(id_mem_r_en),
    .data_in(wb_data_out),
    .data_out1(data_out1),
    .data_out2(data_out2),
    .clk(clk)
    );
    
    ALU #(.PART_LEN(PART_LEN))alu (
    .clk(clk),
    .a(mem_alu_data_out1),
    .b(mem_alu_data_out2),
    .control_sig(id_alu_sig),
    .res(res)
    );
    
    WB #(.ADDR_LEN(ADDR_LEN),.WORD_SIZE(WORD_SIZE))wbm(
    .dst_addr_i(dst_addr),
    .data_i(res),
    .clk(clk),
    .dst_addr_o(w_addr),
    .data_o(wb_data_out),
    .w_en(w_en)
    );
    
endmodule

AZ8/testbench.v
module testbench();
    
    parameter PART_LEN  = 16;
    parameter WORD_SIZE = 32;
    parameter ADDR_LEN  = 5;
    parameter MEM_SIZE  = 32;
    parameter INST_LEN  = 17;
    parameter INST_CAP  = 5;
    parameter clk_c     = 10;
    
    reg clk, rstn;
    
    PIPELINE #(
    .PART_LEN(PART_LEN),
    .WORD_SIZE(WORD_SIZE),
    .ADDR_LEN(ADDR_LEN),
    .MEM_SIZE(MEM_SIZE),
    .INST_LEN(INST_LEN),
    .INST_CAP(INST_CAP)
    ) pipe (
    .clk(clk),
    .rstn(rstn)
    );
    
    
    initial begin
        $dumpfile("report/waveform.vcd");
        $dumpvars(0,pipe);
    end
    
    initial begin
        clk         = 0;
        forever clk = #(clk_c/2) ~clk;
    end
    
    initial begin
        $readmemb("memory.mem", pipe.memory.mem, 0, MEM_SIZE-1);
        $readmemb("inst_test1.mem", pipe.ifm.inst_mem, 0, INST_CAP-1);
    end
    
    initial begin
        rstn = 0;
        #clk_c
        rstn = 1;
        #(10*clk_c);
        $writememb("report/result.mem", pipe.memory.mem);
        $finish;
    end
    
    // initial
        // $monitor($time, "\t pipe.memory.mem[0]=%b",pipe.memory.mem[0]);
    
endmodule

AZ8/report/waveform.vcd
$date
	Wed May  5 19:24:24 2021
$end
$version
	Icarus Verilog
$end
$timescale
	1s
$end
$scope module testbench $end
$scope module pipe $end
$var wire 1 ! clk $end
$var wire 1 " rstn $end
$var wire 32 # wb_data_out [31:0] $end
$var wire 1 $ w_en $end
$var wire 5 % w_addr [4:0] $end
$var wire 32 & res [31:0] $end
$var wire 1 ' r_en $end
$var wire 5 ( r_addr2 [4:0] $end
$var wire 5 ) r_addr1 [4:0] $end
$var wire 17 * inst [16:0] $end
$var wire 5 + id_dest_addr [4:0] $end
$var wire 32 , data_out2 [31:0] $end
$var wire 32 - data_out1 [31:0] $end
$var wire 2 . alu_sig [1:0] $end
$var reg 2 / alu_sig_buff [1:0] $end
$var reg 32 0 alu_wb_buff_res [31:0] $end
$var reg 5 1 dst_addr [4:0] $end
$var reg 5 2 dst_addr_buff [4:0] $end
$var reg 2 3 id_alu_sig [1:0] $end
$var reg 5 4 id_mem_r_addr1 [4:0] $end
$var reg 5 5 id_mem_r_addr2 [4:0] $end
$var reg 1 6 id_mem_r_en $end
$var reg 17 7 if_id_buff_inst [16:0] $end
$var reg 32 8 mem_alu_data_out1 [31:0] $end
$var reg 32 9 mem_alu_data_out2 [31:0] $end
$var reg 32 : wb_mem_data_out [31:0] $end
$var reg 5 ; wb_mem_w_addr [4:0] $end
$var reg 1 < wb_mem_w_en $end
$scope module alu $end
$var wire 32 = a [31:0] $end
$var wire 32 > b [31:0] $end
$var wire 1 ! clk $end
$var wire 2 ? control_sig [1:0] $end
$var wire 1 @ rstn $end
$var wire 32 A res_mul [31:0] $end
$var wire 32 B res_as [31:0] $end
$var wire 32 C res [31:0] $end
$var wire 1 D opp $end
$var wire 1 E asn $end
$scope module asc $end
$var wire 32 F a [31:0] $end
$var wire 1 E asn $end
$var wire 32 G b [31:0] $end
$var wire 17 H rr [16:0] $end
$var wire 32 I res [31:0] $end
$var wire 16 J rb [15:0] $end
$var wire 16 K ra [15:0] $end
$var wire 17 L ir [16:0] $end
$var wire 16 M ib [15:0] $end
$var wire 16 N ia [15:0] $end
$upscope $end
$scope module mulc $end
$var wire 32 O a [31:0] $end
$var wire 32 P b [31:0] $end
$var wire 17 Q rr [16:0] $end
$var wire 32 R res [31:0] $end
$var wire 16 S rb [15:0] $end
$var wire 16 T ra [15:0] $end
$var wire 17 U ir [16:0] $end
$var wire 16 V ib [15:0] $end
$var wire 16 W ia [15:0] $end
$upscope $end
$upscope $end
$scope module idm $end
$var wire 1 ! clk $end
$var wire 17 X inst [16:0] $end
$var wire 1 ' mem_read $end
$var wire 1 " rstn $end
$var wire 5 Y oper2 [4:0] $end
$var wire 5 Z oper1 [4:0] $end
$var wire 5 [ dest [4:0] $end
$var wire 2 \ alu_sig [1:0] $end
$upscope $end
$scope module ifm $end
$var wire 1 ! clk $end
$var wire 1 " rstn $end
$var reg 17 ] inst [16:0] $end
$var reg 4 ^ pc [3:0] $end
$upscope $end
$scope module memory $end
$var wire 1 ! clk $end
$var wire 5 _ r_addr1 [4:0] $end
$var wire 5 ` r_addr2 [4:0] $end
$var wire 1 6 r_en $end
$var wire 1 $ w_en $end
$var wire 5 a w_addr [4:0] $end
$var wire 32 b data_in [31:0] $end
$var reg 32 c data_out1 [31:0] $end
$var reg 32 d data_out2 [31:0] $end
$upscope $end
$scope module wbm $end
$var wire 1 ! clk $end
$var wire 32 e data_i [31:0] $end
$var wire 32 f data_o [31:0] $end
$var wire 5 g dst_addr_i [4:0] $end
$var wire 5 h dst_addr_o [4:0] $end
$var wire 1 $ w_en $end
$var reg 32 i data_out [31:0] $end
$var reg 5 j dst_addr_out [4:0] $end
$var reg 1 k memory_write_mod $end
$upscope $end
$upscope $end
$upscope $end
$enddefinitions $end
#0
$dumpvars
1k
bx j
bx i
bx h
bx g
bx f
bx e
bx d
bx c
bx b
bx a
bx `
bx _
b0 ^
bx ]
bx \
bx [
bx Z
bx Y
bx X
bx W
bx V
bx U
bx T
bx S
bx R
bx Q
bx P
bx O
bx N
bx M
bx L
bx K
bx J
bx I
bx H
bx G
bx F
xE
xD
bx C
bx B
bx A
x@
bx ?
bx >
bx =
x<
bx ;
bx :
bx 9
bx 8
bx 7
x6
bx 5
bx 4
bx 3
bx 2
bx 1
bx 0
bx /
bx .
bx -
bx ,
bx +
bx *
bx )
bx (
0'
bx &
bx %
1$
bx #
0"
0!
$end
#5
0$
0k
1<
16
1'
1!
#10
1$
1k
0'
0!
1"
#15
b1 ^
b1000010000100001 *
b1000010000100001 ]
0$
0k
1'
1!
#20
1$
1k
0'
0!
#25
b1 .
b1 \
b1 )
b1 Z
b1 (
b1 Y
b1 +
b1 [
b10 ^
b0 *
b0 ]
0$
0k
b1000010000100001 7
b1000010000100001 X
1'
1!
#30
1$
1k
0'
0!
#35
b100000000000000010 ,
b100000000000000010 d
b100000000000000010 -
b100000000000000010 c
b0 .
b0 \
b0 )
b0 Z
b0 (
b0 Y
b0 +
b0 [
b11 ^
0$
0k
b1 /
b1 5
b1 `
b1 4
b1 _
b0 7
b0 X
b1 2
1'
1!
#40
1$
1k
0'
0!
#45
b1000000000000000100 #
b1000000000000000100 b
b1000000000000000100 f
b1000000000000000100 i
b11110000000000001111 ,
b11110000000000001111 d
b11110000000000001111 -
b11110000000000001111 c
b1 %
b1 a
b1 h
b1 j
b1000000000000000100 &
b1000000000000000100 C
b1000000000000000100 e
b1000000000000000100 A
b1000000000000000100 I
b1000 B
b1000 R
b100 H
b100 L
0@
b10 J
b10 M
b0 Q
b1000 U
b10 S
b10 V
b10 K
b10 N
b10 T
b10 W
1E
0D
b100 ^
0$
0k
b100000000000000010 9
b100000000000000010 >
b100000000000000010 G
b100000000000000010 P
b100000000000000010 8
b100000000000000010 =
b100000000000000010 F
b100000000000000010 O
b1 3
b1 ?
b0 /
b0 5
b0 `
b0 4
b0 _
b1 1
b1 g
b0 2
1'
1!
#50
1$
1k
0'
0!
#55
b0 #
b0 b
b0 f
b0 i
b0 %
b0 a
b0 h
b0 j
b0 &
b0 C
b0 e
b0 A
b0 I
b111000010 B
b111000010 R
b0 H
b0 L
b1111 J
b1111 M
b1111 S
b1111 V
b1111 K
b1111 N
b1111 T
b0 Q
b111000010 U
b1111 W
0E
b101 ^
0$
0k
b1000000000000000100 :
b1 ;
b1000000000000000100 0
b11110000000000001111 9
b11110000000000001111 >
b11110000000000001111 G
b11110000000000001111 P
b11110000000000001111 8
b11110000000000001111 =
b11110000000000001111 F
b11110000000000001111 O
b0 3
b0 ?
b0 1
b0 g
1'
1!
#60
b0 ,
b0 d
b0 -
b0 c
1$
1k
0'
0!
#65
b0 B
b0 R
b0 J
b0 M
b0 S
b0 V
b0 K
b0 N
b0 T
b0 Q
b0 U
b0 W
0$
0k
b0 :
b0 ;
b0 0
b0 9
b0 >
b0 G
b0 P
b0 8
b0 =
b0 F
b0 O
1'
1!
#70
1$
1k
0'
0!
#75
0$
0k
1'
1!
#80
1$
1k
0'
0!
#85
0$
0k
1'
1!
#90
1$
1k
0'
0!
#95
0$
0k
1'
1!
#100
1$
1k
0'
0!
#105
0$
0k
1'
1!
#110
1$
1k
0'
0!
