AZ10/stack.v
module Stack (rstn,
              data_in,
              push,
              pop,
              clk,
              data_out,
              full,
              empty);
    
    parameter STACK_DEPTH = 8;
    parameter WORD_LEN    = 8;
    
    input wire rstn, push, pop, clk;
    input wire[WORD_LEN-1:0] data_in;
    output full, empty;
    output reg [WORD_LEN-1:0] data_out;
    
    reg[$clog2(STACK_DEPTH):0] stack_ptr;
    reg[WORD_LEN-1:0] memory [0:STACK_DEPTH-1];
    
    assign empty = (stack_ptr == 0) ? 1'b1 : 1'b0;
    assign full  = (stack_ptr == STACK_DEPTH) ? 1'b1 : 1'b0;
    
    // stack reset
    task reset_memory;
        integer i;
        begin
            for (i = 0; i < STACK_DEPTH;i++) begin
                memory[i] = {WORD_LEN{1'b0}};
            end
            stack_ptr = 0;
        end
    endtask
    
    always @(posedge clk or negedge rstn) begin
        if (rstn) begin
            reset_memory;
        end
        else begin
            // pushing into stack
            if (push && !pop && !full) begin
                memory[stack_ptr] = data_in;
                stack_ptr         = stack_ptr + 1;
            end
            // pop from stack
            if (pop && !push && !empty) begin
                data_out  = memory[stack_ptr - 1];
                stack_ptr = stack_ptr - 1;
            end
        end
    end
    
    initial
        $monitor($time, "\t [STACK] rstn = %b, data_in = %d, push = %b, pop = %b, data_out = %d, full = %b, empty = %b", rstn, data_in, push, pop, data_out, full, empty);
    
endmodule

AZ10/memory.v
module MEMORY (addr,
               r_en,
               w_en,
               data_out,
               data_in,
               clk);
    
    parameter ADDR_LEN  = 8;
    parameter WORD_LEN = 8;
    parameter MEM_SIZE  = 256;
    
    
    input [ADDR_LEN-1:0] addr;
    input r_en,w_en,clk;
    
    input [WORD_LEN-1:0]data_in;
    output reg [WORD_LEN-1:0]data_out;
    
    reg [WORD_LEN-1:0] mem [MEM_SIZE-1:0];
    
    reg [WORD_LEN-1:0] data_o1,data_o2;
    
    always @(*) //todo: refactor
    begin
        if (r_en) begin
            data_out <= mem[addr];
        end
        if (w_en) begin
            mem[addr] <= data_in;
        end
    end
    
    initial
        $monitor($time, "\t [MEMORY] r_en = %b, addr = %d, w_en = %b, data_in = %b, data_out = %b", r_en, addr, w_en, data_in, data_out);
    
endmodule

AZ10/PC.v
`define INIT    00
`define POP     01
`define NXTL      10
`define BR      11

module PC (control_bus,
           clk,
           rstn,
           en,
           pc,
           z_flag,
           s_flag,
           stk_pop,
           stk_data_out);
    
    parameter INST_CAP = 20;
    parameter DATA_LEN = 8;
    
    input clk, en, rstn, z_flag, s_flag;
    input [3:0] control_bus;
    input [DATA_LEN-1:0] stk_data_out;
    output reg stk_pop;
    output reg [$clog2(INST_CAP):0] pc;
    
    wire[1:0] opc = {control_bus[2], control_bus[0]};
    wire branch   = (control_bus > 2 && control_bus < 6);
    
    reg [3:0]state;
    
    always @(posedge clk, negedge rstn) begin
        if (!rstn && !en) begin
            state   <= `INIT;
            stk_pop <= 1'bz;
            pc      <= 0;
        end
        else begin
            case(state)
                `INIT:
                begin
                    if (rstn) begin
                        if (en) begin
                            state <= (branch) ? `POP : `NXTL;
                        end
                        stk_pop <= 1'bz;
                    end
                end
                `POP:
                begin
                    stk_pop <= 1;
                    state   <= `BR;
                end
                `NXTL:
                begin
                    if (pc < INST_CAP - 1) begin
                        pc <= pc + 1;
                    end
                    state <= `INIT;
                end
                `BR:
                begin
                    if ((opc == 2'b01) || (opc == 2'b10 && z_flag) ||  (opc == 2'b11 && s_flag)) begin
                        pc <= stk_data_out;
                    end
                    state <= `INIT;
                end
            endcase
        end
    end
    
    initial
        $monitor($time, "\t [PC::%d] rstn = %b, en = %b, control_bus = %b, pc = %d, z_flag = %b, s_flag = %b, stk_pop = %b, stk_data_out = %d", state, rstn, en, control_bus, pc, z_flag, s_flag, stk_pop, stk_data_out);
    
endmodule

AZ10/WBPB.v
`define INIT    000
`define PUSH    001
`define POP     010
`define LOAD    011
`define STORE   100

module WBPB (control_bus,
             clk,
             en,
             rstn,
             addr_const,
             stk_data_in,
             stk_push,
             stk_pop,
             stk_data_out,
             mem_data_in,
             mem_addr,
             mem_r_en,
             mem_w_en,
             mem_data_out);
    
    parameter ADDR_LEN = 8;
    parameter DATA_LEN = 8;
    
    input clk, rstn, en;
    input [3:0] control_bus;
    input [DATA_LEN-1:0] stk_data_out, mem_data_out, addr_const;
    output reg [DATA_LEN-1:0] stk_data_in, mem_data_in;
    output reg [ADDR_LEN-1:0] mem_addr;
    output reg stk_push, stk_pop, mem_r_en, mem_w_en;
    
    wire [1:0] opc = control_bus[1:0];
    wire wbpb_en   = (en && control_bus < 3);
    
    reg [3:0]state;
    
    always @(posedge clk, negedge rstn) begin
        if (!rstn && !wbpb_en) begin
            state       <= `INIT;
            stk_data_in <= {DATA_LEN{1'bz}};
            stk_push    <= 1'bz;
            stk_pop     <= 1'bz;
            mem_data_in <= {DATA_LEN{1'bz}};
            mem_addr    <= {ADDR_LEN{1'bz}};
            mem_r_en    <= 1'bz;
            mem_w_en    <= 1'bz;
        end
        else begin
            case(state)
                `INIT:
                begin
                    if (rstn) begin
                        if (wbpb_en) begin
                            if (opc == 2'b00) begin
                                state <= `PUSH;
                            end
                            else if (opc == 2'b01) begin
                                state <= `LOAD;
                            end
                            else if (opc == 2'b10) begin
                                state <= `POP;
                            end
                        end
                        stk_data_in <= {DATA_LEN{1'bz}};
                        stk_push    <= 1'bz;
                        stk_pop     <= 1'bz;
                        mem_data_in <= {DATA_LEN{1'bz}};
                        mem_addr    <= {ADDR_LEN{1'bz}};
                        mem_r_en    <= 1'bz;
                        mem_w_en    <= 1'bz;
                    end
                end
                `PUSH:
                begin
                    stk_push    <= 1;
                    stk_data_in <= (opc == 2'b00) ? addr_const : mem_data_out;
                    state       <= `INIT;
                end
                `POP:
                begin
                    stk_pop <= 1;
                    state   <= `STORE;
                end
                `LOAD:
                begin
                    mem_r_en <= 1;
                    mem_w_en <= 0;
                    mem_addr <= addr_const;
                    state    <= `PUSH;
                end
                `STORE:
                begin
                    mem_w_en    <= 1;
                    mem_r_en    <= 0;
                    mem_data_in <= stk_data_out;
                    mem_addr    <= addr_const;
                    state       <= `INIT;
                end
            endcase
        end
    end
    
    initial
        $monitor($time, "\t [WBPB::%d] rstn = %b, control_bus = %b, addr_const = %d, stk_data_in = %d, stk_push = %b, stk_pop = %b, stk_data_out = %d, mem_data_in = %d, mem_addr = %d, mem_r_en = %b, mem_w_en = %b, mem_data_out = %d", state, rstn, control_bus, addr_const, stk_data_in, stk_push, stk_pop, stk_data_out, mem_data_in, mem_addr, mem_r_en, mem_w_en, mem_data_out);
    
endmodule

AZ10/ALU.v
`define INIT    0000
`define OP1_POP 0001
`define OP1_RCV 0010
`define OP2_POP 0011
`define OP2_RCV 0100
`define ALU     0101
`define ADD     0110
`define SUB     0111
`define PUSH    1000

module ALU (control_bus,
            clk,
            en,
            rstn,
            z_flag,
            s_flag,
            stk_data_in,
            stk_push,
            stk_pop,
            stk_data_out);
    
    parameter DATA_LEN = 8;
    
    input clk, rstn, en;
    input [3:0] control_bus;
    input [DATA_LEN-1:0] stk_data_out;
    output reg [DATA_LEN-1:0] stk_data_in;
    output reg stk_push, stk_pop;
    output z_flag, s_flag;
    
    wire asn      = control_bus[0];
    wire alu_en   = (en && control_bus[1] && control_bus[2]);
    assign s_flag = (res < 0);
    assign z_flag = (res == 0);
    
    reg [3:0]state;
    
    reg signed [DATA_LEN-1:0] op1, op2, res;
    
    always @(posedge clk, negedge rstn) begin
        if (!rstn && !alu_en) begin
            state       <= `INIT;
            stk_data_in <= {DATA_LEN{1'bz}};
            stk_push    <= 1'bz;
            stk_pop     <= 1'bz;
        end
        else begin
            case(state)
                `INIT:
                begin
                    if (rstn) begin
                        if (alu_en) begin
                            state <= `OP1_POP;
                        end
                        stk_data_in <= {DATA_LEN{1'bz}};
                        stk_push    <= 1'bz;
                        stk_pop     <= 1'bz;
                    end
                end
                `OP1_POP:
                begin
                    stk_pop <= 1;
                    state   <= `OP1_RCV;
                end
                `OP1_RCV:
                begin
                    stk_pop <= 0;
                    op1     <= stk_data_out;
                    state   <= `OP2_POP;
                end
                `OP2_POP:
                begin
                    stk_pop <= 1;
                    state   <= `OP2_RCV;
                end
                `OP2_RCV:
                begin
                    stk_pop <= 0;
                    op2     <= stk_data_out;
                    state   <= `ALU;
                end
                `ALU:
                begin
                    if (asn)
                        state <= `ADD;
                    else
                        state <= `SUB;
                end
                `ADD:
                begin
                    res   <= op1+op2;
                    state <= `PUSH;
                end
                `SUB:
                begin
                    res   <= op1-op2;
                    state <= `PUSH;
                end
                `PUSH:
                begin
                    stk_push    <= 1;
                    stk_data_in <= res;
                    state       <= `INIT;
                end
            endcase
        end
    end
    
    initial
        $monitor($time, "\t [ALU::%d] rstn = %b, control_bus = %b, z_flag = %b, s_flag = %b, opt1 = %d, opt2 = %d, res = %d, stk_data_in = %d, stk_push = %b, stk_pop = %b, stk_data_out = %d", state, rstn, control_bus, z_flag, s_flag, op1, op2, res, stk_data_in, stk_push, stk_pop, stk_data_out);
    
endmodule

AZ10/EXEC.v
`define NXTI 2'b00
`define EXIT 2'b11

module EXEC (clk,
             en,
             rstn,
             pc,
             control_bus,
             addr_const,
             stk_data_in,
             stk_push,
             stk_pop,
             stk_data_out,
             mem_data_in,
             mem_addr,
             mem_r_en,
             mem_w_en,
             mem_data_out,
             exec_code);
    
    parameter DATA_LEN = 8;
    parameter ADDR_LEN = 8;
    parameter INST_CAP = 20;
    
    input clk, en, rstn;
    input [3:0] control_bus;
    input [DATA_LEN-1:0] stk_data_out, mem_data_out, addr_const;
    output wire [DATA_LEN-1:0] stk_data_in, mem_data_in;
    output wire [ADDR_LEN-1:0] mem_addr;
    output wire stk_push, stk_pop, mem_r_en, mem_w_en;
    output wire [$clog2(INST_CAP):0] pc;
    wire alu_z_flag, alu_s_flag;
    output wire [1:0] exec_code;
    
    assign exec_code = (en && control_bus[3] == 1) ? `EXIT : `NXTI;
    
    ALU  #(
    .DATA_LEN(DATA_LEN)
    ) alu0 (
    .clk(clk),
    .rstn(rstn),
    .en(en),
    .control_bus(control_bus),
    .z_flag(alu_z_flag),
    .s_flag(alu_s_flag),
    .stk_data_in(stk_data_in),
    .stk_push(stk_push),
    .stk_pop(stk_pop),
    .stk_data_out(stk_data_out)
    );
    
    WBPB  #(
    .DATA_LEN(DATA_LEN),
    .ADDR_LEN(ADDR_LEN)
    ) wbpb0 (
    .clk(clk),
    .rstn(rstn),
    .en(en),
    .control_bus(control_bus),
    .addr_const(addr_const),
    .stk_data_in(stk_data_in),
    .stk_push(stk_push),
    .stk_pop(stk_pop),
    .stk_data_out(stk_data_out),
    .mem_data_in(mem_data_in),
    .mem_addr(mem_addr),
    .mem_r_en(mem_r_en),
    .mem_w_en(mem_w_en),
    .mem_data_out(mem_data_out)
    );
    
    PC #(
    .DATA_LEN(DATA_LEN),
    .INST_CAP(INST_CAP)
    ) pc0 (
    .clk(clk),
    .rstn(rstn),
    .en(en),
    .control_bus(control_bus),
    .pc(pc),
    .z_flag(alu_z_flag),
    .s_flag(alu_s_flag),
    .stk_pop(stk_pop),
    .stk_data_out(stk_data_out)
    );
    
endmodule

AZ10/IFIDC.v
`define INIT    0000
`define IF      0001
`define ID      0010

module IFIDC (clk,
              en,
              rstn,
              pc,
              control_bus,
              data);
              
    parameter INST_CAP = 20;
    parameter INST_LEN = 12;
    parameter DATA_LEN = 8;
    
    input clk, rstn, en;
    input [$clog2(INST_CAP):0] pc;
    output reg [3:0]control_bus;
    output reg [DATA_LEN-1:0]data;
    
    reg [INST_LEN-1:0] inst_mem [INST_CAP-1:0];
    reg[INST_LEN-1:0] inst;
    
    reg [3:0]state;
    
    always @(posedge clk or negedge rstn) begin
        if (!rstn && !en) begin
            control_bus <= 0;
            data        <= 0;
            state       <= `INIT;
        end
        else begin
            case(state)
                `INIT:
                begin
                    if (rstn) begin
                        if (en) begin
                            state       <= `IF;
                            control_bus <= 0;
                            data        <= 0;
                        end
                    end
                end
                
                `IF:
                begin
                    inst  <= inst_mem[pc];
                    state <= `ID;
                end
                
                `ID:
                begin
                    control_bus[3:0] <= inst[INST_LEN-1:DATA_LEN];
                    data             <= inst[DATA_LEN-1:0];
                    state            <= `INIT;
                end
            endcase
        end
    end
    
    initial
        $monitor($time, "\t [IFIDC::%d] pc=%d control_bus=%b data=%d", state, pc, control_bus, data);
    
endmodule

AZ10/CPU.v
`define IFIDC   2'b01
`define EXEC    2'b10
`define EXRET   2'b00
`define EXIT    2'b11

module CPU (rstn,
            clk);
    
    parameter DATA_LEN    = 8;
    parameter ADDR_LEN    = 8;
    parameter INST_CAP    = 20;
    parameter INST_LEN    = 12;
    parameter WORD_LEN    = 8;
    parameter MEM_SIZE    = 256;
    parameter STACK_DEPTH = 8;
    
    input rstn, clk;
    
    wire stk_full, stk_empty, stk_push, stk_pop, mem_r_en, mem_w_en;
    wire [1:0] exec_code;
    wire [3:0] ifidc_control_bus;
    wire [DATA_LEN-1:0] stk_data_in, stk_data_out, mem_data_in, mem_data_out, ifidc_addr_const;
    wire [ADDR_LEN-1:0] mem_addr;
    wire [$clog2(INST_CAP):0] exec_pc;
    
    reg ifidc_en, exec_en;
    reg [1:0] state;
    
    always @(posedge clk or negedge rstn) begin
        if (!rstn) begin
            ifidc_en <= 0;
            exec_en  <= 0;
            state    <= `IFIDC;
        end
        else begin
            case(state)
                `IFIDC:
                begin
                    ifidc_en <= 1;
                    exec_en  <= 0;
                    state    <= `EXEC;
                end
                `EXEC:
                begin
                    ifidc_en <= 0;
                    exec_en  <= 1;
                    state    <= `EXRET;
                end
                `EXRET:
                begin
                    if (exec_code == `EXIT)
                        state <= `EXRET;
                    else
                        state <= `IFIDC;
                end
            endcase
        end
    end
    
    IFIDC #(
    .INST_CAP(INST_CAP),
    .INST_LEN(INST_LEN),
    .DATA_LEN(DATA_LEN)
    ) ifidc0 (
    .clk(clk),
    .en(ifidc_en),
    .rstn(rstn),
    .pc(exec_pc),
    .control_bus(ifidc_control_bus),
    .data(ifidc_addr_const)
    );
    
    EXEC #(
    .DATA_LEN(DATA_LEN),
    .ADDR_LEN(ADDR_LEN),
    .INST_CAP(INST_CAP)
    ) exec0 (
    .clk(clk),
    .en(exec_en),
    .rstn(rstn),
    .pc(exec_pc),
    .control_bus(ifidc_control_bus),
    .addr_const(ifidc_addr_const),
    .stk_data_in(stk_data_in),
    .stk_push(stk_push),
    .stk_pop(stk_pop),
    .stk_data_out(stk_data_out),
    .mem_data_in(mem_data_in),
    .mem_addr(mem_addr),
    .mem_r_en(mem_r_en),
    .mem_w_en(mem_w_en),
    .mem_data_out(mem_data_out),
    .exec_code(exec_code)
    );
    
    MEMORY #(
    .ADDR_LEN(ADDR_LEN),
    .WORD_LEN(WORD_LEN),
    .MEM_SIZE(MEM_SIZE)
    ) memory0 (
    .clk(clk),
    .addr(mem_addr),
    .r_en(mem_r_en),
    .w_en(mem_w_en),
    .data_out(mem_data_out),
    .data_in(mem_data_in)
    );
    
    Stack #(
    .WORD_LEN(WORD_LEN),
    .STACK_DEPTH(STACK_DEPTH)
    ) stack0 (
    .clk(clk),
    .rstn(rstn),
    .data_in(stk_data_in),
    .push(stk_push),
    .pop(stk_pop),
    .data_out(stk_data_out),
    .full(stk_full),
    .empty(stk_empty)
    );
    
    initial
        $monitor($time, "\t [CPU::%d] ifidc_en = %b, exec_en = %b", state, ifidc_en, exec_en);
    
endmodule

AZ10/testbench.v
module testbench();
    
    parameter CLK_C       = 10;
    parameter DATA_LEN    = 8;
    parameter ADDR_LEN    = 8;
    parameter INST_CAP    = 20;
    parameter INST_LEN    = 12;
    parameter WORD_LEN    = 8;
    parameter MEM_SIZE    = 256;
    parameter STACK_DEPTH = 8;
    
    reg clk, rstn;
    
    CPU #(
    .WORD_LEN(WORD_LEN),
    .DATA_LEN(DATA_LEN),
    .ADDR_LEN(ADDR_LEN),
    .MEM_SIZE(MEM_SIZE),
    .STACK_DEPTH(STACK_DEPTH),
    .INST_LEN(INST_LEN),
    .INST_CAP(INST_CAP)
    ) cpu0 (
    .clk(clk),
    .rstn(rstn)
    );
    
    
    initial begin
        $dumpfile("report/waveform.vcd");
        $dumpvars(0,cpu0);
    end
    
    initial begin
        clk         = 0;
        forever clk = #(CLK_C/2) ~clk;
    end
    
    initial begin
        $readmemb("report/memory.mem", cpu0.memory0.mem, 0, MEM_SIZE-1);
        $readmemb("report/is.mem", cpu0.ifidc0.inst_mem, 0, INST_CAP-1);
    end
    
    initial begin
        rstn = 0;
        #CLK_C
        rstn = 1;
        #(20 * CLK_C);
        $writememb("report/result.mem", cpu0.memory0.mem, 0, MEM_SIZE-1);
        $finish;
    end
    
endmodule

AZ10/report/waveform.vcd
$date
	Sat May 29 02:11:17 2021
$end
$version
	Icarus Verilog
$end
$timescale
	1s
$end
$scope module testbench $end
$scope module cpu0 $end
$var wire 1 ! clk $end
$var wire 1 " rstn $end
$var wire 8 # stk_data_in [7:0] $end
$var wire 1 $ stk_pop $end
$var wire 1 % stk_push $end
$var wire 1 & stk_full $end
$var wire 1 ' stk_empty $end
$var wire 8 ( stk_data_out [7:0] $end
$var wire 1 ) mem_w_en $end
$var wire 1 * mem_r_en $end
$var wire 8 + mem_data_out [7:0] $end
$var wire 8 , mem_data_in [7:0] $end
$var wire 8 - mem_addr [7:0] $end
$var wire 4 . ifidc_control_bus [3:0] $end
$var wire 8 / ifidc_addr_const [7:0] $end
$var wire 6 0 exec_pc [5:0] $end
$var wire 2 1 exec_code [1:0] $end
$var reg 1 2 exec_en $end
$var reg 1 3 ifidc_en $end
$var reg 2 4 state [1:0] $end
$scope module exec0 $end
$var wire 1 ! clk $end
$var wire 1 2 en $end
$var wire 1 " rstn $end
$var wire 8 5 stk_data_in [7:0] $end
$var wire 1 $ stk_pop $end
$var wire 1 % stk_push $end
$var wire 8 6 stk_data_out [7:0] $end
$var wire 6 7 pc [5:0] $end
$var wire 1 ) mem_w_en $end
$var wire 1 * mem_r_en $end
$var wire 8 8 mem_data_out [7:0] $end
$var wire 8 9 mem_data_in [7:0] $end
$var wire 8 : mem_addr [7:0] $end
$var wire 2 ; exec_code [1:0] $end
$var wire 4 < control_bus [3:0] $end
$var wire 1 = alu_z_flag $end
$var wire 1 > alu_s_flag $end
$var wire 8 ? addr_const [7:0] $end
$scope module alu0 $end
$var wire 1 @ alu_en $end
$var wire 1 ! clk $end
$var wire 1 2 en $end
$var wire 1 " rstn $end
$var wire 1 = z_flag $end
$var wire 8 A stk_data_out [7:0] $end
$var wire 1 > s_flag $end
$var wire 4 B control_bus [3:0] $end
$var wire 1 C asn $end
$var reg 8 D op1 [7:0] $end
$var reg 8 E op2 [7:0] $end
$var reg 8 F res [7:0] $end
$var reg 4 G state [3:0] $end
$var reg 8 H stk_data_in [7:0] $end
$var reg 1 I stk_pop $end
$var reg 1 J stk_push $end
$upscope $end
$scope module pc0 $end
$var wire 1 K branch $end
$var wire 1 ! clk $end
$var wire 1 2 en $end
$var wire 1 " rstn $end
$var wire 1 > s_flag $end
$var wire 1 = z_flag $end
$var wire 8 L stk_data_out [7:0] $end
$var wire 2 M opc [1:0] $end
$var wire 4 N control_bus [3:0] $end
$var reg 6 O pc [5:0] $end
$var reg 4 P state [3:0] $end
$var reg 1 Q stk_pop $end
$upscope $end
$scope module wbpb0 $end
$var wire 1 ! clk $end
$var wire 1 2 en $end
$var wire 1 " rstn $end
$var wire 1 R wbpb_en $end
$var wire 8 S stk_data_out [7:0] $end
$var wire 2 T opc [1:0] $end
$var wire 8 U mem_data_out [7:0] $end
$var wire 4 V control_bus [3:0] $end
$var wire 8 W addr_const [7:0] $end
$var reg 8 X mem_addr [7:0] $end
$var reg 8 Y mem_data_in [7:0] $end
$var reg 1 * mem_r_en $end
$var reg 1 ) mem_w_en $end
$var reg 4 Z state [3:0] $end
$var reg 8 [ stk_data_in [7:0] $end
$var reg 1 \ stk_pop $end
$var reg 1 ] stk_push $end
$upscope $end
$upscope $end
$scope module ifidc0 $end
$var wire 1 ! clk $end
$var wire 1 3 en $end
$var wire 6 ^ pc [5:0] $end
$var wire 1 " rstn $end
$var reg 4 _ control_bus [3:0] $end
$var reg 8 ` data [7:0] $end
$var reg 12 a inst [11:0] $end
$var reg 4 b state [3:0] $end
$upscope $end
$scope module memory0 $end
$var wire 8 c addr [7:0] $end
$var wire 1 ! clk $end
$var wire 8 d data_in [7:0] $end
$var wire 1 * r_en $end
$var wire 1 ) w_en $end
$var reg 8 e data_out [7:0] $end
$upscope $end
$scope module stack0 $end
$var wire 1 ! clk $end
$var wire 8 f data_in [7:0] $end
$var wire 1 $ pop $end
$var wire 1 % push $end
$var wire 1 " rstn $end
$var wire 1 & full $end
$var wire 1 ' empty $end
$var reg 8 g data_out [7:0] $end
$var reg 4 h stack_ptr [3:0] $end
$scope task reset_memory $end
$var integer 32 i i [31:0] $end
$upscope $end
$upscope $end
$upscope $end
$upscope $end
$enddefinitions $end
#0
$dumpvars
bx i
bx h
bx g
bx f
bx e
bx d
bx c
bx b
bx a
bx `
bx _
bx ^
x]
x\
bx [
bx Z
bx Y
bx X
bx W
bx V
bx U
bx T
bx S
0R
xQ
bx P
bx O
bx N
bx M
bx L
xK
xJ
xI
bx H
bx G
bx F
bx E
bx D
xC
bx B
bx A
0@
bx ?
x>
x=
bx <
b0 ;
bx :
bx 9
bx 8
bx 7
bx 6
bx 5
b1 4
03
02
b0 1
bx 0
bx /
bx .
bx -
bx ,
bx +
x*
x)
bx (
x'
x&
x%
x$
bx #
0"
0!
$end
#5
b0 T
0K
b0 M
0C
b0 0
b0 7
b0 O
b0 ^
z$
zQ
b0 P
z)
z*
bz -
bz :
bz X
bz c
bz ,
bz 9
bz Y
bz d
z\
z%
z]
bz #
bz 5
bz f
bz [
b0 Z
zI
zJ
bz H
b0 G
b0 b
b0 /
b0 ?
b0 W
b0 `
b0 .
b0 <
b0 B
b0 N
b0 V
b0 _
1!
#10
0!
1"
#15
b10 4
13
1'
0&
b0 h
b1000 i
1!
#20
0!
#25
1R
b0 4
12
03
b1 b
b1000 i
1!
#30
0!
#35
b1010 b
b100000001 a
b1 Z
b1010 P
b1 4
b1000 i
1!
#40
0!
#45
0R
b1 T
b1 M
1C
b10 4
02
13
b0 P
b1 0
b1 7
b1 O
b1 ^
b0 Z
b0 #
b0 5
b0 f
b0 [
1%
1]
b0 b
b1 /
b1 ?
b1 W
b1 `
b1 .
b1 <
b1 B
b1 N
b1 V
b1 _
b1000 i
1!
#50
0!
#55
b0 T
b0 M
0C
1R
b0 /
b0 ?
b0 W
b0 `
b0 .
b0 <
b0 B
b0 N
b0 V
b0 _
b1 b
z%
z]
bz #
bz 5
bz f
bz [
b0 4
12
03
b1000 i
1!
#60
0!
#65
b1 4
b1010 P
b1 Z
b1010 b
b10111 a
b1000 i
1!
#70
0!
#75
0R
b0 b
b10111 /
b10111 ?
b10111 W
b10111 `
b0 Z
b0 #
b0 5
b0 f
b0 [
1%
1]
b0 P
b10 0
b10 7
b10 O
b10 ^
b10 4
02
13
b1000 i
1!
#80
0!
#85
1R
b0 4
12
03
z%
z]
bz #
bz 5
bz f
bz [
b0 /
b0 ?
b0 W
b0 `
b1 b
b1000 i
1!
#90
0!
#95
b1010 b
b110xxxxxxxx a
b1 Z
b1010 P
b1 4
b1000 i
1!
#100
0!
#105
0R
b10 T
b10 M
b10 4
02
13
b0 P
b11 0
b11 7
b11 O
b11 ^
b0 Z
b0 #
b0 5
b0 f
b0 [
1%
1]
b0 b
bx /
bx ?
bx W
bx `
b110 .
b110 <
b110 B
b110 N
b110 V
b110 _
b1000 i
1!
#110
0!
#115
b0 T
b0 M
1R
b0 /
b0 ?
b0 W
b0 `
b0 .
b0 <
b0 B
b0 N
b0 V
b0 _
b1 b
z%
z]
bz #
bz 5
bz f
bz [
b0 4
12
03
b1000 i
1!
#120
0!
#125
b1 4
b1010 P
b1 Z
b1010 b
b1000000010 a
b1000 i
1!
#130
0!
#135
b10 T
0R
b0 b
b10 /
b10 ?
b10 W
b10 `
b10 .
b10 <
b10 B
b10 N
b10 V
b10 _
b0 Z
b0 #
b0 5
b0 f
b0 [
1%
1]
b0 P
b100 0
b100 7
b100 O
b100 ^
b10 4
02
13
b1000 i
1!
#140
0!
#145
1R
b0 T
b0 4
12
03
z%
z]
bz #
bz 5
bz f
bz [
b0 /
b0 ?
b0 W
b0 `
b0 .
b0 <
b0 B
b0 N
b0 V
b0 _
b1 b
b1000 i
1!
#150
0!
#155
b1010 b
b100000010 a
b1 Z
b1010 P
b1 4
b1000 i
1!
#160
0!
#165
0R
b1 T
b1 M
1C
b10 4
02
13
b0 P
b101 0
b101 7
b101 O
b101 ^
b0 Z
b0 #
b0 5
b0 f
b0 [
1%
1]
b0 b
b10 /
b10 ?
b10 W
b10 `
b1 .
b1 <
b1 B
b1 N
b1 V
b1 _
b1000 i
1!
#170
0!
#175
b0 T
b0 M
0C
1R
b0 /
b0 ?
b0 W
b0 `
b0 .
b0 <
b0 B
b0 N
b0 V
b0 _
b1 b
z%
z]
bz #
bz 5
bz f
bz [
b0 4
12
03
b1000 i
1!
#180
0!
#185
b1 4
b1010 P
b1 Z
b1010 b
b1000 i
1!
#190
0!
#195
b1 T
b1 M
1C
0R
b0 b
b10 /
b10 ?
b10 W
b10 `
b1 .
b1 <
b1 B
b1 N
b1 V
b1 _
b0 Z
b0 #
b0 5
b0 f
b0 [
1%
1]
b0 P
b110 0
b110 7
b110 O
b110 ^
b10 4
02
13
b1000 i
1!
#200
0!
#205
1R
b0 T
b0 M
0C
b0 4
12
03
z%
z]
bz #
bz 5
bz f
bz [
b0 /
b0 ?
b0 W
b0 `
b0 .
b0 <
b0 B
b0 N
b0 V
b0 _
b1 b
b1000 i
1!
