AZ10/stack.v
module Stack (rstn,
              data_in,
              push,
              pop,
              clk,
              data_out,
              full,
              empty);
    
    parameter STACK_DEPTH = 8;
    parameter WORD_LEN    = 8;
    
    input wire rstn, push, pop, clk;
    input wire[WORD_LEN-1:0] data_in;
    output full, empty;
    output reg [WORD_LEN-1:0] data_out;
    
    reg[$clog2(STACK_DEPTH):0] stack_ptr;
    reg[WORD_LEN-1:0] memory [0:STACK_DEPTH-1];
    
    assign empty = (stack_ptr == 0) ? 1'b1 : 1'b0;
    assign full  = (stack_ptr == STACK_DEPTH) ? 1'b1 : 1'b0;
    
    wire [WORD_LEN-1:0]top = memory[stack_ptr-1];
    
    // stack reset
    task reset_memory;
        integer i;
        begin
            for (i = 0; i < STACK_DEPTH;i++) begin
                memory[i] <= {WORD_LEN{1'b0}};
            end
            stack_ptr <= 0;
        end
    endtask
    
    always @(posedge clk or negedge rstn) begin
        if (!rstn) begin
            reset_memory;
        end
        else begin
            // pushing into stack
            if (push && !pop && !full) begin
                memory[stack_ptr] <= data_in;
                stack_ptr         <= stack_ptr + 1;
            end
            // pop from stack
            if (pop && !push && !empty) begin
                data_out  <= memory[stack_ptr - 1];
                stack_ptr <= stack_ptr - 1;
            end
        end
        
    end
    
    //debugging
    always @(*)
        $display($time, "\t [STACK] rstn = %b, stack_ptr = %d, top = %d, data_in = %d, push = %b, pop = %b, data_out = %d, full = %b, empty = %b", rstn, stack_ptr, top, data_in, push, pop, data_out, full, empty);
    
endmodule

AZ10/memory.v
module MEMORY (addr,
               r_en,
               w_en,
               data_out,
               data_in,
               clk);
    
    parameter ADDR_LEN = 8;
    parameter WORD_LEN = 8;
    parameter MEM_SIZE = 256;
    
    
    input [ADDR_LEN-1:0] addr;
    input r_en,w_en,clk;
    
    input [WORD_LEN-1:0]data_in;
    output reg [WORD_LEN-1:0]data_out;
    
    reg [WORD_LEN-1:0] mem [MEM_SIZE-1:0];
    
    reg [WORD_LEN-1:0] data_o1,data_o2;
    
    always @(*)
    begin
        if (r_en) begin
            data_out <= mem[addr];
        end
        if (w_en) begin
            mem[addr] <= data_in;
        end
    end
    
    //debugging
    always @(*)
        $display($time, "\t [MEMORY] r_en = %b, addr = %d, w_en = %b, data_in = %b, data_out = %b", r_en, addr, w_en, data_in, data_out);
    
endmodule

AZ10/PC.v
`define INIT    3'b000
`define POP     3'b001
`define NXTL    3'b010
`define BR      3'b011
`define EXIT    3'b100
`define POP_W   3'b101

`define OP_JP   2'b01
`define OP_JS   2'b10
`define OP_JZ   2'b11

module PC (control_bus,
           clk,
           rstn,
           en,
           pc,
           z_flag,
           s_flag,
           stk_pop,
           stk_push,
           stk_data_out,
           fin_sig);
    
    parameter INST_CAP = 20;
    parameter DATA_LEN = 8;
    
    input clk, en, rstn, z_flag, s_flag;
    input [3:0] control_bus;
    input [DATA_LEN-1:0] stk_data_out;
    output reg stk_pop,stk_push, fin_sig;
    output reg [$clog2(INST_CAP):0] pc;
    
    wire[1:0] opc = {control_bus[2], control_bus[0]};
    wire branch   = (control_bus > 2 && control_bus < 6);
    wire exit     = (control_bus == 4'b1111);
    wire stall    = !(control_bus < 4'b1000 || control_bus == 4'b1111);
    
    reg [2:0]state;
    
    always @(posedge clk, negedge rstn) begin
        if (!rstn && !en) begin
            state    <= `INIT;
            stk_pop  <= 1'bz;
            stk_push <= 1'bz;
            pc       <= 0;
            fin_sig  <= 0;
        end
        else begin
            case(state)
                `INIT:
                begin
                    if (en) begin
                        if (branch)
                            state <= `POP;
                        else if (exit)
                            state <= `EXIT;
                        else
                            state <= `NXTL;
                    end
                    fin_sig  <= 0;
                    stk_pop  <= 1'bz;
                    stk_push <= 1'bz;
                end
                `POP:
                begin
                    stk_push <= 0;
                    if ((opc == `OP_JP) || (opc == `OP_JZ && z_flag) ||  (opc == `OP_JS && s_flag)) begin
                        stk_pop <= 1;
                        state   <= `POP_W;
                    end
                    else begin
                        state <= `NXTL;
                    end
                end
                `POP_W:
                begin
                    stk_pop <= 1;
                    state   <= `BR;
                end
                `NXTL:
                begin
                    if (pc < INST_CAP - 1) begin
                        pc <= pc + 1;
                    end
                    state <= `INIT;
                    if (stall) begin
                        fin_sig <= 1;
                    end
                end
                `BR:
                begin
                    pc      <= stk_data_out;
                    state   <= `INIT;
                    fin_sig <= 1;
                end
                `EXIT:
                begin
                    $writememb("report/result.mem", cpu0.memory0.mem);
                    $finish;
                end
            endcase
        end
        
    end
    
    //debugging
    always @(*)
        $display($time, "\t [PC::%d] rstn = %b, en = %b, control_bus = %b, pc = %d, z_flag = %b, s_flag = %b, stk_pop = %b, stk_data_out = %d", state, rstn, en, control_bus, pc, z_flag, s_flag, stk_pop, stk_data_out);
    
endmodule

AZ10/PP.v
`define INIT    3'b000

`define LOAD    3'b011
`define PUSH    3'b001
`define PUSH_W  3'b010

`define POP     3'b101
`define POP_W   3'b110
`define STORE   3'b111

`define OP_PUSHC    2'b00
`define OP_PUSHM    2'b01
`define OP_POPM     2'b10

module PP (control_bus,
           clk,
           en,
           rstn,
           addr_const,
           stk_data_in,
           stk_push,
           stk_pop,
           stk_data_out,
           mem_data_in,
           mem_addr,
           mem_r_en,
           mem_w_en,
           mem_data_out,
           fin_sig);
    
    parameter ADDR_LEN = 8;
    parameter DATA_LEN = 8;
    
    input clk, rstn, en;
    input [3:0] control_bus;
    input [DATA_LEN-1:0] stk_data_out, mem_data_out, addr_const;
    output reg [DATA_LEN-1:0] stk_data_in, mem_data_in;
    output reg [ADDR_LEN-1:0] mem_addr;
    output reg stk_push, stk_pop, mem_r_en, mem_w_en, fin_sig;
    
    wire [1:0] opc = control_bus[1:0];
    wire pp_en     = (en && control_bus < 3);
    
    reg [2:0]state;
    
    always @(posedge clk, negedge rstn) begin
        if (!rstn && !pp_en) begin
            state       <= `INIT;
            stk_data_in <= {DATA_LEN{1'bz}};
            stk_push    <= 1'bz;
            stk_pop     <= 1'bz;
            mem_data_in <= {DATA_LEN{1'bz}};
            mem_addr    <= {ADDR_LEN{1'bz}};
            mem_r_en    <= 1'bz;
            mem_w_en    <= 1'bz;
            fin_sig     <= 0;
        end
        else begin
            case(state)
                `INIT:
                begin
                    if (pp_en) begin
                        state <= {opc,1'b1};
                    end
                    fin_sig     <= 0;
                    stk_data_in <= {DATA_LEN{1'bz}};
                    stk_push    <= 1'bz;
                    stk_pop     <= 1'bz;
                    mem_data_in <= {DATA_LEN{1'bz}};
                    mem_addr    <= {ADDR_LEN{1'bz}};
                    mem_r_en    <= 1'bz;
                    mem_w_en    <= 1'bz;
                end
                `PUSH:
                begin
                    mem_r_en    <= 0;
                    mem_w_en    <= 0;
                    stk_pop     <= 0;
                    stk_data_in <= (opc == `OP_PUSHC) ? addr_const : mem_data_out;
                    state       <= `PUSH_W;
                end
                `PUSH_W:
                begin
                    stk_push <= 1;
                    state    <= `INIT;
                    fin_sig  <= 1;
                end
                `STORE:
                begin
                    mem_w_en    <= 1;
                    mem_r_en    <= 0;
                    mem_data_in <= stk_data_out;
                    mem_addr    <= addr_const;
                    state       <= `INIT;
                    fin_sig     <= 1;
                end
                `POP:
                begin
                    stk_push <= 0;
                    stk_pop  <= 1;
                    state    <= `POP_W;
                end
                `POP_W:
                begin
                    state <= `STORE;
                end
                `LOAD:
                begin
                    mem_r_en <= 1;
                    mem_w_en <= 0;
                    mem_addr <= addr_const;
                    state    <= `PUSH;
                end
                default:
                state <= `INIT;
            endcase
        end
        
    end
    
    //debugging
    always @(*)
        $display($time, "\t [WBPB::%d] rstn = %b, en = %b, fin_sig = %b, control_bus = %b, addr_const = %d, stk_data_in = %d, stk_push = %b, stk_pop = %b, stk_data_out = %d, mem_data_in = %d, mem_addr = %d, mem_r_en = %b, mem_w_en = %b, mem_data_out = %d", state, rstn, en, fin_sig, control_bus, addr_const, stk_data_in, stk_push, stk_pop, stk_data_out, mem_data_in, mem_addr, mem_r_en, mem_w_en, mem_data_out);
    
endmodule

AZ10/ALU.v
`define INIT    4'b0000
`define OP1_POP 4'b0001
`define OP1_RCV 4'b0010
`define OP1_STR 4'b0011
`define OP2_POP 4'b0100
`define OP2_RCV 4'b0101
`define OP2_STR 4'b0110
`define ALU     4'b0111
`define PUSH    4'b1000
`define PUSH_W  4'b1001

module ALU (control_bus,
            clk,
            en,
            rstn,
            z_flag,
            s_flag,
            stk_data_in,
            stk_push,
            stk_pop,
            stk_data_out,
            fin_sig);
    
    parameter DATA_LEN = 8;
    
    input clk, rstn, en;
    input [3:0] control_bus;
    input [DATA_LEN-1:0] stk_data_out;
    output reg [DATA_LEN-1:0] stk_data_in;
    output reg stk_push, stk_pop;
    output reg z_flag, s_flag, fin_sig;
    
    wire asn    = !control_bus[0];
    wire alu_en = (en && control_bus[1] && control_bus[2]);
    
    reg [3:0]state;
    
    reg signed [DATA_LEN-1:0] op1, op2, result;
    
    always @(posedge clk, negedge rstn) begin
        if (!rstn && !alu_en) begin
            state       <= `INIT;
            stk_data_in <= {DATA_LEN{1'bz}};
            stk_push    <= 1'bz;
            stk_pop     <= 1'bz;
            s_flag      <= 0;
            z_flag      <= 0;
            fin_sig     <= 0;
        end
        else begin
            case(state)
                `INIT:
                begin
                    if (alu_en) begin
                        state <= `OP1_POP;
                    end
                    fin_sig     <= 0;
                    stk_data_in <= {DATA_LEN{1'bz}};
                    stk_push    <= 1'bz;
                    stk_pop     <= 1'bz;
                end
                `OP1_POP:
                begin
                    stk_push<= 0;
                    stk_pop <= 1;
                    state   <= `OP1_RCV;
                end
                `OP1_RCV:
                begin
                    stk_pop <= 0;
                    state   <= `OP1_STR;
                end
                `OP1_STR:
                begin
                    op1     <= stk_data_out;
                    state   <= `OP2_POP;
                end
                `OP2_POP:
                begin
                    stk_pop <= 1;
                    state   <= `OP2_RCV;
                end
                `OP2_RCV:
                begin
                    stk_pop <= 0;
                    state   <= `OP2_STR;
                end
                `OP2_STR:
                begin
                    op2     <= stk_data_out;
                    state   <= `ALU;
                end
                `ALU:
                begin
                    if (asn)
                        result   <= op2 + op1;
                    else
                        result   <= op2 - op1;
                    state <= `PUSH;
                end
                `PUSH:
                begin
                    s_flag      <= (result < 0);
                    z_flag      <= (result == 0);
                    stk_push    <= 1;
                    stk_data_in <= result;
                    state       <= `PUSH_W;
                end
                `PUSH_W:
                begin
                    stk_push    <= 0;
                    state       <= `INIT;
                    fin_sig     <= 1;
                end
            endcase
        end
    end
    
    //debugging
    always @(*)
        $display($time, "\t [ALU::%d] rstn = %b, control_bus = %b, opt1 = %d, opt2 = %d, result = %d, stk_data_in = %d, stk_push = %b, stk_pop = %b, stk_data_out = %d z_flag = %b, s_flag = %b,", state, rstn, control_bus, op1, op2, result, stk_data_in, stk_push, stk_pop, stk_data_out, z_flag, s_flag);
    
endmodule

AZ10/EXEC.v
`define NXTI 2'b00
`define EXIT 2'b11

module EXEC (clk,
             en,
             rstn,
             pc,
             control_bus,
             addr_const,
             stk_data_in,
             stk_push,
             stk_pop,
             stk_data_out,
             mem_data_in,
             mem_addr,
             mem_r_en,
             mem_w_en,
             mem_data_out,
             fin_sig);
    
    parameter DATA_LEN = 8;
    parameter ADDR_LEN = 8;
    parameter INST_CAP = 20;
    
    input clk, en, rstn;
    input [3:0] control_bus;
    input [DATA_LEN-1:0] stk_data_out, mem_data_out, addr_const;
    output wire [DATA_LEN-1:0] stk_data_in, mem_data_in;
    output wire [ADDR_LEN-1:0] mem_addr;
    output wire stk_push, stk_pop, mem_r_en, mem_w_en, fin_sig;
    output wire [$clog2(INST_CAP):0] pc;
    wire alu_z_flag, alu_s_flag, alu_fin_sig, wbpb_fin_sig, pc_fin_sig;
    
    assign fin_sig = (alu_fin_sig | wbpb_fin_sig | pc_fin_sig);
    
    ALU  #(
    .DATA_LEN(DATA_LEN)
    ) alu0 (
    .clk(clk),
    .rstn(rstn),
    .en(en),
    .control_bus(control_bus),
    .z_flag(alu_z_flag),
    .s_flag(alu_s_flag),
    .stk_data_in(stk_data_in),
    .stk_push(stk_push),
    .stk_pop(stk_pop),
    .stk_data_out(stk_data_out),
    .fin_sig(alu_fin_sig)
    );
    
    PP  #(
    .DATA_LEN(DATA_LEN),
    .ADDR_LEN(ADDR_LEN)
    ) pp0 (
    .clk(clk),
    .rstn(rstn),
    .en(en),
    .control_bus(control_bus),
    .addr_const(addr_const),
    .stk_data_in(stk_data_in),
    .stk_push(stk_push),
    .stk_pop(stk_pop),
    .stk_data_out(stk_data_out),
    .mem_data_in(mem_data_in),
    .mem_addr(mem_addr),
    .mem_r_en(mem_r_en),
    .mem_w_en(mem_w_en),
    .mem_data_out(mem_data_out),
    .fin_sig(wbpb_fin_sig)
    );
    
    PC #(
    .DATA_LEN(DATA_LEN),
    .INST_CAP(INST_CAP)
    ) pc0 (
    .clk(clk),
    .rstn(rstn),
    .en(en),
    .control_bus(control_bus),
    .pc(pc),
    .z_flag(alu_z_flag),
    .s_flag(alu_s_flag),
    .stk_pop(stk_pop),
    .stk_push(stk_push),
    .stk_data_out(stk_data_out),
    .fin_sig(pc_fin_sig)
    );
    
endmodule

AZ10/IFIDC.v
`define INIT    2'b00
`define IF      2'b01
`define ID      2'b10
`define OP_STL  4'b1000

module IFIDC (clk,
              en,
              rstn,
              pc,
              IS_ready,
              control_bus,
              data);
    
    parameter INST_CAP = 20;
    parameter INST_LEN = 12;
    parameter DATA_LEN = 8;
    
    input clk, rstn, en;
    input [$clog2(INST_CAP):0] pc;
    output reg [3:0]control_bus;
    output reg [DATA_LEN-1:0]data;
    output reg IS_ready;
    
    reg [INST_LEN-1:0] inst_mem [INST_CAP-1:0];
    reg[INST_LEN-1:0] inst;
    
    reg [1:0]state;
    
    always @(posedge clk or negedge rstn) begin
        if (!rstn && !en) begin
            control_bus <= `OP_STL;
            data        <= 8'bx;
            state       <= `INIT;
            IS_ready    <= 0;
        end
        else begin
            case(state)
                `INIT:
                begin
                    if (en) begin
                        state <= `IF;
                    end
                    IS_ready <= 0;
                end
                `IF:
                begin
                    inst  <= inst_mem[pc];
                    state <= `ID;
                end
                `ID:
                begin
                    control_bus[3:0] <= inst[INST_LEN-1:DATA_LEN];
                    data             <= inst[DATA_LEN-1:0];
                    state            <= `INIT;
                    IS_ready         <= 1;
                end
            endcase
        end
        
    end
    
    //debugging
    always @(*)
        $display($time, "\t [IFIDC::%d] pc = %d control_bus = %b addr_imm = %d IS_ready = %b rstn = %b en = %b", state, pc, control_bus, data,IS_ready,rstn, en);
    
endmodule

AZ10/CPU.v
`define IFIDC   2'b00
`define IFIDC_W 2'b01
`define EXEC    2'b10
`define EXEC_W  2'b11

module CPU (rstn,
            clk);
    
    parameter DATA_LEN    = 8;
    parameter ADDR_LEN    = 8;
    parameter INST_CAP    = 20;
    parameter INST_LEN    = 12;
    parameter WORD_LEN    = 8;
    parameter MEM_SIZE    = 256;
    parameter STACK_DEPTH = 8;
    
    input rstn, clk;
    
    wire stk_full, stk_empty, stk_push, stk_pop, mem_r_en, mem_w_en, exec_fin_sig,IS_ready;
    wire [3:0] ifidc_control_bus;
    wire [DATA_LEN-1:0] stk_data_in, stk_data_out, mem_data_in, mem_data_out, ifidc_addr_const;
    wire [ADDR_LEN-1:0] mem_addr;
    wire [$clog2(INST_CAP):0] exec_pc;
    
    reg ifidc_fetch, exec_en;
    reg [1:0] state;
    
    always @(posedge clk or negedge rstn) begin
        if (!rstn) begin
            ifidc_fetch <= 0;
            exec_en     <= 0;
            state       <= `IFIDC;
        end
        else begin
            case(state)
                `IFIDC:
                begin
                    ifidc_fetch <= 1;
                    state       <= `IFIDC_W;
                end
                `IFIDC_W:
                begin
                    ifidc_fetch <= 0;
                    if (IS_ready) begin
                        state <= `EXEC;
                    end
                end
                `EXEC:
                begin
                    exec_en <= 1;
                    state   <= `EXEC_W;
                end
                `EXEC_W:
                begin
                    exec_en <= 0;
                    if (exec_fin_sig) begin
                        state <= `IFIDC;
                    end
                end
            endcase
        end
    end
    
    IFIDC #(
    .INST_CAP(INST_CAP),
    .INST_LEN(INST_LEN),
    .DATA_LEN(DATA_LEN)
    ) ifidc0 (
    .clk(clk),
    .en(ifidc_fetch),
    .rstn(rstn),
    .pc(exec_pc),
    .IS_ready(IS_ready),
    .control_bus(ifidc_control_bus),
    .data(ifidc_addr_const)
    );
    
    EXEC #(
    .DATA_LEN(DATA_LEN),
    .ADDR_LEN(ADDR_LEN),
    .INST_CAP(INST_CAP)
    ) exec0 (
    .clk(clk),
    .en(exec_en),
    .rstn(rstn),
    .pc(exec_pc),
    .control_bus(ifidc_control_bus),
    .addr_const(ifidc_addr_const),
    .stk_data_in(stk_data_in),
    .stk_push(stk_push),
    .stk_pop(stk_pop),
    .stk_data_out(stk_data_out),
    .mem_data_in(mem_data_in),
    .mem_addr(mem_addr),
    .mem_r_en(mem_r_en),
    .mem_w_en(mem_w_en),
    .mem_data_out(mem_data_out),
    .fin_sig(exec_fin_sig)
    );
    
    MEMORY #(
    .ADDR_LEN(ADDR_LEN),
    .WORD_LEN(WORD_LEN),
    .MEM_SIZE(MEM_SIZE)
    ) memory0 (
    .clk(clk),
    .addr(mem_addr),
    .r_en(mem_r_en),
    .w_en(mem_w_en),
    .data_out(mem_data_out),
    .data_in(mem_data_in)
    );
    
    Stack #(
    .WORD_LEN(WORD_LEN),
    .STACK_DEPTH(STACK_DEPTH)
    ) stack0 (
    .clk(clk),
    .rstn(rstn),
    .data_in(stk_data_in),
    .push(stk_push),
    .pop(stk_pop),
    .data_out(stk_data_out),
    .full(stk_full),
    .empty(stk_empty)
    );
    
    //debugging
    always @(*)
        $display($time, "\t [CPU::%d] ifidc_fetch = %b, exec_en = %b, exec_finish = %b", state, ifidc_fetch, exec_en, exec_fin_sig);
    
    
endmodule

AZ10/testbench.v
module testbench();
    
    parameter CLK_C       = 10;
    parameter DATA_LEN    = 8;
    parameter ADDR_LEN    = 8;
    parameter INST_CAP    = 20;
    parameter INST_LEN    = 12;
    parameter WORD_LEN    = 8;
    parameter MEM_SIZE    = 256;
    parameter STACK_DEPTH = 8;
    
    reg clk, rstn;
    
    CPU #(
    .WORD_LEN(WORD_LEN),
    .DATA_LEN(DATA_LEN),
    .ADDR_LEN(ADDR_LEN),
    .MEM_SIZE(MEM_SIZE),
    .STACK_DEPTH(STACK_DEPTH),
    .INST_LEN(INST_LEN),
    .INST_CAP(INST_CAP)
    ) cpu0 (
    .clk(clk),
    .rstn(rstn)
    );
    
    // initial begin
    //     $dumpfile("report/waveform.vcd");
    //     $dumpvars(0,cpu0);
    // end
    
    initial begin
        clk         = 0;
        forever clk = #(CLK_C/2) ~clk;
    end
    
    initial begin
        $readmemb("report/memory.mem", cpu0.memory0.mem, 0, MEM_SIZE-1);
        $readmemb("report/is.mem", cpu0.ifidc0.inst_mem, 0, INST_CAP-1);
    end
    
    initial begin
        rstn = 0;
        #CLK_C
        rstn = 1;
        #(100 * CLK_C);
        $writememb("report/result.mem", cpu0.memory0.mem);
        $finish;
    end
    
endmodule

AZ10/report/waveform.vcd
$date
	Tue Jun  1 00:17:58 2021
$end
$version
	Icarus Verilog
$end
$timescale
	1s
$end
$scope module testbench $end
$scope module cpu0 $end
$var wire 1 ! clk $end
$var wire 1 " rstn $end
$var wire 8 # stk_data_in [7:0] $end
$var wire 1 $ stk_pop $end
$var wire 1 % stk_push $end
$var wire 1 & stk_full $end
$var wire 1 ' stk_empty $end
$var wire 8 ( stk_data_out [7:0] $end
$var wire 1 ) mem_w_en $end
$var wire 1 * mem_r_en $end
$var wire 8 + mem_data_out [7:0] $end
$var wire 8 , mem_data_in [7:0] $end
$var wire 8 - mem_addr [7:0] $end
$var wire 4 . ifidc_control_bus [3:0] $end
$var wire 8 / ifidc_addr_const [7:0] $end
$var wire 6 0 exec_pc [5:0] $end
$var wire 1 1 exec_fin_sig $end
$var wire 1 2 IS_ready $end
$var reg 1 3 exec_en $end
$var reg 1 4 ifidc_fetch $end
$var reg 2 5 state [1:0] $end
$scope module exec0 $end
$var wire 1 ! clk $end
$var wire 1 3 en $end
$var wire 1 1 fin_sig $end
$var wire 1 " rstn $end
$var wire 8 6 stk_data_in [7:0] $end
$var wire 1 $ stk_pop $end
$var wire 1 % stk_push $end
$var wire 1 7 wbpb_fin_sig $end
$var wire 8 8 stk_data_out [7:0] $end
$var wire 1 9 pc_fin_sig $end
$var wire 6 : pc [5:0] $end
$var wire 1 ) mem_w_en $end
$var wire 1 * mem_r_en $end
$var wire 8 ; mem_data_out [7:0] $end
$var wire 8 < mem_data_in [7:0] $end
$var wire 8 = mem_addr [7:0] $end
$var wire 4 > control_bus [3:0] $end
$var wire 1 ? alu_z_flag $end
$var wire 1 @ alu_s_flag $end
$var wire 1 A alu_fin_sig $end
$var wire 8 B addr_const [7:0] $end
$scope module alu0 $end
$var wire 1 C alu_en $end
$var wire 1 ! clk $end
$var wire 1 3 en $end
$var wire 1 " rstn $end
$var wire 8 D stk_data_out [7:0] $end
$var wire 4 E control_bus [3:0] $end
$var wire 1 F asn $end
$var reg 1 A fin_sig $end
$var reg 8 G op1 [7:0] $end
$var reg 8 H op2 [7:0] $end
$var reg 8 I result [7:0] $end
$var reg 1 @ s_flag $end
$var reg 4 J state [3:0] $end
$var reg 8 K stk_data_in [7:0] $end
$var reg 1 L stk_pop $end
$var reg 1 M stk_push $end
$var reg 1 ? z_flag $end
$upscope $end
$scope module pc0 $end
$var wire 1 N branch $end
$var wire 1 ! clk $end
$var wire 1 3 en $end
$var wire 1 " rstn $end
$var wire 1 @ s_flag $end
$var wire 1 ? z_flag $end
$var wire 8 O stk_data_out [7:0] $end
$var wire 1 P stall $end
$var wire 2 Q opc [1:0] $end
$var wire 1 R exit $end
$var wire 4 S control_bus [3:0] $end
$var reg 1 9 fin_sig $end
$var reg 6 T pc [5:0] $end
$var reg 3 U state [2:0] $end
$var reg 1 V stk_pop $end
$var reg 1 W stk_push $end
$upscope $end
$scope module pp0 $end
$var wire 1 ! clk $end
$var wire 1 3 en $end
$var wire 1 X pp_en $end
$var wire 1 " rstn $end
$var wire 8 Y stk_data_out [7:0] $end
$var wire 2 Z opc [1:0] $end
$var wire 8 [ mem_data_out [7:0] $end
$var wire 4 \ control_bus [3:0] $end
$var wire 8 ] addr_const [7:0] $end
$var reg 1 7 fin_sig $end
$var reg 8 ^ mem_addr [7:0] $end
$var reg 8 _ mem_data_in [7:0] $end
$var reg 1 * mem_r_en $end
$var reg 1 ) mem_w_en $end
$var reg 3 ` state [2:0] $end
$var reg 8 a stk_data_in [7:0] $end
$var reg 1 b stk_pop $end
$var reg 1 c stk_push $end
$upscope $end
$upscope $end
$scope module ifidc0 $end
$var wire 1 ! clk $end
$var wire 1 4 en $end
$var wire 6 d pc [5:0] $end
$var wire 1 " rstn $end
$var reg 1 2 IS_ready $end
$var reg 4 e control_bus [3:0] $end
$var reg 8 f data [7:0] $end
$var reg 12 g inst [11:0] $end
$var reg 2 h state [1:0] $end
$upscope $end
$scope module memory0 $end
$var wire 8 i addr [7:0] $end
$var wire 1 ! clk $end
$var wire 8 j data_in [7:0] $end
$var wire 1 * r_en $end
$var wire 1 ) w_en $end
$var reg 8 k data_out [7:0] $end
$upscope $end
$scope module stack0 $end
$var wire 1 ! clk $end
$var wire 8 l data_in [7:0] $end
$var wire 1 $ pop $end
$var wire 1 % push $end
$var wire 1 " rstn $end
$var wire 8 m top [7:0] $end
$var wire 1 & full $end
$var wire 1 ' empty $end
$var reg 8 n data_out [7:0] $end
$var reg 4 o stack_ptr [3:0] $end
$scope task reset_memory $end
$var integer 32 p i [31:0] $end
$upscope $end
$upscope $end
$upscope $end
$upscope $end
$enddefinitions $end
#0
$dumpvars
b1000 p
b0 o
bx n
bx m
bx l
bx k
bx j
bx i
bx h
bx g
bx f
bx e
bx d
xc
xb
bx a
b0 `
bx _
bx ^
bx ]
bx \
bx [
bx Z
bx Y
0X
xW
xV
bx U
bx T
bx S
xR
bx Q
xP
bx O
xN
xM
xL
bx K
bx J
bx I
bx H
bx G
xF
bx E
bx D
0C
bx B
xA
x@
x?
bx >
bx =
bx <
bx ;
bx :
x9
bx 8
x7
bx 6
b0 5
04
03
x2
x1
bx 0
bx /
bx .
bx -
bx ,
bx +
x*
x)
bx (
1'
0&
x%
x$
bx #
0"
0!
$end
#5
01
b0 Z
1P
0N
b0 Q
1F
09
b0 0
b0 :
b0 T
b0 d
z%
zW
z$
zV
b0 U
07
z)
z*
bz -
bz =
bz ^
bz i
bz ,
bz <
bz _
bz j
zb
zc
bz #
bz 6
bz l
bz a
0A
0?
0@
zL
zM
bz K
b0 J
02
b0 h
0R
b1000 .
b1000 >
b1000 E
b1000 S
b1000 \
b1000 e
b1000 p
1!
#10
0!
1"
#15
b1 5
14
1!
#20
0!
#25
04
b1 h
1!
#30
0!
#35
b10 h
b100000001 g
1!
#40
0!
#45
b1 Z
0P
b1 Q
0F
12
b0 h
b1 /
b1 B
b1 ]
b1 f
b1 .
b1 >
b1 E
b1 S
b1 \
b1 e
1!
#50
0!
#55
02
b10 5
1!
#60
0!
#65
1X
b11 5
13
1!
#70
0!
#75
0X
b11 `
b10 U
03
1!
#80
0!
#85
b101 +
b101 ;
b101 [
b101 k
b0 U
b1 0
b1 :
b1 T
b1 d
b1 `
b1 -
b1 =
b1 ^
b1 i
0)
1*
1!
#90
0!
#95
b10 `
b101 #
b101 6
b101 l
b101 a
0$
0b
0*
1!
#100
0!
#105
11
17
b0 `
1%
1c
1!
#110
0!
#115
01
0'
z)
z*
bz -
bz =
bz ^
bz i
z$
zb
z%
zc
bz #
bz 6
bz l
bz a
07
b0 5
b101 m
b1 o
1!
#120
0!
#125
b1 5
14
1!
#130
0!
#135
b1 h
04
1!
#140
0!
#145
b10 h
b10111 g
1!
#150
0!
#155
b0 Z
b0 Q
1F
12
b0 h
b10111 /
b10111 B
b10111 ]
b10111 f
b0 .
b0 >
b0 E
b0 S
b0 \
b0 e
1!
#160
0!
#165
b10 5
02
1!
#170
0!
#175
1X
b11 5
13
1!
#180
0!
#185
0X
03
b10 U
b1 `
1!
#190
0!
#195
b10 `
b10111 #
b10111 6
b10111 l
b10111 a
0$
0b
0)
0*
b0 U
b10 0
b10 :
b10 T
b10 d
1!
#200
0!
#205
11
17
b0 `
1%
1c
1!
#210
0!
#215
01
z)
z*
z$
zb
z%
zc
bz #
bz 6
bz l
bz a
07
b0 5
b10111 m
b10 o
1!
#220
0!
#225
b1 5
14
1!
#230
0!
#235
b1 h
04
1!
#240
0!
#245
b10 h
b110xxxxxxxx g
1!
#250
0!
#255
b10 Z
b10 Q
12
b0 h
bx /
bx B
bx ]
bx f
b110 .
b110 >
b110 E
b110 S
b110 \
b110 e
1!
#260
0!
#265
b10 5
02
1!
#270
0!
#275
1C
b11 5
13
1!
#280
0!
#285
0C
03
b10 U
b1 J
1!
#290
0!
#295
b10 J
1$
1L
0%
0M
b0 U
b11 0
b11 :
b11 T
b11 d
1!
#300
0!
#305
b101 m
b1 o
b10111 (
b10111 8
b10111 D
b10111 O
b10111 Y
b10111 n
b11 J
0$
0L
1!
#310
0!
#315
b100 J
b10111 G
1!
#320
0!
#325
b101 J
1$
1L
1!
#330
0!
#335
1'
b110 J
0$
0L
bx m
b0 o
b101 (
b101 8
b101 D
b101 O
b101 Y
b101 n
1!
#340
0!
#345
b111 J
b101 H
1!
#350
0!
#355
b1000 J
b11100 I
1!
#360
0!
#365
b1001 J
b11100 #
b11100 6
b11100 l
b11100 K
1%
1M
1!
#370
0!
#375
11
0'
1A
b0 J
0%
0M
b11100 m
b1 o
1!
#380
0!
#385
01
b0 5
z$
zL
z%
zM
bz #
bz 6
bz l
bz K
0A
1!
#390
0!
#395
b1 5
14
1!
#400
0!
#405
04
b1 h
1!
#410
0!
#415
b10 h
b1000000010 g
1!
#420
0!
#425
b0 Q
12
b0 h
b10 /
b10 B
b10 ]
b10 f
b10 .
b10 >
b10 E
b10 S
b10 \
b10 e
1!
#430
0!
#435
02
b10 5
1!
#440
0!
#445
1X
b11 5
13
1!
#450
0!
#455
0X
b101 `
b10 U
03
1!
#460
0!
#465
b0 U
b100 0
b100 :
b100 T
b100 d
b110 `
1$
1b
0%
0c
1!
#470
0!
#475
1'
b111 `
bx m
b0 o
b11100 (
b11100 8
b11100 D
b11100 O
b11100 Y
b11100 n
1!
#480
0!
#485
11
17
b0 `
b10 -
b10 =
b10 ^
b10 i
b11100 ,
b11100 <
b11100 _
b11100 j
0*
1)
1!
#490
0!
#495
01
z)
z*
bz -
bz =
bz ^
bz i
bz ,
bz <
bz _
bz j
z$
zb
z%
zc
07
b0 5
1!
#500
0!
#505
b1 5
14
1!
#510
0!
#515
b1 h
04
1!
#520
0!
#525
b10 h
b100000010 g
1!
#530
0!
#535
b1 Z
b1 Q
0F
12
b0 h
b1 .
b1 >
b1 E
b1 S
b1 \
b1 e
1!
#540
0!
#545
b10 5
02
1!
#550
0!
#555
1X
b11 5
13
1!
#560
0!
#565
0X
03
b10 U
b11 `
1!
#570
0!
#575
b11100 +
b11100 ;
b11100 [
b11100 k
b1 `
b10 -
b10 =
b10 ^
b10 i
0)
1*
b0 U
b101 0
b101 :
b101 T
b101 d
1!
#580
0!
#585
b10 `
b11100 #
b11100 6
b11100 l
b11100 a
0$
0b
0*
1!
#590
0!
#595
11
17
b0 `
1%
1c
1!
#600
0!
#605
01
0'
b11100 m
b1 o
b0 5
z)
z*
bz -
bz =
bz ^
bz i
z$
zb
z%
zc
bz #
bz 6
bz l
bz a
07
1!
#610
0!
#615
b1 5
14
1!
#620
0!
#625
04
b1 h
1!
#630
0!
#635
b10 h
1!
#640
0!
#645
12
b0 h
1!
#650
0!
#655
02
b10 5
1!
#660
0!
#665
1X
b11 5
13
1!
#670
0!
#675
0X
b11 `
b10 U
03
1!
#680
0!
