AZ5/DP.v
`define ST_INIT     3'b000
`define ST_ADD      3'b001
`define ST_SUB      3'b010
`define ST_SHIFT    3'b011
`define ST_CHOOSE   3'b100

module DP (control,
           IN1,
           IN2,
           OUT,
           status,
           EF,
           rstn,
           clk);
    parameter BIT_LEN = 4;
    
    input [2:0]control;
    input [BIT_LEN-1:0]IN1;
    input [BIT_LEN-1:0]IN2;
    input clk, rstn;
    
    output [2*BIT_LEN-1:0]OUT;
    output [2:0]status;
    output EF;
    output reg BO;
    
    reg [BIT_LEN-1:0] A, B, X;
    reg[$clog2(BIT_LEN):0] cont;
    
    assign OUT    = (EF)? {X,B}: OUT;
    assign status = {B[0], BO,EF};
    assign EF     = (cont == 0);
    
    always @(posedge clk, negedge rstn) begin
        if (!rstn) begin
            A    <= IN1;
            B    <= IN2;
            X    <= 0;
            cont <= BIT_LEN;
            BO   <= 0;
        end
        else begin
            case (control)
                `ST_INIT:
                begin
                    cont <= BIT_LEN;
                    A    <= IN1;
                    B    <= IN2;
                    X    <= 0;
                    BO   <= 0;
                end
                `ST_ADD:
                begin
                    X <= X + A;
                end
                `ST_SUB:
                begin
                    X <= X - A;
                end
                `ST_SHIFT:
                begin
                    BO    <= B[0];
                    {X,B} <= {X[BIT_LEN-1], X, B[BIT_LEN-1:1]};
                    cont  <= cont - 1;
                end
                `ST_CHOOSE:
                begin
                    //do nothing
                end
            endcase
        end
    end
    
endmodule

AZ5/CU.v
`define ST_INIT     3'b000
`define ST_ADD      3'b001
`define ST_SUB      3'b010
`define ST_SHIFT    3'b011
`define ST_CHOOSE   3'b100

module CU(clk,
          status,
          control,
          rstn,
          start);
    
    input [2:0] status;
    input clk, rstn, start;
    output [2:0] control;
    
    wire B0, BO, FIN;
    reg [2:0] state;
    reg [2:0] next_state;
    
    assign B0      = status[2];
    assign BO      = status[1];
    assign FIN     = status[0];
    assign control = state;
    
    always @(posedge clk or negedge rstn) begin
        if (!rstn)
            state <= `ST_INIT;
        else
            state <= next_state;
    end
    
    
    always @(state or B0 or BO or FIN or start) begin
        case (state)
            `ST_INIT:
            begin
                if (start) begin
                    next_state <= `ST_CHOOSE;
                end
            end
            `ST_ADD:
            begin
                next_state <= `ST_SHIFT;
            end
            `ST_SUB:
            begin
                next_state <= `ST_SHIFT;
            end
            `ST_SHIFT:
            begin
                if (FIN)
                    next_state <= `ST_INIT;
                else
                    next_state <= `ST_CHOOSE;
            end
            `ST_CHOOSE:
            begin
                if (B0 && !BO)
                    next_state <= `ST_SUB;
                else if (!B0 && BO)
                    next_state <= `ST_ADD;
                else
                    next_state <= `ST_SHIFT;
            end
        endcase
    end
    
    
endmodule

AZ5/MUL_BOOTH.v
module MUL_BOOTH(in1,
                 in2,
                 out,
                 out_r,
                 clk,
                 start,
                 rstn);
    parameter BIT_LEN = 4;
    
    input [BIT_LEN-1:0] in1, in2;
    input clk, start, rstn;
    output [2*BIT_LEN-1:0] out;
    output out_r;
    
    wire [2:0] status, control;
    
    CU cu (
    .status(status),
    .control(control),
    .start(start),
    .rstn(rstn),
    .clk(clk)
    );
    
    DP #(.BIT_LEN(BIT_LEN)) dp(
    .control(control),
    .IN1(in1),
    .IN2(in2),
    .OUT(out),
    .status(status),
    .EF(out_r),
    .rstn(rstn),
    .clk(clk)
    );
    
endmodule //mul_booth

AZ5/testbench.v
`define NULL 0
module testbench();
    
    parameter BIT_LEN = 4;
    parameter clk_c   = 5;
    wire out_r;
    reg clk, start, rstn;
    reg signed [BIT_LEN - 1:0] in1, in2;
    wire signed [2 * BIT_LEN - 1:0] out;
    
    MUL_BOOTH #(.BIT_LEN(BIT_LEN)) mb (
    .in1(in1),
    .in2(in2),
    .out(out),
    .out_r(out_r),
    .clk(clk),
    .start(start),
    .rstn(rstn)
    );
    
    
    initial begin
        $dumpfile("report/waveform.vcd");
        $dumpvars(0,mb);
    end
    
    integer data_file;
    integer scan_file;
    integer seed;
    initial begin
        data_file = $fopen("seed.dat", "r");
        if (data_file == `NULL) begin
            $display("data_file handle was NULL");
            $finish;
        end
        scan_file = $fscanf(data_file, "%d", seed);
        if (scan_file == `NULL) begin
            $display("integer read error");
            $finish;
        end
    end
    
    
    initial begin
        clk         = 0;
        forever clk = #(clk_c/2) ~clk;
    end
    
    integer i,n;
    initial begin
        rstn  = 0;
        start = 0;
        n     = {$random(seed)}%15 + 10;
        for (i = 0; i < n; i = i+1) begin
            rstn = 0;
            #clk_c;
            in1   = {BIT_LEN{$random(seed)}};
            in2   = {BIT_LEN{$random(seed)}};
            rstn  = 1;
            start = 1;
            while (!out_r)
            begin
                #clk_c;
            end
        end
        $finish;
    end
    
    initial
        $monitor($time, "  %d * %d = %d _______ A:%b, XB:%b%b, state = %d, next_state = %d, count = %d , B0,B-1 = %b%b, out_ready = %b",in1, in2, out, mb.dp.A, mb.dp.X, mb.dp.B, mb.cu.state, mb.cu.next_state, mb.dp.cont, mb.cu.B0, mb.cu.BO, out_r);
    
endmodule

AZ5/report/waveform.vcd
$date
	Fri Apr 16 18:42:21 2021
$end
$version
	Icarus Verilog
$end
$timescale
	1s
$end
$scope module testbench $end
$scope module mb $end
$var wire 1 ! clk $end
$var wire 4 " in1 [3:0] $end
$var wire 4 # in2 [3:0] $end
$var wire 1 $ rstn $end
$var wire 1 % start $end
$var wire 3 & status [2:0] $end
$var wire 1 ' out_r $end
$var wire 8 ( out [7:0] $end
$var wire 3 ) control [2:0] $end
$scope module cu $end
$var wire 1 ! clk $end
$var wire 3 * control [2:0] $end
$var wire 1 $ rstn $end
$var wire 1 % start $end
$var wire 3 + status [2:0] $end
$var wire 1 , FIN $end
$var wire 1 - BO $end
$var wire 1 . B0 $end
$var reg 3 / next_state [2:0] $end
$var reg 3 0 state [2:0] $end
$upscope $end
$scope module dp $end
$var wire 4 1 IN1 [3:0] $end
$var wire 4 2 IN2 [3:0] $end
$var wire 1 ! clk $end
$var wire 3 3 control [2:0] $end
$var wire 1 $ rstn $end
$var wire 3 4 status [2:0] $end
$var wire 8 5 OUT [7:0] $end
$var wire 1 ' EF $end
$var reg 4 6 A [3:0] $end
$var reg 4 7 B [3:0] $end
$var reg 1 8 BO $end
$var reg 4 9 X [3:0] $end
$var reg 3 : cont [2:0] $end
$upscope $end
$upscope $end
$upscope $end
$enddefinitions $end
#0
$dumpvars
b100 :
b0 9
08
bx 7
bx 6
bx 5
bx00 4
b0 3
bx 2
bx 1
b0 0
bx /
x.
0-
0,
bx00 +
b0 *
b0 )
bx (
0'
bx00 &
0%
0$
bx #
bx "
0!
$end
#2
1!
#4
0!
#5
b100 /
1%
1$
b11 #
b11 2
b1010 "
b1010 1
#6
b10 /
1.
b100 &
b100 +
b100 4
b100 )
b100 *
b100 3
b100 0
b11 7
b1010 6
1!
#8
0!
#10
b11 /
b10 )
b10 *
b10 3
b10 0
1!
#12
0!
#14
b100 /
b11 )
b11 *
b11 3
b11 0
b110 9
1!
#16
0!
#18
b11 /
1-
b11 :
b11 9
b1 7
b110 &
b110 +
b110 4
18
b100 )
b100 *
b100 3
b100 0
1!
#20
0!
#22
b100 /
b11 )
b11 *
b11 3
b11 0
1!
#24
0!
#26
b1 /
0.
b10 &
b10 +
b10 4
b10 :
b1 9
b1000 7
b100 )
b100 *
b100 3
b100 0
1!
#28
0!
#30
b11 /
b1 )
b1 *
b1 3
b1 0
1!
#32
0!
#34
b100 /
b1011 9
b11 )
b11 *
b11 3
b11 0
1!
#36
0!
#38
b11 /
0-
b100 )
b100 *
b100 3
b100 0
b1 :
b1101 9
b1100 7
b0 &
b0 +
b0 4
08
1!
#40
0!
#42
b100 /
b11 )
b11 *
b11 3
b11 0
1!
#44
0!
#46
b11 /
1,
b11101110 (
b11101110 5
b100 )
b100 *
b100 3
b100 0
b1 &
b1 +
b1 4
1'
b0 :
b1110 9
b1110 7
1!
#48
0!
#50
b100 /
1.
0,
b100 &
b100 +
b100 4
0'
b100 :
b0 9
b11 7
b0 )
b0 *
b0 3
b0 0
1!
0$
#52
0!
#54
1!
#55
1$
#56
0!
#58
b10 /
b100 )
b100 *
b100 3
b100 0
1!
#60
0!
#62
b11 /
b10 )
b10 *
b10 3
b10 0
1!
#64
0!
#66
b100 /
b110 9
b11 )
b11 *
b11 3
b11 0
1!
#68
0!
#70
b11 /
1-
b100 )
b100 *
b100 3
b100 0
b11 :
b11 9
b1 7
b110 &
b110 +
b110 4
18
1!
#72
0!
#74
b100 /
b11 )
b11 *
b11 3
b11 0
1!
#76
0!
#78
b1 /
0.
b10 &
b10 +
b10 4
b100 )
b100 *
b100 3
b100 0
b10 :
b1 9
b1000 7
1!
#80
0!
#82
b11 /
b1 )
b1 *
b1 3
b1 0
1!
#84
0!
#86
b100 /
b11 )
b11 *
b11 3
b11 0
b1011 9
1!
#88
0!
#90
b11 /
0-
b1 :
b1101 9
b1100 7
b0 &
b0 +
b0 4
08
b100 )
b100 *
b100 3
b100 0
1!
#92
0!
#94
b100 /
b11 )
b11 *
b11 3
b11 0
1!
#96
0!
#98
b11 /
1,
b1 &
b1 +
b1 4
1'
b0 :
b1110 9
b1110 7
b100 )
b100 *
b100 3
b100 0
1!
#100
b100 /
1.
0,
b0 )
b0 *
b0 3
b0 0
b100 &
b100 +
b100 4
0'
b100 :
b0 9
b11 7
0!
0$
#102
1!
#104
0!
#105
1$
b110 #
b110 2
b1011 "
b1011 1
#106
b11 /
0.
b0 &
b0 +
b0 4
b100 )
b100 *
b100 3
b100 0
b110 7
b1011 6
1!
#108
0!
#110
b100 /
b11 )
b11 *
b11 3
b11 0
1!
#112
0!
#114
b10 /
1.
b100 &
b100 +
b100 4
b100 )
b100 *
b100 3
b100 0
b11 :
b11 7
1!
#116
0!
#118
b11 /
b10 )
b10 *
b10 3
b10 0
1!
#120
0!
#122
b100 /
b11 )
b11 *
b11 3
b11 0
b101 9
1!
#124
0!
#126
b11 /
1-
b10 :
b10 9
b1001 7
b110 &
b110 +
b110 4
18
b100 )
b100 *
b100 3
b100 0
1!
#128
0!
#130
b100 /
b11 )
b11 *
b11 3
b11 0
1!
#132
0!
#134
b1 /
0.
b10 &
b10 +
b10 4
b1 :
b1 9
b100 7
b100 )
b100 *
b100 3
b100 0
1!
#136
0!
#138
b11 /
b1 )
b1 *
b1 3
b1 0
1!
#140
0!
#142
b100 /
b1100 9
b11 )
b11 *
b11 3
b11 0
1!
#144
0!
#146
b11 /
1,
b11100010 (
b11100010 5
0-
b100 )
b100 *
b100 3
b100 0
1'
b0 :
b1110 9
b10 7
b1 &
b1 +
b1 4
08
1!
#148
0!
#150
b100 /
0,
b0 &
b0 +
b0 4
0'
b100 :
b0 9
b110 7
b0 )
b0 *
b0 3
b0 0
1!
0$
#152
0!
#154
1!
#155
1$
b1001 "
b1001 1
#156
0!
#158
b11 /
b1001 6
b100 )
b100 *
b100 3
b100 0
1!
#160
0!
#162
b100 /
b11 )
b11 *
b11 3
b11 0
1!
#164
0!
#166
b10 /
1.
b100 &
b100 +
b100 4
b11 :
b11 7
b100 )
b100 *
b100 3
b100 0
1!
#168
0!
#170
b11 /
b10 )
b10 *
b10 3
b10 0
1!
#172
0!
#174
b100 /
b111 9
b11 )
b11 *
b11 3
b11 0
1!
#176
0!
#178
b11 /
1-
b100 )
b100 *
b100 3
b100 0
b10 :
b11 9
b1001 7
b110 &
b110 +
b110 4
18
1!
#180
0!
#182
b100 /
b11 )
b11 *
b11 3
b11 0
1!
#184
0!
#186
b1 /
0.
b10 &
b10 +
b10 4
b100 )
b100 *
b100 3
b100 0
b1 :
b1 9
b1100 7
1!
#188
0!
#190
b11 /
b1 )
b1 *
b1 3
b1 0
1!
#192
0!
#194
b100 /
b11 )
b11 *
b11 3
b11 0
b1010 9
1!
#196
0!
#198
b11 /
1,
b11010110 (
b11010110 5
0-
1'
b0 :
b1101 9
b110 7
b1 &
b1 +
b1 4
08
b100 )
b100 *
b100 3
b100 0
1!
#200
b100 /
0,
b0 )
b0 *
b0 3
b0 0
b0 &
b0 +
b0 4
0'
b100 :
b0 9
0!
0$
#202
1!
#204
0!
#205
1$
b1101 #
b1101 2
b1010 "
b1010 1
#206
b10 /
1.
b100 &
b100 +
b100 4
b100 )
b100 *
b100 3
b100 0
b1101 7
b1010 6
1!
#208
0!
#210
b11 /
b10 )
b10 *
b10 3
b10 0
1!
#212
0!
#214
b100 /
b11 )
b11 *
b11 3
b11 0
b110 9
1!
#216
0!
#218
b1 /
0.
1-
b11 :
b11 9
b110 7
b10 &
b10 +
b10 4
18
b100 )
b100 *
b100 3
b100 0
1!
#220
0!
#222
b11 /
b1 )
b1 *
b1 3
b1 0
1!
#224
0!
#226
b100 /
b1101 9
b11 )
b11 *
b11 3
b11 0
1!
#228
0!
#230
b10 /
1.
0-
b100 )
b100 *
b100 3
b100 0
b10 :
b1110 9
b1011 7
b100 &
b100 +
b100 4
08
1!
#232
0!
#234
b11 /
b10 )
b10 *
b10 3
b10 0
1!
#236
0!
#238
b100 /
b11 )
b11 *
b11 3
b11 0
b100 9
1!
#240
0!
#242
b11 /
1-
b1 :
b10 9
b101 7
b110 &
b110 +
b110 4
18
b100 )
b100 *
b100 3
b100 0
1!
#244
0!
#246
b100 /
b11 )
b11 *
b11 3
b11 0
1!
#248
0!
#250
b1 /
0.
1,
b10010 (
b10010 5
b11 &
b11 +
b11 4
1'
b0 :
b1 9
b10 7
b100 )
b100 *
b100 3
b100 0
1!
#252
0!
#254
b11 /
b1 )
b1 *
b1 3
b1 0
1!
#255
b100 /
1.
0-
0,
08
b100 &
b100 +
b100 4
0'
b100 :
b0 9
b1101 7
b0 )
b0 *
b0 3
b0 0
0$
#256
0!
#258
1!
#260
0!
1$
b11 #
b11 2
b10 "
b10 1
#262
b10 /
b11 7
b10 6
b100 )
b100 *
b100 3
b100 0
1!
#264
0!
#266
b11 /
b10 )
b10 *
b10 3
b10 0
1!
#268
0!
#270
b100 /
b1110 9
b11 )
b11 *
b11 3
b11 0
1!
#272
0!
#274
b11 /
1-
b100 )
b100 *
b100 3
b100 0
b11 :
b1111 9
b1 7
b110 &
b110 +
b110 4
18
1!
#276
0!
#278
b100 /
b11 )
b11 *
b11 3
b11 0
1!
#280
0!
#282
b1 /
0.
b10 &
b10 +
b10 4
b100 )
b100 *
b100 3
b100 0
b10 :
b1000 7
1!
#284
0!
#286
b11 /
b1 )
b1 *
b1 3
b1 0
1!
#288
0!
#290
b100 /
b11 )
b11 *
b11 3
b11 0
b1 9
1!
#292
0!
#294
b11 /
0-
b1 :
b0 9
b1100 7
b0 &
b0 +
b0 4
08
b100 )
b100 *
b100 3
b100 0
1!
#296
0!
#298
b100 /
b11 )
b11 *
b11 3
b11 0
1!
#300
0!
#302
b11 /
1,
b110 (
b110 5
b1 &
b1 +
b1 4
1'
b0 :
b110 7
b100 )
b100 *
b100 3
b100 0
1!
#304
0!
#305
b100 /
1.
0,
b0 )
b0 *
b0 3
b0 0
b100 &
b100 +
b100 4
0'
b100 :
b11 7
0$
#306
1!
#308
0!
#310
b11 /
0.
b0 &
b0 +
b0 4
b100 )
b100 *
b100 3
b100 0
b100 7
b1011 6
1!
1$
b100 #
b100 2
b1011 "
b1011 1
#312
0!
#314
b100 /
b11 )
b11 *
b11 3
b11 0
1!
#316
0!
#318
b11 /
b100 )
b100 *
b100 3
b100 0
b11 :
b10 7
1!
#320
0!
#322
b100 /
b11 )
b11 *
b11 3
b11 0
1!
#324
0!
#326
b10 /
1.
b100 &
b100 +
b100 4
b100 )
b100 *
b100 3
b100 0
b10 :
b1 7
1!
#328
0!
#330
b11 /
b10 )
b10 *
b10 3
b10 0
1!
#332
0!
#334
b100 /
b11 )
b11 *
b11 3
b11 0
b101 9
1!
#336
0!
#338
b1 /
0.
1-
b1 :
b10 9
b1000 7
b10 &
b10 +
b10 4
18
b100 )
b100 *
b100 3
b100 0
1!
#340
0!
#342
b11 /
b1 )
b1 *
b1 3
b1 0
1!
#344
0!
#346
b100 /
b1101 9
b11 )
b11 *
b11 3
b11 0
1!
#348
0!
#350
b11 /
1,
b11101100 (
b11101100 5
0-
b100 )
b100 *
b100 3
b100 0
1'
b0 :
b1110 9
b1100 7
b1 &
b1 +
b1 4
08
1!
#352
0!
#354
b0 /
b11 )
b11 *
b11 3
b11 0
1!
#355
b100 /
0,
b0 )
b0 *
b0 3
b0 0
b0 &
b0 +
b0 4
0'
b100 :
b0 9
b100 7
0$
#356
0!
#358
1!
#360
0!
1$
b1100 "
b1100 1
#362
b11 /
b100 )
b100 *
b100 3
b100 0
b1100 6
1!
#364
0!
#366
b100 /
b11 )
b11 *
b11 3
b11 0
1!
#368
0!
#370
b11 /
b100 )
b100 *
b100 3
b100 0
b11 :
b10 7
1!
#372
0!
#374
b100 /
b11 )
b11 *
b11 3
b11 0
1!
#376
0!
#378
b10 /
1.
b100 &
b100 +
b100 4
b100 )
b100 *
b100 3
b100 0
b10 :
b1 7
1!
#380
0!
#382
b11 /
b10 )
b10 *
b10 3
b10 0
1!
#384
0!
#386
b100 /
b11 )
b11 *
b11 3
b11 0
b100 9
1!
#388
0!
#390
b1 /
0.
1-
b1 :
b10 9
b0 7
b10 &
b10 +
b10 4
18
b100 )
b100 *
b100 3
b100 0
1!
#392
0!
#394
b11 /
b1 )
b1 *
b1 3
b1 0
1!
#396
0!
#398
b100 /
b1110 9
b11 )
b11 *
b11 3
b11 0
1!
#400
0!
#402
b11 /
1,
b11110000 (
b11110000 5
0-
b100 )
b100 *
b100 3
b100 0
1'
b0 :
b1111 9
b1 &
b1 +
b1 4
08
1!
#404
0!
#405
b100 /
0,
b0 &
b0 +
b0 4
0'
b100 :
b0 9
b100 7
b0 )
b0 *
b0 3
b0 0
0$
#406
1!
#408
0!
#410
b10 /
1.
b100 &
b100 +
b100 4
b111 7
b1 6
b100 )
b100 *
b100 3
b100 0
1!
1$
b111 #
b111 2
b1 "
b1 1
#412
0!
#414
b11 /
b10 )
b10 *
b10 3
b10 0
1!
#416
0!
#418
b100 /
b1111 9
b11 )
b11 *
b11 3
b11 0
1!
#420
0!
#422
b11 /
1-
b100 )
b100 *
b100 3
b100 0
b11 :
b1011 7
b110 &
b110 +
b110 4
18
1!
#424
0!
#426
b100 /
b11 )
b11 *
b11 3
b11 0
1!
#428
0!
#430
b11 /
b100 )
b100 *
b100 3
b100 0
b10 :
b1101 7
1!
#432
0!
#434
b100 /
b11 )
b11 *
b11 3
b11 0
1!
#436
0!
#438
b1 /
0.
b10 &
b10 +
b10 4
b100 )
b100 *
b100 3
b100 0
b1 :
b1110 7
1!
#440
0!
#442
b11 /
b1 )
b1 *
b1 3
b1 0
1!
#444
0!
#446
b100 /
b11 )
b11 *
b11 3
b11 0
b0 9
1!
#448
0!
#450
b10 /
1.
1,
b111 (
b111 5
0-
1'
b0 :
b111 7
b101 &
b101 +
b101 4
08
b100 )
b100 *
b100 3
b100 0
1!
#452
0!
#454
b11 /
b10 )
b10 *
b10 3
b10 0
1!
#455
b100 /
0,
b100 &
b100 +
b100 4
0'
b100 :
b0 )
b0 *
b0 3
b0 0
0$
#456
0!
#458
1!
#460
0!
1$
#462
b10 /
b100 )
b100 *
b100 3
b100 0
1!
#464
0!
#466
b11 /
b10 )
b10 *
b10 3
b10 0
1!
#468
0!
#470
b100 /
b1111 9
b11 )
b11 *
b11 3
b11 0
1!
#472
0!
#474
b11 /
1-
b100 )
b100 *
b100 3
b100 0
b11 :
b1011 7
b110 &
b110 +
b110 4
18
1!
#476
0!
#478
b100 /
b11 )
b11 *
b11 3
b11 0
1!
#480
0!
#482
b11 /
b100 )
b100 *
b100 3
b100 0
b10 :
b1101 7
1!
#484
0!
#486
b100 /
b11 )
b11 *
b11 3
b11 0
1!
#488
0!
#490
b1 /
0.
b10 &
b10 +
b10 4
b100 )
b100 *
b100 3
b100 0
b1 :
b1110 7
1!
#492
0!
#494
b11 /
b1 )
b1 *
b1 3
b1 0
1!
#496
0!
#498
b100 /
b11 )
b11 *
b11 3
b11 0
b0 9
1!
#500
0!
#502
b10 /
1.
1,
0-
1'
b0 :
b111 7
b101 &
b101 +
b101 4
08
b100 )
b100 *
b100 3
b100 0
1!
#504
0!
#505
b100 /
0,
b0 )
b0 *
b0 3
b0 0
b100 &
b100 +
b100 4
0'
b100 :
0$
#506
1!
#508
0!
#510
b11 /
0.
b0 &
b0 +
b0 4
b100 )
b100 *
b100 3
b100 0
b10 7
1!
1$
b10 #
b10 2
#512
0!
#514
b100 /
b11 )
b11 *
b11 3
b11 0
1!
#516
0!
#518
b10 /
1.
b100 &
b100 +
b100 4
b100 )
b100 *
b100 3
b100 0
b11 :
b1 7
1!
#520
0!
#522
b11 /
b10 )
b10 *
b10 3
b10 0
1!
#524
0!
#526
b100 /
b11 )
b11 *
b11 3
b11 0
b1111 9
1!
#528
0!
#530
b1 /
0.
1-
b10 :
b1000 7
b10 &
b10 +
b10 4
18
b100 )
b100 *
b100 3
b100 0
1!
#532
0!
#534
b11 /
b1 )
b1 *
b1 3
b1 0
1!
#536
0!
#538
b100 /
b0 9
b11 )
b11 *
b11 3
b11 0
1!
#540
0!
#542
b11 /
0-
b100 )
b100 *
b100 3
b100 0
b1 :
b100 7
b0 &
b0 +
b0 4
08
1!
#544
0!
#546
b100 /
b11 )
b11 *
b11 3
b11 0
1!
#548
0!
#550
b11 /
1,
b10 (
b10 5
b100 )
b100 *
b100 3
b100 0
b1 &
b1 +
b1 4
1'
b0 :
b10 7
1!
#552
0!
#554
b0 /
b11 )
b11 *
b11 3
b11 0
1!
#555
b100 /
0,
b0 )
b0 *
b0 3
b0 0
b0 &
b0 +
b0 4
0'
b100 :
0$
#556
0!
#558
1!
#560
0!
1$
b111 #
b111 2
b0 "
b0 1
#562
b10 /
1.
b100 &
b100 +
b100 4
b100 )
b100 *
b100 3
b100 0
b111 7
b0 6
1!
#564
0!
#566
b11 /
b10 )
b10 *
b10 3
b10 0
1!
#568
0!
#570
b100 /
b11 )
b11 *
b11 3
b11 0
1!
#572
0!
#574
b11 /
1-
b11 :
b11 7
b110 &
b110 +
b110 4
18
b100 )
b100 *
b100 3
b100 0
1!
#576
0!
#578
b100 /
b11 )
b11 *
b11 3
b11 0
1!
#580
0!
#582
b11 /
b10 :
b1 7
b100 )
b100 *
b100 3
b100 0
1!
#584
0!
#586
b100 /
b11 )
b11 *
b11 3
b11 0
1!
#588
0!
#590
b1 /
0.
b10 &
b10 +
b10 4
b1 :
b0 7
b100 )
b100 *
b100 3
b100 0
1!
#592
0!
#594
b11 /
b1 )
b1 *
b1 3
b1 0
1!
#596
0!
#598
b100 /
b11 )
b11 *
b11 3
b11 0
1!
#600
0!
#602
b11 /
1,
b0 (
b0 5
0-
b100 )
b100 *
b100 3
b100 0
1'
b0 :
b1 &
b1 +
b1 4
08
1!
#604
0!
#605
b100 /
1.
0,
b100 &
b100 +
b100 4
0'
b100 :
b111 7
b0 )
b0 *
b0 3
b0 0
0$
#606
1!
#608
0!
#610
b10 /
b1001 6
b100 )
b100 *
b100 3
b100 0
1!
1$
b1001 "
b1001 1
#612
0!
#614
b11 /
b10 )
b10 *
b10 3
b10 0
1!
#616
0!
#618
b100 /
b111 9
b11 )
b11 *
b11 3
b11 0
1!
#620
0!
#622
b11 /
1-
b100 )
b100 *
b100 3
b100 0
b11 :
b11 9
b1011 7
b110 &
b110 +
b110 4
18
1!
#624
0!
#626
b100 /
b11 )
b11 *
b11 3
b11 0
1!
#628
0!
#630
b11 /
b100 )
b100 *
b100 3
b100 0
b10 :
b1 9
b1101 7
1!
#632
0!
#634
b100 /
b11 )
b11 *
b11 3
b11 0
1!
#636
0!
#638
b1 /
0.
b10 &
b10 +
b10 4
b100 )
b100 *
b100 3
b100 0
b1 :
b0 9
b1110 7
1!
#640
0!
#642
b11 /
b1 )
b1 *
b1 3
b1 0
1!
#644
0!
#646
b100 /
b11 )
b11 *
b11 3
b11 0
b1001 9
1!
#648
0!
#650
b10 /
1.
1,
b11001111 (
b11001111 5
0-
1'
b0 :
b1100 9
b1111 7
b101 &
b101 +
b101 4
08
b100 )
b100 *
b100 3
b100 0
1!
#652
0!
#654
b11 /
b10 )
b10 *
b10 3
b10 0
1!
#655
b100 /
0,
b100 &
b100 +
b100 4
0'
b100 :
b0 9
b111 7
b0 )
b0 *
b0 3
b0 0
0$
#656
0!
#658
1!
#660
0!
1$
b1 #
b1 2
b1011 "
b1011 1
#662
b10 /
b1 7
b1011 6
b100 )
b100 *
b100 3
b100 0
1!
#664
0!
#666
b11 /
b10 )
b10 *
b10 3
b10 0
1!
#668
0!
#670
b100 /
b101 9
b11 )
b11 *
b11 3
b11 0
1!
#672
0!
#674
b1 /
0.
1-
b100 )
b100 *
b100 3
b100 0
b11 :
b10 9
b1000 7
b10 &
b10 +
b10 4
18
1!
#676
0!
#678
b11 /
b1 )
b1 *
b1 3
b1 0
1!
#680
0!
#682
b100 /
b11 )
b11 *
b11 3
b11 0
b1101 9
1!
#684
0!
#686
b11 /
0-
b10 :
b1110 9
b1100 7
b0 &
b0 +
b0 4
08
b100 )
b100 *
b100 3
b100 0
1!
#688
0!
#690
b100 /
b11 )
b11 *
b11 3
b11 0
1!
#692
0!
#694
b11 /
b1 :
b1111 9
b110 7
b100 )
b100 *
b100 3
b100 0
1!
#696
0!
#698
b100 /
b11 )
b11 *
b11 3
b11 0
1!
#700
0!
#702
b10 /
1.
1,
b11111011 (
b11111011 5
b101 &
b101 +
b101 4
1'
b0 :
b1011 7
b100 )
b100 *
b100 3
b100 0
1!
#704
0!
#705
b100 /
0,
b0 )
b0 *
b0 3
b0 0
b100 &
b100 +
b100 4
0'
b100 :
b0 9
b1 7
0$
#706
1!
#708
0!
#710
b10 /
b100 )
b100 *
b100 3
b100 0
b1011 7
b1001 6
1!
1$
b1011 #
b1011 2
b1001 "
b1001 1
#712
0!
#714
b11 /
b10 )
b10 *
b10 3
b10 0
1!
#716
0!
#718
b100 /
b11 )
b11 *
b11 3
b11 0
b111 9
1!
#720
0!
#722
b11 /
1-
b11 :
b11 9
b1101 7
b110 &
b110 +
b110 4
18
b100 )
b100 *
b100 3
b100 0
1!
#724
0!
#726
b100 /
b11 )
b11 *
b11 3
b11 0
1!
#728
0!
#730
b1 /
0.
b10 &
b10 +
b10 4
b10 :
b1 9
b1110 7
b100 )
b100 *
b100 3
b100 0
1!
#732
0!
#734
b11 /
b1 )
b1 *
b1 3
b1 0
1!
#736
0!
#738
b100 /
b1010 9
b11 )
b11 *
b11 3
b11 0
1!
#740
0!
#742
b10 /
1.
0-
b100 )
b100 *
b100 3
b100 0
b1 :
b1101 9
b111 7
b100 &
b100 +
b100 4
08
1!
#744
0!
#746
b11 /
b10 )
b10 *
b10 3
b10 0
1!
#748
0!
#750
b100 /
b11 )
b11 *
b11 3
b11 0
b100 9
1!
#752
0!
#754
b11 /
1,
b100011 (
b100011 5
1-
1'
b0 :
b10 9
b11 7
b111 &
b111 +
b111 4
18
b100 )
b100 *
b100 3
b100 0
1!
#755
b100 /
0-
0,
b0 )
b0 *
b0 3
b0 0
08
b100 &
b100 +
b100 4
0'
b100 :
b0 9
b1011 7
0$
#756
0!
#758
1!
#760
0!
1$
b1100 #
b1100 2
b1011 "
b1011 1
#762
b11 /
0.
b0 &
b0 +
b0 4
b100 )
b100 *
b100 3
b100 0
b1100 7
b1011 6
1!
#764
0!
#766
b100 /
b11 )
b11 *
b11 3
b11 0
1!
#768
0!
#770
b11 /
b100 )
b100 *
b100 3
b100 0
b11 :
b110 7
1!
#772
0!
#774
b100 /
b11 )
b11 *
b11 3
b11 0
1!
#776
0!
#778
b10 /
1.
b100 &
b100 +
b100 4
b100 )
b100 *
b100 3
b100 0
b10 :
b11 7
1!
#780
0!
#782
b11 /
b10 )
b10 *
b10 3
b10 0
1!
#784
0!
#786
b100 /
b11 )
b11 *
b11 3
b11 0
b101 9
1!
#788
0!
#790
b11 /
1-
b1 :
b10 9
b1001 7
b110 &
b110 +
b110 4
18
b100 )
b100 *
b100 3
b100 0
1!
#792
0!
#794
b100 /
b11 )
b11 *
b11 3
b11 0
1!
#796
0!
#798
b1 /
0.
1,
b10100 (
b10100 5
b11 &
b11 +
b11 4
1'
b0 :
b1 9
b100 7
b100 )
b100 *
b100 3
b100 0
1!
#800
b100 /
0-
0,
b0 )
b0 *
b0 3
b0 0
08
b0 &
b0 +
b0 4
0'
b100 :
b0 9
b1100 7
0!
0$
#802
1!
#804
0!
#805
1$
b1110 #
b1110 2
b111 "
b111 1
#806
b11 /
b100 )
b100 *
b100 3
b100 0
b1110 7
b111 6
1!
#808
0!
#810
b100 /
b11 )
b11 *
b11 3
b11 0
1!
#812
0!
#814
b10 /
1.
b100 &
b100 +
b100 4
b100 )
b100 *
b100 3
b100 0
b11 :
b111 7
1!
#816
0!
#818
b11 /
b10 )
b10 *
b10 3
b10 0
1!
#820
0!
#822
b100 /
b11 )
b11 *
b11 3
b11 0
b1001 9
1!
#824
0!
#826
b11 /
1-
b10 :
b1100 9
b1011 7
b110 &
b110 +
b110 4
18
b100 )
b100 *
b100 3
b100 0
1!
#828
0!
#830
b100 /
b11 )
b11 *
b11 3
b11 0
1!
#832
0!
#834
b11 /
b1 :
b1110 9
b101 7
b100 )
b100 *
b100 3
b100 0
1!
#836
0!
#838
b100 /
b11 )
b11 *
b11 3
b11 0
1!
#840
0!
#842
b1 /
0.
1,
b11110010 (
b11110010 5
b11 &
b11 +
b11 4
1'
b0 :
b1111 9
b10 7
b100 )
b100 *
b100 3
b100 0
1!
#844
0!
#845
b100 /
0-
0,
b0 )
b0 *
b0 3
b0 0
08
b0 &
b0 +
b0 4
0'
b100 :
b0 9
b1110 7
0$
#846
1!
#848
0!
