AZ5/DP.v


module DP (control,
           IN1,
           IN2,
           OUT,
           status,
           EF,
           rstn);
    parameter BIT_LEN = 4;
    
    input [9:0]control;
    input [BIT_LEN-1:0]IN1;
    input [BIT_LEN-1:0]IN2;
    input rstn;
    
    output [2*BIT_LEN-1:0]OUT;
    output [1:0]status;
    output EF;
    
    reg [BIT_LEN-1:0]A;
    reg [BIT_LEN-1:0]B;
    reg [BIT_LEN-1:0]X;
    reg EF;
    wire LD_A, LD_B, LD_CONT, RST_X, SUB_X, ADD_X, SUB_CONT, SHIFT_XB;
    
    integer cont;
    reg FIN;
    reg B0;
    
    assign OUT                                                                             = {X,B};
    assign status                                                                          = {B0,FIN};
    assign { LD_A, LD_B, LD_CONT, SET_EF, RST_X, RST_EF, SUB_X, SUB_CONT, ADD_X, SHIFT_XB} = control;
    
    always @(control or negedge rstn) begin
        if (!rstn) begin
            FIN = 0;
            B0  = IN2[0];
        end
        else begin
            if (LD_A) A         = IN1;
            if (LD_B) B         = IN2;
            if (LD_CONT) cont   = 2*BIT_LEN;
            if (SET_EF) EF      = 1;
            if (RST_X) X        = 0;
            if (RST_EF) EF      = 0;
            if (ADD_X) X        = X+A;
            if (SUB_X) X        = X-A;
            if (SUB_CONT) cont  = cont -1;
            if (SHIFT_XB) {X,B} = {X[BIT_LEN-1],X,B[BIT_LEN-1:1]};
            
            B0  = B[0];
            FIN = (cont == 0);
        end
    end
    
endmodule

AZ5/DFF.v
module DFF(q,
           clk,
           d);
    input clk,d;
    output reg q;
    
    always @(posedge clk) begin
        q <= d;
    end
    
endmodule

AZ5/CU.v
module CU(clk,
          status,
          control,
          rstn,
          start);
    
    input [1:0] status;
    input clk, rstn, start;
    output [9:0] control;
    
    wire B0, FIN;
    reg LD_A, LD_B, LD_CONT, SET_EF, RST_X,RST_EF, SUB_X, SUB_CONT, ADD_X, SHIFT_XB;
    wire INIT, ADD, SUB, SHIFT1, SHIFT2;
    reg INIT_D, ADD_D, SUB_D, SHIFT1_D, SHIFT2_D;
    
    assign B0      = status[1];
    assign FIN     = status[0];
    assign control = { LD_A, LD_B, LD_CONT, SET_EF, RST_X, RST_EF, SUB_X, SUB_CONT, ADD_X, SHIFT_XB};
    
    always @(INIT or ADD or SUB or SHIFT1 or SHIFT2 or FIN or B0 or posedge clk or negedge rstn) begin
        if (!rstn) begin
            INIT_D   = 1;
            ADD_D    = 0;
            SUB_D    = 0;
            SHIFT1_D = 0;
            SHIFT2_D = 0;
        end
        else begin
            INIT_D   = (INIT && !start) || (SHIFT1 && FIN) || (SHIFT2 && FIN);
            SUB_D    = (INIT && start && B0) || (SHIFT2 && !FIN && B0);
            ADD_D    = (SHIFT1 && !FIN && !B0);
            SHIFT1_D = SUB || (SHIFT1 && !FIN && B0);
            SHIFT2_D = ADD || (INIT && start && !B0) || (SHIFT2 && !FIN && !B0);
        end
    end
    
    DFF init (
    .d(INIT_D),
    .q(INIT),
    .clk(clk)
    );
    
    DFF sub (
    .d(SUB_D),
    .q(SUB),
    .clk(clk)
    );
    
    
    DFF add (
    .d(ADD_D),
    .q(ADD),
    .clk(clk)
    );
    
    
    DFF shift1 (
    .d(SHIFT1_D),
    .q(SHIFT1),
    .clk(clk)
    );
    
    
    DFF shift2 (
    .d(SHIFT2_D),
    .q(SHIFT2),
    .clk(clk)
    );
    
    always @(posedge clk) begin
        LD_A     = (INIT && start);
        LD_B     = (INIT && start);
        LD_CONT  = (INIT && start);
        SET_EF   = ((SHIFT1 || SHIFT2) && FIN);
        RST_X    = (INIT && start);
        RST_EF   = (INIT && start);
        SUB_X    = (SUB);
        ADD_X    = (ADD);
        SHIFT_XB = (SHIFT1 || SHIFT2);
        SUB_CONT = (SHIFT1 || SHIFT2);
    end
    
endmodule

AZ5/MUL_BOOTH.v
module MUL_BOOTH(in1,
                 in2,
                 out,
                 out_r,
                 clk,
                 start,
                 rstn);
    parameter BIT_LEN = 4;
    
    input [BIT_LEN-1:0] in1, in2;
    input clk, start, rstn;
    output [2*BIT_LEN-1:0] out;
    output out_r;
    
    wire [1:0] status;
    wire [9:0] control;
    
    CU cu (
    .clk(clk),
    .status(status),
    .control(control),
    .start(start),
    .rstn(rstn)
    );
    
    DP #(.BIT_LEN(BIT_LEN)) dp(
    .control(control),
    .IN1(in1),
    .IN2(in2),
    .OUT(out),
    .status(status),
    .EF(out_r),
    .rstn(rstn)
    );
    
endmodule //mul_booth

AZ5/testbench.v
`define NULL 0
module testbench();
    
    parameter BIT_LEN = 4;
    parameter clk_c   = 5;
    wire out_r;
    reg clk, start, rstn;
    reg [BIT_LEN - 1:0] in1, in2;
    wire [2 * BIT_LEN - 1:0] out;
    
    MUL_BOOTH #(.BIT_LEN(BIT_LEN)) mb (
    .in1(in1),
    .in2(in2),
    .out(out),
    .out_r(out_r),
    .clk(clk),
    .start(start),
    .rstn(rstn)
    );
    
    
    initial begin
        $dumpfile("report/waveform.vcd");
        $dumpvars(0,mb);
    end
    
    integer data_file;
    integer scan_file;
    integer seed;
    initial begin
        data_file = $fopen("seed.dat", "r");
        if (data_file == `NULL) begin
            $display("data_file handle was NULL");
            $finish;
        end
        scan_file = $fscanf(data_file, "%d", seed);
        if (scan_file == `NULL) begin
            $display("integer read error");
            $finish;
        end
    end
    
    
    initial begin
        clk         = 0;
        forever clk = #(clk_c/2) ~clk;
    end
    
    // integer i,n;
    // initial begin
    //     n = {$random(seed)}%15+5;
    //     for (i = 0; i<n; i = i+1) begin
    //         start = 0;
    //         #clk_c
    //         start = 1;
    //         in1   = {BIT_LEN{$random(seed)}};
    //         in2   = {BIT_LEN{$random(seed)}};
    
    //         while (!out_r)
    //         begin
    //             #clk_c;
    //         end
    //     end
    // end
    
    initial begin
        in1   = 4'b0010;
        in2   = 4'b1000;
        rstn  = 1;
        start = 0;
        #clk_c
        rstn = 0;
        start = 1;
        #clk_c
        rstn  = 1;
        // start = 0;
        #200;
        $finish;
    end
    
    initial
        $monitor(clk,"%d*%d = %d | XB:%b%b, INIT = %b, ADD = %b, SUB = %b, SHIFT1 = %b, SHIFT2 = %b , B0 = %b, FIN = %b, out_ready = %b, start = %b", in1, in2, out,mb.dp.X, mb.dp.B, mb.cu.INIT, mb.cu.ADD, mb.cu.SUB, mb.cu.SHIFT1, mb.cu.SHIFT2, mb.cu.B0, mb.cu.FIN, out_r, start);
    
endmodule

AZ5/report/waveform.vcd
$date
	Wed Apr 14 18:39:53 2021
$end
$version
	Icarus Verilog
$end
$timescale
	1s
$end
$scope module testbench $end
$scope module mb $end
$var wire 1 ! clk $end
$var wire 4 " in1 [3:0] $end
$var wire 4 # in2 [3:0] $end
$var wire 1 $ rstn $end
$var wire 1 % start $end
$var wire 2 & status [1:0] $end
$var wire 1 ' out_r $end
$var wire 8 ( out [7:0] $end
$var wire 10 ) control [9:0] $end
$scope module cu $end
$var wire 1 ! clk $end
$var wire 1 $ rstn $end
$var wire 1 % start $end
$var wire 2 * status [1:0] $end
$var wire 10 + control [9:0] $end
$var wire 1 , SUB $end
$var wire 1 - SHIFT2 $end
$var wire 1 . SHIFT1 $end
$var wire 1 / INIT $end
$var wire 1 0 FIN $end
$var wire 1 1 B0 $end
$var wire 1 2 ADD $end
$var reg 1 3 ADD_D $end
$var reg 1 4 ADD_X $end
$var reg 1 5 INIT_D $end
$var reg 1 6 LD_A $end
$var reg 1 7 LD_B $end
$var reg 1 8 LD_CONT $end
$var reg 1 9 RST_EF $end
$var reg 1 : RST_X $end
$var reg 1 ; SET_EF $end
$var reg 1 < SHIFT1_D $end
$var reg 1 = SHIFT2_D $end
$var reg 1 > SHIFT_XB $end
$var reg 1 ? SUB_CONT $end
$var reg 1 @ SUB_D $end
$var reg 1 A SUB_X $end
$scope module add $end
$var wire 1 ! clk $end
$var wire 1 3 d $end
$var reg 1 2 q $end
$upscope $end
$scope module init $end
$var wire 1 ! clk $end
$var wire 1 5 d $end
$var reg 1 / q $end
$upscope $end
$scope module shift1 $end
$var wire 1 ! clk $end
$var wire 1 < d $end
$var reg 1 . q $end
$upscope $end
$scope module shift2 $end
$var wire 1 ! clk $end
$var wire 1 = d $end
$var reg 1 - q $end
$upscope $end
$scope module sub $end
$var wire 1 ! clk $end
$var wire 1 @ d $end
$var reg 1 , q $end
$upscope $end
$upscope $end
$scope module dp $end
$var wire 4 B IN1 [3:0] $end
$var wire 4 C IN2 [3:0] $end
$var wire 10 D control [9:0] $end
$var wire 1 $ rstn $end
$var wire 2 E status [1:0] $end
$var wire 1 F SUB_X $end
$var wire 1 G SUB_CONT $end
$var wire 1 H SHIFT_XB $end
$var wire 1 I SET_EF $end
$var wire 1 J RST_X $end
$var wire 1 K RST_EF $end
$var wire 8 L OUT [7:0] $end
$var wire 1 M LD_CONT $end
$var wire 1 N LD_B $end
$var wire 1 O LD_A $end
$var wire 1 P ADD_X $end
$var reg 4 Q A [3:0] $end
$var reg 4 R B [3:0] $end
$var reg 1 S B0 $end
$var reg 1 ' EF $end
$var reg 1 T FIN $end
$var reg 4 U X [3:0] $end
$var integer 32 V cont [31:0] $end
$upscope $end
$upscope $end
$upscope $end
$enddefinitions $end
#0
$dumpvars
bx V
bx U
xT
xS
bx R
bx Q
xP
xO
xN
xM
bx L
xK
xJ
xI
xH
xG
xF
bx E
bx D
b1000 C
b10 B
xA
x@
x?
x>
x=
x<
x;
x:
x9
x8
x7
x6
x5
x4
x3
x2
x1
x0
x/
x.
x-
x,
bx +
bx *
bx )
bx (
x'
bx &
0%
1$
b1000 #
b10 "
0!
$end
#2
0K
0J
0M
0N
0O
09
0:
08
07
b0x00xxxx )
b0x00xxxx +
b0x00xxxx D
06
1!
#4
0!
#5
01
00
0=
0<
0@
03
15
0S
b0 &
b0 *
b0 E
0T
1%
0$
#6
0-
0.
02
0,
1/
xK
xJ
0I
xM
xN
xO
x9
x:
0;
x8
x7
bx0xxxxxx )
bx0xxxxxx +
bx0xxxxxx D
x6
1!
#8
0!
#10
0/
1-
x@
x0
x1
0G
0H
0P
0F
1K
1J
1M
1N
1O
xT
bx &
bx *
bx E
xS
0?
0>
04
0A
19
1:
18
17
b1110110000 )
b1110110000 +
b1110110000 D
16
x=
x5
1!
1$
#12
0!
#14
x<
x-
x,
x/
x=
0@
05
00
01
1G
1H
0K
0J
xI
0M
0N
0O
0T
b0 &
b0 *
b0 E
0S
0'
b0 U
b1000 V
b1000 (
b1000 L
b1000 R
b10 Q
1?
1>
09
0:
x;
08
07
b0x000101 )
b0x000101 +
b0x000101 D
06
1!
#16
0!
#18
0<
x3
0/
0,
x.
xG
xH
xF
xK
xJ
0I
xM
xN
xO
b100 (
b100 L
b100 R
b111 V
x?
x>
xA
x9
x:
0;
x8
x7
bx0xxxx0x )
bx0xxxx0x +
bx0xxxx0x D
x6
1!
#20
0!
#22
03
0.
x2
0F
0K
0J
0M
0N
0O
0A
09
0:
08
07
b0x0x )
b0x0x +
b0x0x D
06
1!
#24
0!
#26
02
xP
b0xxx )
b0xxx +
b0xxx D
x4
1!
#28
0!
#30
0P
b0x0x )
b0x0x +
b0x0x D
04
1!
