AZ5/DP.v
`define ST_INIT     3'b000
`define ST_ADD      3'b001
`define ST_SUB      3'b010
`define ST_SHIFT    3'b011
`define ST_CHOOSE   3'b100

module DP (control,
           IN1,
           IN2,
           OUT,
           status,
           EF,
           rstn,
           clk);
    parameter BIT_LEN = 4;
    
    input [2:0]control;
    input [BIT_LEN-1:0]IN1;
    input [BIT_LEN-1:0]IN2;
    input clk, rstn;
    
    output [2*BIT_LEN-1:0]OUT;
    output [2:0]status;
    output EF;
    output reg BO;
    
    reg [BIT_LEN-1:0] A, B, X;
    reg[$clog2(BIT_LEN):0] cont;
    
    assign OUT    = (EF)? {X,B}: OUT;
    assign status = {B[0], BO,EF};
    assign EF     = (cont == 0);
    
    always @(posedge clk, negedge rstn) begin
        if (!rstn) begin
            A    <= IN1;
            B    <= IN2;
            X    <= 0;
            cont <= BIT_LEN;
            BO   <= 0;
        end
        else begin
            case (control)
                `ST_INIT:
                begin
                    cont <= BIT_LEN;
                    A    <= IN1;
                    B    <= IN2;
                    X    <= 0;
                    BO   <= 0;
                end
                `ST_ADD:
                begin
                    X <= X + A;
                end
                `ST_SUB:
                begin
                    X <= X - A;
                end
                `ST_SHIFT:
                begin
                    BO    <= B[0];
                    {X,B} <= {X[BIT_LEN-1], X, B[BIT_LEN-1:1]};
                    cont  <= cont - 1;
                end
                `ST_CHOOSE:
                begin
                    //do nothing
                end
            endcase
        end
    end
    
endmodule

AZ5/CU.v
`define ST_INIT     3'b000
`define ST_ADD      3'b001
`define ST_SUB      3'b010
`define ST_SHIFT    3'b011
`define ST_CHOOSE   3'b100

module CU(clk,
          status,
          control,
          rstn,
          start);
    
    input [2:0] status;
    input clk, rstn, start;
    output [2:0] control;
    
    wire B0, BO, FIN;
    reg [2:0] state;
    reg [2:0] next_state;
    
    assign B0      = status[2];
    assign BO      = status[1];
    assign FIN     = status[0];
    assign control = state;
    
    always @(posedge clk or negedge rstn) begin
        if (!rstn)
            state <= `ST_INIT;
        else
            state <= next_state;
    end
    
    
    always @(state or B0 or BO or FIN or start) begin
        case (state)
            `ST_INIT:
            begin
                if (start) begin
                    next_state <= `ST_CHOOSE;
                end
            end
            `ST_ADD:
            begin
                next_state <= `ST_SHIFT;
            end
            `ST_SUB:
            begin
                next_state <= `ST_SHIFT;
            end
            `ST_SHIFT:
            begin
                if (FIN)
                    next_state <= `ST_INIT;
                else
                    next_state <= `ST_CHOOSE;
            end
            `ST_CHOOSE:
            begin
                if (B0 && !BO)
                    next_state <= `ST_SUB;
                else if (!B0 && BO)
                    next_state <= `ST_ADD;
                else
                    next_state <= `ST_SHIFT;
            end
        endcase
    end
    
    
endmodule

AZ5/MUL_BOOTH.v
module MUL_BOOTH(in1,
                 in2,
                 out,
                 out_r,
                 clk,
                 start,
                 rstn);
    parameter BIT_LEN = 4;
    
    input [BIT_LEN-1:0] in1, in2;
    input clk, start, rstn;
    output [2*BIT_LEN-1:0] out;
    output out_r;
    
    wire [2:0] status, control;
    
    CU cu (
    .status(status),
    .control(control),
    .start(start),
    .rstn(rstn),
    .clk(clk)
    );
    
    DP #(.BIT_LEN(BIT_LEN)) dp(
    .control(control),
    .IN1(in1),
    .IN2(in2),
    .OUT(out),
    .status(status),
    .EF(out_r),
    .rstn(rstn),
    .clk(clk)
    );
    
endmodule //mul_booth

AZ5/testbench.v
`define NULL 0
module testbench();
    
    parameter BIT_LEN = 4;
    parameter clk_c   = 5;
    wire out_r;
    reg clk, start, rstn;
    reg signed [BIT_LEN - 1:0] in1, in2;
    wire signed [2 * BIT_LEN - 1:0] out;
    
    MUL_BOOTH #(.BIT_LEN(BIT_LEN)) mb (
    .in1(in1),
    .in2(in2),
    .out(out),
    .out_r(out_r),
    .clk(clk),
    .start(start),
    .rstn(rstn)
    );
    
    
    initial begin
        $dumpfile("report/waveform.vcd");
        $dumpvars(0,mb);
    end
    
    integer data_file;
    integer scan_file;
    integer seed;
    initial begin
        data_file = $fopen("seed.dat", "r");
        if (data_file == `NULL) begin
            $display("data_file handle was NULL");
            $finish;
        end
        scan_file = $fscanf(data_file, "%d", seed);
        if (scan_file == `NULL) begin
            $display("integer read error");
            $finish;
        end
    end
    
    
    initial begin
        clk         = 0;
        forever clk = #(clk_c/2) ~clk;
    end
    
    integer i,n;
    initial begin
        rstn  = 0;
        start = 0;
        n     = {$random(seed)}%15 + 10;
        for (i = 0; i < n; i = i+1) begin
            rstn = 0;
            #clk_c;
            in1 = {BIT_LEN{$random(seed)}};
            while (in1 == {1'b1,{BIT_LEN-1{1'b0}}})begin
                in1 = {BIT_LEN{$random(seed)}};
            end
            in2   = {BIT_LEN{$random(seed)}};
            rstn  = 1;
            start = 1;
            while (!out_r)
            begin
                #clk_c;
            end
            $display("result is ready: \t%d * %d = %d",in1, in2, out);
        end
        $finish;
    end
    
    initial
        $monitor($time, "  A:%b, XB:%b%b, state = %d, next_state = %d, count = %d , B0,B-1 = %b%b, out_ready = %b", mb.dp.A, mb.dp.X, mb.dp.B, mb.cu.state, mb.cu.next_state, mb.dp.cont, mb.cu.B0, mb.cu.BO, out_r);
    
endmodule

AZ5/report/waveform.vcd
$date
	Fri Apr 16 18:36:05 2021
$end
$version
	Icarus Verilog
$end
$timescale
	1s
$end
$scope module testbench $end
$scope module mb $end
$var wire 1 ! clk $end
$var wire 4 " in1 [3:0] $end
$var wire 4 # in2 [3:0] $end
$var wire 1 $ rstn $end
$var wire 1 % start $end
$var wire 3 & status [2:0] $end
$var wire 1 ' out_r $end
$var wire 8 ( out [7:0] $end
$var wire 3 ) control [2:0] $end
$scope module cu $end
$var wire 1 ! clk $end
$var wire 3 * control [2:0] $end
$var wire 1 $ rstn $end
$var wire 1 % start $end
$var wire 3 + status [2:0] $end
$var wire 1 , FIN $end
$var wire 1 - BO $end
$var wire 1 . B0 $end
$var reg 3 / next_state [2:0] $end
$var reg 3 0 state [2:0] $end
$upscope $end
$scope module dp $end
$var wire 4 1 IN1 [3:0] $end
$var wire 4 2 IN2 [3:0] $end
$var wire 1 ! clk $end
$var wire 3 3 control [2:0] $end
$var wire 1 $ rstn $end
$var wire 3 4 status [2:0] $end
$var wire 8 5 OUT [7:0] $end
$var wire 1 ' EF $end
$var reg 4 6 A [3:0] $end
$var reg 4 7 B [3:0] $end
$var reg 1 8 BO $end
$var reg 4 9 X [3:0] $end
$var reg 3 : cont [2:0] $end
$upscope $end
$upscope $end
$upscope $end
$enddefinitions $end
#0
$dumpvars
b100 :
b0 9
08
bx 7
bx 6
bx 5
bx00 4
b0 3
bx 2
bx 1
b0 0
bx /
x.
0-
0,
bx00 +
b0 *
b0 )
bx (
0'
bx00 &
0%
0$
bx #
bx "
0!
$end
#2
1!
#4
0!
#5
b100 /
1%
1$
b0 #
b0 2
b110 "
b110 1
#6
b11 /
0.
b0 &
b0 +
b0 4
b100 )
b100 *
b100 3
b100 0
b0 7
b110 6
1!
#8
0!
#10
b100 /
b11 )
b11 *
b11 3
b11 0
1!
#12
0!
#14
b11 /
b100 )
b100 *
b100 3
b100 0
b11 :
1!
#16
0!
#18
b100 /
b11 )
b11 *
b11 3
b11 0
1!
#20
0!
#22
b11 /
b100 )
b100 *
b100 3
b100 0
b10 :
1!
#24
0!
#26
b100 /
b11 )
b11 *
b11 3
b11 0
1!
#28
0!
#30
b11 /
b100 )
b100 *
b100 3
b100 0
b1 :
1!
#32
0!
#34
b100 /
b11 )
b11 *
b11 3
b11 0
1!
#36
0!
#38
b11 /
1,
b0 (
b0 5
b100 )
b100 *
b100 3
b100 0
b1 &
b1 +
b1 4
1'
b0 :
1!
#40
b100 /
0,
b0 &
b0 +
b0 4
0'
b100 :
b0 )
b0 *
b0 3
b0 0
0!
0$
#42
1!
#44
0!
#45
1$
b111 #
b111 2
b10 "
b10 1
#46
b10 /
1.
b100 &
b100 +
b100 4
b111 7
b10 6
b100 )
b100 *
b100 3
b100 0
1!
#48
0!
#50
b11 /
b10 )
b10 *
b10 3
b10 0
1!
#52
0!
#54
b100 /
b1110 9
b11 )
b11 *
b11 3
b11 0
1!
#56
0!
#58
b11 /
1-
b100 )
b100 *
b100 3
b100 0
b11 :
b1111 9
b11 7
b110 &
b110 +
b110 4
18
1!
#60
0!
#62
b100 /
b11 )
b11 *
b11 3
b11 0
1!
#64
0!
#66
b11 /
b100 )
b100 *
b100 3
b100 0
b10 :
b1001 7
1!
#68
0!
#70
b100 /
b11 )
b11 *
b11 3
b11 0
1!
#72
0!
#74
b1 /
0.
b10 &
b10 +
b10 4
b100 )
b100 *
b100 3
b100 0
b1 :
b1100 7
1!
#76
0!
#78
b11 /
b1 )
b1 *
b1 3
b1 0
1!
#80
0!
#82
b100 /
b11 )
b11 *
b11 3
b11 0
b1 9
1!
#84
0!
#86
b11 /
1,
b1110 (
b1110 5
0-
1'
b0 :
b0 9
b1110 7
b1 &
b1 +
b1 4
08
b100 )
b100 *
b100 3
b100 0
1!
#88
0!
#90
b100 /
1.
0,
b0 )
b0 *
b0 3
b0 0
b100 &
b100 +
b100 4
0'
b100 :
b111 7
1!
0$
#92
0!
#94
1!
#95
1$
b10 #
b10 2
b1 "
b1 1
#96
0!
#98
b11 /
0.
b0 &
b0 +
b0 4
b100 )
b100 *
b100 3
b100 0
b10 7
b1 6
1!
#100
0!
#102
b100 /
b11 )
b11 *
b11 3
b11 0
1!
#104
0!
#106
b10 /
1.
b100 &
b100 +
b100 4
b100 )
b100 *
b100 3
b100 0
b11 :
b1 7
1!
#108
0!
#110
b11 /
b10 )
b10 *
b10 3
b10 0
1!
#112
0!
#114
b100 /
b11 )
b11 *
b11 3
b11 0
b1111 9
1!
#116
0!
#118
b1 /
0.
1-
b10 :
b1000 7
b10 &
b10 +
b10 4
18
b100 )
b100 *
b100 3
b100 0
1!
#120
0!
#122
b11 /
b1 )
b1 *
b1 3
b1 0
1!
#124
0!
#126
b100 /
b0 9
b11 )
b11 *
b11 3
b11 0
1!
#128
0!
#130
b11 /
0-
b100 )
b100 *
b100 3
b100 0
b1 :
b100 7
b0 &
b0 +
b0 4
08
1!
#132
0!
#134
b100 /
b11 )
b11 *
b11 3
b11 0
1!
#136
0!
#138
b11 /
1,
b10 (
b10 5
b100 )
b100 *
b100 3
b100 0
b1 &
b1 +
b1 4
1'
b0 :
b10 7
1!
#140
b100 /
0,
b0 &
b0 +
b0 4
0'
b100 :
b0 )
b0 *
b0 3
b0 0
0!
0$
#142
1!
#144
0!
#145
1$
b1100 #
b1100 2
b1100 "
b1100 1
#146
b11 /
b1100 7
b1100 6
b100 )
b100 *
b100 3
b100 0
1!
#148
0!
#150
b100 /
b11 )
b11 *
b11 3
b11 0
1!
#152
0!
#154
b11 /
b11 :
b110 7
b100 )
b100 *
b100 3
b100 0
1!
#156
0!
#158
b100 /
b11 )
b11 *
b11 3
b11 0
1!
#160
0!
#162
b10 /
1.
b100 &
b100 +
b100 4
b10 :
b11 7
b100 )
b100 *
b100 3
b100 0
1!
#164
0!
#166
b11 /
b10 )
b10 *
b10 3
b10 0
1!
#168
0!
#170
b100 /
b100 9
b11 )
b11 *
b11 3
b11 0
1!
#172
0!
#174
b11 /
1-
b100 )
b100 *
b100 3
b100 0
b1 :
b10 9
b1 7
b110 &
b110 +
b110 4
18
1!
#176
0!
#178
b100 /
b11 )
b11 *
b11 3
b11 0
1!
#180
0!
#182
b1 /
0.
1,
b10000 (
b10000 5
b100 )
b100 *
b100 3
b100 0
b11 &
b11 +
b11 4
1'
b0 :
b1 9
b0 7
1!
#184
0!
#185
b100 /
0-
0,
08
b0 &
b0 +
b0 4
0'
b100 :
b0 9
b1100 7
b0 )
b0 *
b0 3
b0 0
0$
#186
1!
#188
0!
#190
b10 /
1.
b100 &
b100 +
b100 4
b1001 7
b10 6
b100 )
b100 *
b100 3
b100 0
1!
1$
b1001 #
b1001 2
b10 "
b10 1
#192
0!
#194
b11 /
b10 )
b10 *
b10 3
b10 0
1!
#196
0!
#198
b100 /
b1110 9
b11 )
b11 *
b11 3
b11 0
1!
#200
0!
#202
b1 /
0.
1-
b100 )
b100 *
b100 3
b100 0
b11 :
b1111 9
b100 7
b10 &
b10 +
b10 4
18
1!
#204
0!
#206
b11 /
b1 )
b1 *
b1 3
b1 0
1!
#208
0!
#210
b100 /
b11 )
b11 *
b11 3
b11 0
b1 9
1!
#212
0!
#214
b11 /
0-
b10 :
b0 9
b1010 7
b0 &
b0 +
b0 4
08
b100 )
b100 *
b100 3
b100 0
1!
#216
0!
#218
b100 /
b11 )
b11 *
b11 3
b11 0
1!
#220
0!
#222
b10 /
1.
b100 &
b100 +
b100 4
b1 :
b101 7
b100 )
b100 *
b100 3
b100 0
1!
#224
0!
#226
b11 /
b10 )
b10 *
b10 3
b10 0
1!
#228
0!
#230
b100 /
b1110 9
b11 )
b11 *
b11 3
b11 0
1!
#232
0!
#234
b1 /
0.
1,
b11110010 (
b11110010 5
1-
b100 )
b100 *
b100 3
b100 0
1'
b0 :
b1111 9
b10 7
b11 &
b11 +
b11 4
18
1!
#235
b100 /
1.
0-
0,
08
b100 &
b100 +
b100 4
0'
b100 :
b0 9
b1001 7
b0 )
b0 *
b0 3
b0 0
0$
#236
0!
#238
1!
#240
0!
1$
b110 #
b110 2
b1011 "
b1011 1
#242
b11 /
0.
b0 &
b0 +
b0 4
b110 7
b1011 6
b100 )
b100 *
b100 3
b100 0
1!
#244
0!
#246
b100 /
b11 )
b11 *
b11 3
b11 0
1!
#248
0!
#250
b10 /
1.
b100 &
b100 +
b100 4
b11 :
b11 7
b100 )
b100 *
b100 3
b100 0
1!
#252
0!
#254
b11 /
b10 )
b10 *
b10 3
b10 0
1!
#256
0!
#258
b100 /
b101 9
b11 )
b11 *
b11 3
b11 0
1!
#260
0!
#262
b11 /
1-
b100 )
b100 *
b100 3
b100 0
b10 :
b10 9
b1001 7
b110 &
b110 +
b110 4
18
1!
#264
0!
#266
b100 /
b11 )
b11 *
b11 3
b11 0
1!
#268
0!
#270
b1 /
0.
b10 &
b10 +
b10 4
b100 )
b100 *
b100 3
b100 0
b1 :
b1 9
b100 7
1!
#272
0!
#274
b11 /
b1 )
b1 *
b1 3
b1 0
1!
#276
0!
#278
b100 /
b11 )
b11 *
b11 3
b11 0
b1100 9
1!
#280
0!
#282
b11 /
1,
b11100010 (
b11100010 5
0-
1'
b0 :
b1110 9
b10 7
b1 &
b1 +
b1 4
08
b100 )
b100 *
b100 3
b100 0
1!
#284
0!
#285
b100 /
0,
b0 )
b0 *
b0 3
b0 0
b0 &
b0 +
b0 4
0'
b100 :
b0 9
b110 7
0$
#286
1!
#288
0!
#290
b11 /
b100 )
b100 *
b100 3
b100 0
b1110 7
b11 6
1!
1$
b1110 #
b1110 2
b11 "
b11 1
#292
0!
#294
b100 /
b11 )
b11 *
b11 3
b11 0
1!
#296
0!
#298
b10 /
1.
b100 &
b100 +
b100 4
b100 )
b100 *
b100 3
b100 0
b11 :
b111 7
1!
#300
0!
#302
b11 /
b10 )
b10 *
b10 3
b10 0
1!
#304
0!
#306
b100 /
b11 )
b11 *
b11 3
b11 0
b1101 9
1!
#308
0!
#310
b11 /
1-
b10 :
b1110 9
b1011 7
b110 &
b110 +
b110 4
18
b100 )
b100 *
b100 3
b100 0
1!
#312
0!
#314
b100 /
b11 )
b11 *
b11 3
b11 0
1!
#316
0!
#318
b11 /
b1 :
b1111 9
b101 7
b100 )
b100 *
b100 3
b100 0
1!
#320
0!
#322
b100 /
b11 )
b11 *
b11 3
b11 0
1!
#324
0!
#326
b1 /
0.
1,
b11111010 (
b11111010 5
b11 &
b11 +
b11 4
1'
b0 :
b1010 7
b100 )
b100 *
b100 3
b100 0
1!
#328
0!
#330
b100 /
0-
0,
b0 )
b0 *
b0 3
b0 0
08
b0 &
b0 +
b0 4
0'
b100 :
b0 9
b1110 7
1!
0$
#332
0!
#334
1!
#335
1$
b1100 #
b1100 2
b1001 "
b1001 1
#336
0!
#338
b11 /
b100 )
b100 *
b100 3
b100 0
b1100 7
b1001 6
1!
#340
0!
#342
b100 /
b11 )
b11 *
b11 3
b11 0
1!
#344
0!
#346
b11 /
b100 )
b100 *
b100 3
b100 0
b11 :
b110 7
1!
#348
0!
#350
b100 /
b11 )
b11 *
b11 3
b11 0
1!
#352
0!
#354
b10 /
1.
b100 &
b100 +
b100 4
b100 )
b100 *
b100 3
b100 0
b10 :
b11 7
1!
#356
0!
#358
b11 /
b10 )
b10 *
b10 3
b10 0
1!
#360
0!
#362
b100 /
b11 )
b11 *
b11 3
b11 0
b111 9
1!
#364
0!
#366
b11 /
1-
b1 :
b11 9
b1001 7
b110 &
b110 +
b110 4
18
b100 )
b100 *
b100 3
b100 0
1!
#368
0!
#370
b100 /
b11 )
b11 *
b11 3
b11 0
1!
#372
0!
#374
b1 /
0.
1,
b11100 (
b11100 5
b11 &
b11 +
b11 4
1'
b0 :
b1 9
b1100 7
b100 )
b100 *
b100 3
b100 0
1!
#375
b100 /
0-
0,
b0 )
b0 *
b0 3
b0 0
08
b0 &
b0 +
b0 4
0'
b100 :
b0 9
0$
#376
0!
#378
1!
#380
0!
1$
b100 #
b100 2
b1 "
b1 1
#382
b11 /
b100 )
b100 *
b100 3
b100 0
b100 7
b1 6
1!
#384
0!
#386
b100 /
b11 )
b11 *
b11 3
b11 0
1!
#388
0!
#390
b11 /
b100 )
b100 *
b100 3
b100 0
b11 :
b10 7
1!
#392
0!
#394
b100 /
b11 )
b11 *
b11 3
b11 0
1!
#396
0!
#398
b10 /
1.
b100 &
b100 +
b100 4
b100 )
b100 *
b100 3
b100 0
b10 :
b1 7
1!
#400
0!
#402
b11 /
b10 )
b10 *
b10 3
b10 0
1!
#404
0!
#406
b100 /
b11 )
b11 *
b11 3
b11 0
b1111 9
1!
#408
0!
#410
b1 /
0.
1-
b1 :
b1000 7
b10 &
b10 +
b10 4
18
b100 )
b100 *
b100 3
b100 0
1!
#412
0!
#414
b11 /
b1 )
b1 *
b1 3
b1 0
1!
#416
0!
#418
b100 /
b0 9
b11 )
b11 *
b11 3
b11 0
1!
#420
0!
#422
b11 /
1,
b100 (
b100 5
0-
b100 )
b100 *
b100 3
b100 0
1'
b0 :
b100 7
b1 &
b1 +
b1 4
08
1!
#424
0!
#425
b100 /
0,
b0 &
b0 +
b0 4
0'
b100 :
b0 )
b0 *
b0 3
b0 0
0$
#426
1!
#428
0!
#430
b10 /
1.
b100 &
b100 +
b100 4
b101 7
b0 6
b100 )
b100 *
b100 3
b100 0
1!
1$
b101 #
b101 2
b0 "
b0 1
#432
0!
#434
b11 /
b10 )
b10 *
b10 3
b10 0
1!
#436
0!
#438
b100 /
b11 )
b11 *
b11 3
b11 0
1!
#440
0!
#442
b1 /
0.
1-
b100 )
b100 *
b100 3
b100 0
b11 :
b10 7
b10 &
b10 +
b10 4
18
1!
#444
0!
#446
b11 /
b1 )
b1 *
b1 3
b1 0
1!
#448
0!
#450
b100 /
b11 )
b11 *
b11 3
b11 0
1!
#452
0!
#454
b10 /
1.
0-
b10 :
b1 7
b100 &
b100 +
b100 4
08
b100 )
b100 *
b100 3
b100 0
1!
#456
0!
#458
b11 /
b10 )
b10 *
b10 3
b10 0
1!
#460
0!
#462
b100 /
b11 )
b11 *
b11 3
b11 0
1!
#464
0!
#466
b1 /
0.
1-
b100 )
b100 *
b100 3
b100 0
b1 :
b0 7
b10 &
b10 +
b10 4
18
1!
#468
0!
#470
b11 /
b1 )
b1 *
b1 3
b1 0
1!
#472
0!
#474
b100 /
b11 )
b11 *
b11 3
b11 0
1!
#476
0!
#478
b11 /
1,
b0 (
b0 5
0-
1'
b0 :
b1 &
b1 +
b1 4
08
b100 )
b100 *
b100 3
b100 0
1!
#480
b100 /
1.
0,
b0 )
b0 *
b0 3
b0 0
b100 &
b100 +
b100 4
0'
b100 :
b101 7
0!
0$
#482
1!
#484
0!
#485
1$
b1010 "
b1010 1
#486
b10 /
b100 )
b100 *
b100 3
b100 0
b1010 6
1!
#488
0!
#490
b11 /
b10 )
b10 *
b10 3
b10 0
1!
#492
0!
#494
b100 /
b11 )
b11 *
b11 3
b11 0
b110 9
1!
#496
0!
#498
b1 /
0.
1-
b11 :
b11 9
b10 7
b10 &
b10 +
b10 4
18
b100 )
b100 *
b100 3
b100 0
1!
#500
0!
#502
b11 /
b1 )
b1 *
b1 3
b1 0
1!
#504
0!
#506
b100 /
b1101 9
b11 )
b11 *
b11 3
b11 0
1!
#508
0!
#510
b10 /
1.
0-
b100 )
b100 *
b100 3
b100 0
b10 :
b1110 9
b1001 7
b100 &
b100 +
b100 4
08
1!
#512
0!
#514
b11 /
b10 )
b10 *
b10 3
b10 0
1!
#516
0!
#518
b100 /
b11 )
b11 *
b11 3
b11 0
b100 9
1!
#520
0!
#522
b1 /
0.
1-
b1 :
b10 9
b100 7
b10 &
b10 +
b10 4
18
b100 )
b100 *
b100 3
b100 0
1!
#524
0!
#526
b11 /
b1 )
b1 *
b1 3
b1 0
1!
#528
0!
#530
b100 /
b1100 9
b11 )
b11 *
b11 3
b11 0
1!
#532
0!
#534
b11 /
1,
b11100010 (
b11100010 5
0-
b100 )
b100 *
b100 3
b100 0
1'
b0 :
b1110 9
b10 7
b1 &
b1 +
b1 4
08
1!
#535
b100 /
1.
0,
b100 &
b100 +
b100 4
0'
b100 :
b0 9
b101 7
b0 )
b0 *
b0 3
b0 0
0$
#536
0!
#538
1!
#540
0!
1$
b111 #
b111 2
b1 "
b1 1
#542
b10 /
b111 7
b1 6
b100 )
b100 *
b100 3
b100 0
1!
#544
0!
#546
b11 /
b10 )
b10 *
b10 3
b10 0
1!
#548
0!
#550
b100 /
b1111 9
b11 )
b11 *
b11 3
b11 0
1!
#552
0!
#554
b11 /
1-
b100 )
b100 *
b100 3
b100 0
b11 :
b1011 7
b110 &
b110 +
b110 4
18
1!
#556
0!
#558
b100 /
b11 )
b11 *
b11 3
b11 0
1!
#560
0!
#562
b11 /
b100 )
b100 *
b100 3
b100 0
b10 :
b1101 7
1!
#564
0!
#566
b100 /
b11 )
b11 *
b11 3
b11 0
1!
#568
0!
#570
b1 /
0.
b10 &
b10 +
b10 4
b100 )
b100 *
b100 3
b100 0
b1 :
b1110 7
1!
#572
0!
#574
b11 /
b1 )
b1 *
b1 3
b1 0
1!
#576
0!
#578
b100 /
b11 )
b11 *
b11 3
b11 0
b0 9
1!
#580
0!
#582
b10 /
1.
1,
b111 (
b111 5
0-
1'
b0 :
b111 7
b101 &
b101 +
b101 4
08
b100 )
b100 *
b100 3
b100 0
1!
#584
0!
#585
b100 /
0,
b0 )
b0 *
b0 3
b0 0
b100 &
b100 +
b100 4
0'
b100 :
0$
#586
1!
#588
0!
#590
b11 /
0.
b0 &
b0 +
b0 4
b100 )
b100 *
b100 3
b100 0
b1100 7
b100 6
1!
1$
b1100 #
b1100 2
b100 "
b100 1
#592
0!
#594
b100 /
b11 )
b11 *
b11 3
b11 0
1!
#596
0!
#598
b11 /
b100 )
b100 *
b100 3
b100 0
b11 :
b110 7
1!
#600
0!
#602
b100 /
b11 )
b11 *
b11 3
b11 0
1!
#604
0!
#606
b10 /
1.
b100 &
b100 +
b100 4
b100 )
b100 *
b100 3
b100 0
b10 :
b11 7
1!
#608
0!
#610
b11 /
b10 )
b10 *
b10 3
b10 0
1!
#612
0!
#614
b100 /
b11 )
b11 *
b11 3
b11 0
b1100 9
1!
#616
0!
#618
b11 /
1-
b1 :
b1110 9
b1 7
b110 &
b110 +
b110 4
18
b100 )
b100 *
b100 3
b100 0
1!
#620
0!
#622
b100 /
b11 )
b11 *
b11 3
b11 0
1!
#624
0!
#626
b1 /
0.
1,
b11110000 (
b11110000 5
b11 &
b11 +
b11 4
1'
b0 :
b1111 9
b0 7
b100 )
b100 *
b100 3
b100 0
1!
#628
0!
#630
b100 /
0-
0,
b0 )
b0 *
b0 3
b0 0
08
b0 &
b0 +
b0 4
0'
b100 :
b0 9
b1100 7
1!
0$
#632
0!
#634
1!
#635
1$
b111 #
b111 2
b1110 "
b1110 1
#636
0!
#638
b10 /
1.
b100 &
b100 +
b100 4
b100 )
b100 *
b100 3
b100 0
b111 7
b1110 6
1!
#640
0!
#642
b11 /
b10 )
b10 *
b10 3
b10 0
1!
#644
0!
#646
b100 /
b11 )
b11 *
b11 3
b11 0
b10 9
1!
#648
0!
#650
b11 /
1-
b11 :
b1 9
b11 7
b110 &
b110 +
b110 4
18
b100 )
b100 *
b100 3
b100 0
1!
#652
0!
#654
b100 /
b11 )
b11 *
b11 3
b11 0
1!
#656
0!
#658
b11 /
b10 :
b0 9
b1001 7
b100 )
b100 *
b100 3
b100 0
1!
#660
0!
#662
b100 /
b11 )
b11 *
b11 3
b11 0
1!
#664
0!
#666
b1 /
0.
b10 &
b10 +
b10 4
b1 :
b100 7
b100 )
b100 *
b100 3
b100 0
1!
#668
0!
#670
b11 /
b1 )
b1 *
b1 3
b1 0
1!
#672
0!
#674
b100 /
b1110 9
b11 )
b11 *
b11 3
b11 0
1!
#676
0!
#678
b11 /
1,
b11110010 (
b11110010 5
0-
b100 )
b100 *
b100 3
b100 0
1'
b0 :
b1111 9
b10 7
b1 &
b1 +
b1 4
08
1!
#680
b100 /
1.
0,
b100 &
b100 +
b100 4
0'
b100 :
b0 9
b111 7
b0 )
b0 *
b0 3
b0 0
0!
0$
#682
1!
#684
0!
#685
1$
b1010 #
b1010 2
b1101 "
b1101 1
#686
b11 /
0.
b0 &
b0 +
b0 4
b1010 7
b1101 6
b100 )
b100 *
b100 3
b100 0
1!
#688
0!
#690
b100 /
b11 )
b11 *
b11 3
b11 0
1!
#692
0!
#694
b10 /
1.
b100 &
b100 +
b100 4
b11 :
b101 7
b100 )
b100 *
b100 3
b100 0
1!
#696
0!
#698
b11 /
b10 )
b10 *
b10 3
b10 0
1!
#700
0!
#702
b100 /
b11 9
b11 )
b11 *
b11 3
b11 0
1!
#704
0!
#706
b1 /
0.
1-
b100 )
b100 *
b100 3
b100 0
b10 :
b1 9
b1010 7
b10 &
b10 +
b10 4
18
1!
#708
0!
#710
b11 /
b1 )
b1 *
b1 3
b1 0
1!
#712
0!
#714
b100 /
b11 )
b11 *
b11 3
b11 0
b1110 9
1!
#716
0!
#718
b10 /
1.
0-
b1 :
b1111 9
b101 7
b100 &
b100 +
b100 4
08
b100 )
b100 *
b100 3
b100 0
1!
#720
0!
#722
b11 /
b10 )
b10 *
b10 3
b10 0
1!
#724
0!
#726
b100 /
b10 9
b11 )
b11 *
b11 3
b11 0
1!
#728
0!
#730
b1 /
0.
1,
b10010 (
b10010 5
1-
b100 )
b100 *
b100 3
b100 0
1'
b0 :
b1 9
b10 7
b11 &
b11 +
b11 4
18
1!
#732
0!
#734
b11 /
b1 )
b1 *
b1 3
b1 0
1!
#735
b100 /
0-
0,
b0 )
b0 *
b0 3
b0 0
08
b0 &
b0 +
b0 4
0'
b100 :
b0 9
b1010 7
0$
#736
0!
#738
1!
#740
0!
1$
b11 #
b11 2
#742
b10 /
1.
b100 &
b100 +
b100 4
b100 )
b100 *
b100 3
b100 0
b11 7
1!
#744
0!
#746
b11 /
b10 )
b10 *
b10 3
b10 0
1!
#748
0!
#750
b100 /
b11 )
b11 *
b11 3
b11 0
b11 9
1!
#752
0!
#754
b11 /
1-
b11 :
b1 9
b1001 7
b110 &
b110 +
b110 4
18
b100 )
b100 *
b100 3
b100 0
1!
#756
0!
#758
b100 /
b11 )
b11 *
b11 3
b11 0
1!
#760
0!
#762
b1 /
0.
b10 &
b10 +
b10 4
b10 :
b0 9
b1100 7
b100 )
b100 *
b100 3
b100 0
1!
#764
0!
#766
b11 /
b1 )
b1 *
b1 3
b1 0
1!
#768
0!
#770
b100 /
b1101 9
b11 )
b11 *
b11 3
b11 0
1!
#772
0!
#774
b11 /
0-
b100 )
b100 *
b100 3
b100 0
b1 :
b1110 9
b1110 7
b0 &
b0 +
b0 4
08
1!
#776
0!
#778
b100 /
b11 )
b11 *
b11 3
b11 0
1!
#780
0!
#782
b10 /
1.
1,
b11110111 (
b11110111 5
b100 )
b100 *
b100 3
b100 0
b101 &
b101 +
b101 4
1'
b0 :
b1111 9
b111 7
1!
