AZ5/DP.v
`define ST_INIT     3'b000
`define ST_ADD      3'b001
`define ST_SUB      3'b010
`define ST_SHIFT    3'b011

module DP (control,
           IN1,
           IN2,
           OUT,
           status,
           EF,
           rstn,
           clk);
    parameter BIT_LEN = 4;
    
    input [1:0]control;
    input [BIT_LEN-1:0]IN1;
    input [BIT_LEN-1:0]IN2;
    input clk, rstn;
    
    output [2*BIT_LEN-1:0]OUT;
    output [1:0]status;
    output reg EF;
    
    reg [BIT_LEN-1:0] A, B, X;
    integer cont;
    
    assign OUT    = {X,B};
    assign status = {B[0],(cont == 0)};
    
    always @(posedge clk, negedge rstn) begin
        if (!rstn) begin
            A    <= IN1;
            B    <= IN2;
            X    <= 0;
            cont <= 2 * BIT_LEN;
            EF   <= 0;
        end
        else begin
            case (control)
                `ST_INIT:
                begin
                    cont <= 2 * BIT_LEN;
                    A    <= IN1;
                    B    <= IN2;
                    X    <= 0;
                    EF   <= 0;
                end
                `ST_ADD:
                begin
                    X <= X + A;
                end
                `ST_SUB:
                begin
                    X <= X - A;
                end
                `ST_SHIFT:
                begin
                    {X,B} <= {X[BIT_LEN-1], X, B[BIT_LEN-1:1]};
                    cont  <= cont - 1;
                    if (cont == 0) begin
                        EF <= 1;
                    end
                end
            endcase
        end
    end
    
endmodule

AZ5/CU.v
`define ST_INIT     3'b000
`define ST_ADD      3'b001
`define ST_SUB      3'b010
`define ST_SHIFT1   3'b011
`define ST_SHIFT2   3'b111

module CU(clk,
          status,
          control,
          rstn,
          start);
    
    input [1:0] status;
    input clk, rstn, start;
    output [1:0] control;
    
    wire B0, FIN;
    reg [2:0] state;
    reg [2:0] next_state;
    
    assign B0      = status[1];
    assign FIN     = status[0];
    assign control = state[1:0];
    
    always @(posedge clk or negedge rstn) begin
        if (!rstn)
            state <= `ST_INIT;
        else
            state <= next_state;
    end
    
    
    always @(state or B0 or FIN or start) begin
        case (state)
            `ST_INIT:
            begin
                if (start) begin
                    if (B0)
                        next_state <= `ST_SUB;
                    else
                        next_state <= `ST_SHIFT2;
                end
            end
            `ST_ADD:
            begin
                next_state <= `ST_SHIFT2;
            end
            `ST_SUB:
            begin
                next_state <= `ST_SHIFT1;
            end
            `ST_SHIFT1:
            begin
                if (FIN)
                    next_state <= `ST_INIT;
                else if (!FIN && B0)
                    next_state <= `ST_SHIFT1;
                else
                    next_state <= `ST_ADD;
            end
            `ST_SHIFT2:
            begin
                if (FIN)
                    next_state <= `ST_INIT;
                else if (!FIN && B0)
                    next_state <= `ST_SUB;
                else
                    next_state <= `ST_SHIFT2;
            end
        endcase
    end
    
    
endmodule

AZ5/MUL_BOOTH.v
module MUL_BOOTH(in1,
                 in2,
                 out,
                 out_r,
                 clk,
                 start,
                 rstn);
    parameter BIT_LEN = 4;
    
    input [BIT_LEN-1:0] in1, in2;
    input clk, start, rstn;
    output [2*BIT_LEN-1:0] out;
    output out_r;
    
    wire [1:0] status, control;
    
    CU cu (
    .status(status),
    .control(control),
    .start(start),
    .rstn(rstn),
    .clk(clk)
    );
    
    DP #(.BIT_LEN(BIT_LEN)) dp(
    .control(control),
    .IN1(in1),
    .IN2(in2),
    .OUT(out),
    .status(status),
    .EF(out_r),
    .rstn(rstn),
    .clk(clk)
    );
    
endmodule //mul_booth

AZ5/testbench.v
`define NULL 0
module testbench();
    
    parameter BIT_LEN = 4;
    parameter clk_c   = 5;
    wire out_r;
    reg clk, start, rstn;
    reg [BIT_LEN - 1:0] in1, in2;
    wire [2 * BIT_LEN - 1:0] out;
    
    MUL_BOOTH #(.BIT_LEN(BIT_LEN)) mb (
    .in1(in1),
    .in2(in2),
    .out(out),
    .out_r(out_r),
    .clk(clk),
    .start(start),
    .rstn(rstn)
    );
    
    
    initial begin
        $dumpfile("report/waveform.vcd");
        $dumpvars(0,mb);
    end
    
    integer data_file;
    integer scan_file;
    integer seed;
    initial begin
        data_file = $fopen("seed.dat", "r");
        if (data_file == `NULL) begin
            $display("data_file handle was NULL");
            $finish;
        end
        scan_file = $fscanf(data_file, "%d", seed);
        if (scan_file == `NULL) begin
            $display("integer read error");
            $finish;
        end
    end
    
    
    initial begin
        clk         = 0;
        forever clk = #(clk_c/2) ~clk;
    end
    
    // integer i,n;
    // initial begin
    //     n = {$random(seed)}%15+5;
    //     for (i = 0; i<n; i = i+1) begin
    //         start = 0;
    //         #clk_c
    //         start = 1;
    //         in1   = {BIT_LEN{$random(seed)}};
    //         in2   = {BIT_LEN{$random(seed)}};
    
    //         while (!out_r)
    //         begin
    //             #clk_c;
    //         end
    //     end
    // end
    
    initial begin
        in1   = 4'b0111;
        in2   = 4'b1011;
        rstn  = 0;
        start = 0;
        #clk_c
        rstn = 1;
        start = 1;
        #clk_c
        start = 0;
        #100;
        $finish;
    end
    
    initial
        $monitor(" A:%b, XB:%b%b, state = %d, next_state = %d, count = %d , B0 = %b, FIN = %b, out_ready = %b, start = %b",mb.dp.A, mb.dp.X, mb.dp.B, mb.cu.state, mb.cu.next_state, mb.dp.cont, mb.cu.B0, mb.cu.FIN, out_r, start);
    
endmodule

AZ5/report/waveform.vcd
$date
	Thu Apr 15 03:53:33 2021
$end
$version
	Icarus Verilog
$end
$timescale
	1s
$end
$scope module testbench $end
$scope module mb $end
$var wire 1 ! clk $end
$var wire 4 " in1 [3:0] $end
$var wire 4 # in2 [3:0] $end
$var wire 1 $ rstn $end
$var wire 1 % start $end
$var wire 2 & status [1:0] $end
$var wire 1 ' out_r $end
$var wire 8 ( out [7:0] $end
$var wire 2 ) control [1:0] $end
$scope module cu $end
$var wire 1 ! clk $end
$var wire 1 $ rstn $end
$var wire 1 % start $end
$var wire 2 * status [1:0] $end
$var wire 2 + control [1:0] $end
$var wire 1 , FIN $end
$var wire 1 - B0 $end
$var reg 3 . next_state [2:0] $end
$var reg 3 / state [2:0] $end
$upscope $end
$scope module dp $end
$var wire 4 0 IN1 [3:0] $end
$var wire 4 1 IN2 [3:0] $end
$var wire 1 ! clk $end
$var wire 2 2 control [1:0] $end
$var wire 1 $ rstn $end
$var wire 2 3 status [1:0] $end
$var wire 8 4 OUT [7:0] $end
$var reg 4 5 A [3:0] $end
$var reg 4 6 B [3:0] $end
$var reg 1 ' EF $end
$var reg 4 7 X [3:0] $end
$var integer 32 8 cont [31:0] $end
$upscope $end
$upscope $end
$upscope $end
$enddefinitions $end
#0
$dumpvars
b1000 8
b0 7
b1011 6
b111 5
b1011 4
b10 3
b0 2
b1011 1
b111 0
b0 /
bx .
1-
0,
b0 +
b10 *
b0 )
b1011 (
0'
b10 &
0%
0$
b1011 #
b111 "
0!
$end
#2
1!
#4
0!
#5
b10 .
1%
1$
#6
b11 .
b10 )
b10 +
b10 2
b10 /
1!
#8
0!
#10
b11 )
b11 +
b11 2
b10011011 (
b10011011 4
b1001 7
b11 /
1!
0%
#12
0!
#14
b111 8
b1100 7
b11001101 (
b11001101 4
b1101 6
1!
#16
0!
#18
b1 .
0-
b0 &
b0 *
b0 3
b110 8
b1110 7
b11100110 (
b11100110 4
b110 6
1!
#20
0!
#22
b111 .
1-
b1 )
b1 +
b1 2
b10 &
b10 *
b10 3
b1 /
b101 8
b1111 7
b11110011 (
b11110011 4
b11 6
1!
#24
0!
#26
b10 .
b11 )
b11 +
b11 2
b1100011 (
b1100011 4
b110 7
b111 /
1!
#28
0!
#30
b11 .
b10 )
b10 +
b10 2
b10 /
b100 8
b11 7
b110001 (
b110001 4
b1 6
1!
#32
0!
#34
b11 )
b11 +
b11 2
b11000001 (
b11000001 4
b1100 7
b11 /
1!
#36
0!
#38
b1 .
0-
b0 &
b0 *
b0 3
b11 8
b1110 7
b11100000 (
b11100000 4
b0 6
1!
#40
0!
#42
b111 .
b1 )
b1 +
b1 2
b10 8
b11110000 (
b11110000 4
b1111 7
b1 /
1!
#44
0!
#46
b11 )
b11 +
b11 2
b111 /
b1100000 (
b1100000 4
b110 7
1!
#48
0!
#50
b1 8
b110000 (
b110000 4
b11 7
1!
#52
0!
#54
b0 .
1,
b1 &
b1 *
b1 3
b0 8
b1 7
b11000 (
b11000 4
b1000 6
1!
#56
0!
#58
0,
b0 )
b0 +
b0 2
1'
b0 &
b0 *
b0 3
b11111111111111111111111111111111 8
b0 7
b1100 (
b1100 4
b1100 6
b0 /
1!
#60
0!
#62
1-
b10 &
b10 *
b10 3
0'
b1011 (
b1011 4
b1011 6
b1000 8
1!
