AZ9/TCAM.v
module TCAM (word,
             address,
             rwn,
             clk);
    parameter WORD_LEN = 8;
    parameter ADDR_LEN = 5;
    
    inout [ADDR_LEN - 1 : 0] address;
    input [WORD_LEN - 1 : 0] word;
    input rwn ,clk;
    
    reg [WORD_LEN - 1 : 0] memory [(1 << ADDR_LEN) - 1 : 0];
    reg [ADDR_LEN - 1 : 0] read_candidate;
    
    assign address = (rwn) ? read_candidate : 'bz;
    
    
    reg [ADDR_LEN: 0] i;
    always @ (posedge clk) begin
        if (rwn) begin
            read_candidate = 'bx;
            for (i = 0 ; i < (1 << ADDR_LEN) ; i = i + 1) begin
                if (equals(memory[i] , word)) begin
                    if (read_candidate === 'bx || (number_of_x(memory[read_candidate]) > number_of_x(memory[i]))) begin
                        read_candidate = i;
                    end
                end
            end
        end
        else begin
            memory[address] = word;
        end
    end
    
    
    // this function get number of x elements in given bit-vector
    function [WORD_LEN - 1 : 0] number_of_x;
        input [WORD_LEN - 1 : 0] c;
        reg [WORD_LEN - 1 : 0] number, j;
        begin
            number = 0;
            for(j = 0 ; j < WORD_LEN ; j = j + 1) begin
                if (c[j] === 1'bx) begin
                    number = number + 1;
                end
            end
            number_of_x = number;
        end
    endfunction
    
    // this function checks equality of two bit-vectors with ignoring x's
    function equals;
        input [WORD_LEN - 1 : 0] a,b;
        reg [WORD_LEN - 1 : 0] j;
        reg flag;
        begin
            flag = 1;
            for(j = 0 ; j < WORD_LEN ; j = j + 1) begin
                if (a[j] !== 1'bx && b[j] !== 1'bx && a[j] != b[j]) begin
                    flag = 0;
                end
            end
            equals = flag;
        end
    endfunction
    
endmodule

AZ9/testbench.v
`define NULL 0
module testbench();
    
    parameter WORD_LEN = 16;
    parameter ADDR_LEN = 4;
    
    parameter clk_c = 10;
    reg rwn, clk;
    reg [WORD_LEN-1:0] word;
    wire [ADDR_LEN-1:0] address;
    reg [ADDR_LEN-1:0] w_addr;
    
    TCAM #(.WORD_LEN(WORD_LEN), .ADDR_LEN(ADDR_LEN)) tcam (
    .word(word),
    .address(address),
    .rwn(rwn),
    .clk(clk)
    );
    
    assign address = (!rwn) ? w_addr : 'bz;
    
    initial begin
        $dumpfile("report/waveform.vcd");
        $dumpvars(0,tcam);
    end
    
    initial begin
        clk         = 0;
        forever clk = #(clk_c/2) ~clk;
    end
    
    initial
        $monitor($time," rwn = %d  word = %b address = %d",rwn,word,address);
    
    initial begin
        #clk_c  rwn = 0; word = 16'b0111xx11_0111xx11; w_addr = 0;
        #clk_c  rwn = 0; word = 16'b11x01001_11x01001; w_addr = 1;
        #clk_c  rwn = 0; word = 16'b01110x11_01110x11; w_addr = 2;
        #clk_c  rwn = 0; word = 16'b1101xx11_1101xx11; w_addr = 3;
        #clk_c  rwn = 1; word = 16'b0111xx11_0111xx11;
        #clk_c  rwn = 1; word = 16'bxxxxxxxx_xxxxxxxx;
        #clk_c  rwn = 1; word = 16'b11xxxx11_11xxxx11;
        #clk_c  rwn = 0; word = 16'b11110101_11110101; w_addr = 0;
        #clk_c  rwn = 0; word = 16'b101xxxxx_101xxxxx; w_addr = 1;
        #clk_c  rwn = 0; word = 16'b10110x11_10110x11; w_addr = 2;
        #clk_c  rwn = 0; word = 16'b0100xx01_0100xx01; w_addr = 3;
        #clk_c  rwn = 1; word = 16'b11xx0101_11xx0101;
        #clk_c  rwn = 1; word = 16'b10011011_10011011;
        #clk_c  rwn = 1; word = 16'b10xxxxxx_10xxxxxx;
        #clk_c  $finish;
    end
    
endmodule

AZ9/report/waveform.vcd
$date
	Fri May 14 23:35:20 2021
$end
$version
	Icarus Verilog
$end
$timescale
	1s
$end
$scope module testbench $end
$scope module tcam $end
$var wire 4 ! address [3:0] $end
$var wire 1 " clk $end
$var wire 1 # rwn $end
$var wire 16 $ word [15:0] $end
$var reg 5 % i [4:0] $end
$var reg 4 & read_candidate [3:0] $end
$scope function equals $end
$var reg 16 ' a [15:0] $end
$var reg 16 ( b [15:0] $end
$var reg 1 ) equals $end
$var reg 1 * flag $end
$var reg 16 + j [15:0] $end
$upscope $end
$scope function number_of_x $end
$var reg 16 , c [15:0] $end
$var reg 16 - j [15:0] $end
$var reg 16 . number [15:0] $end
$var reg 16 / number_of_x [15:0] $end
$upscope $end
$upscope $end
$upscope $end
$enddefinitions $end
#0
$dumpvars
bx /
bx .
bx -
bx ,
bx +
x*
x)
bx (
bx '
bx &
bx %
bx $
x#
0"
bx !
$end
#5
1"
#10
b0 !
0"
b111xx110111xx11 $
0#
#15
1"
#20
b1 !
0"
b11x0100111x01001 $
#25
1"
#30
b10 !
0"
b1110x1101110x11 $
#35
1"
#40
b11 !
0"
b1101xx111101xx11 $
#45
1"
#50
bx !
0"
b111xx110111xx11 $
1#
#55
b10 !
b10 &
b10 /
b10000 -
b10 .
b1110x1101110x11 ,
1)
b10000 +
1*
bx '
b111xx110111xx11 (
b10000 %
1"
#60
0"
bx $
#65
b1 !
b10 /
b10000 -
b10 .
b11x0100111x01001 ,
b10000 +
bx '
bx (
b10000 %
b1 &
1"
#70
0"
b11xxxx1111xxxx11 $
#75
b11 !
b100 /
b10000 -
b100 .
b1101xx111101xx11 ,
1)
1*
b10000 +
bx '
b11xxxx1111xxxx11 (
b10000 %
b11 &
1"
#80
b0 !
0"
b1111010111110101 $
0#
#85
1"
#90
b1 !
0"
b101xxxxx101xxxxx $
#95
1"
#100
b10 !
0"
b10110x1110110x11 $
#105
1"
#110
b11 !
0"
b100xx010100xx01 $
#115
1"
#120
0"
b11xx010111xx0101 $
1#
#125
b0 !
1)
1*
b0 /
b10000 -
b0 .
b1111010111110101 ,
b10000 +
bx '
b11xx010111xx0101 (
b10000 %
b0 &
1"
#130
0"
b1001101110011011 $
#135
bx !
b10000 /
b10000 .
b10000 -
bx ,
1)
1*
b10000 +
bx '
b1001101110011011 (
b10000 %
bx &
1"
#140
0"
b10xxxxxx10xxxxxx $
#145
b10 !
b10 &
b10 /
b10000 -
b10 .
b10110x1110110x11 ,
1)
1*
b10000 +
bx '
b10xxxxxx10xxxxxx (
b10000 %
1"
