AZ7/RX.v
`define RST 2'b00
`define RECV 2'b01
`define IDLE 2'b11

module RX (clk,
           rstn,
           channel_in,
           data_out,
           is_valid);
    
    parameter BIT_LEN = 7;
    
    input clk, rstn, channel_in;
    output reg is_valid;
    output reg [BIT_LEN - 1:0] data_out;
    
    reg [1:0] state;
    reg parity;
    reg [BIT_LEN - 1:0] buffer;
    reg [$clog2(BIT_LEN + 1 + 1 + 1):0] fetch_idx;
    
    always @(posedge clk or negedge rstn) begin
        // $display("rx:%d", channel_in);
        if (!rstn) begin
            state <= `RST;
        end
        else begin
            case (state)
                `IDLE:
                begin
                    if (channel_in) begin
                        state <= `RECV;
                    end
                end
                `RECV:
                begin
                    if (channel_in && fetch_idx > BIT_LEN + 1) begin
                        state <= `IDLE;
                    end
                    else if (fetch_idx < BIT_LEN + 2) begin
                        fetch_idx <= fetch_idx + 1;
                    end
                end
                `RST:
                begin
                    if (channel_in) begin
                        state <= `RECV;
                    end
                    else begin
                        state <= `IDLE;
                    end
                end
            endcase
        end
    end
    
    always @(state or fetch_idx) begin
        case (state)
            `IDLE:
            begin
                // do nothing
            end
            `RECV:
            begin
                if (0 < fetch_idx && fetch_idx <= BIT_LEN) begin
                    buffer[fetch_idx - 1] <= channel_in;
                end
                else if (fetch_idx == BIT_LEN + 1) begin
                    parity <= channel_in;
                end
                else if (channel_in && fetch_idx == BIT_LEN + 2) begin
                    data_out <= buffer;
                    is_valid  <= (^buffer == parity);
                    fetch_idx <= 0;
                end
            end
            `RST:
            begin
                is_valid  <= 0;
                parity    <= 0;
                buffer    <= 0;
                fetch_idx <= 0;
                data_out  <= {BIT_LEN{1'bz}};
            end
        endcase
    end
    
endmodule

AZ7/TX.v
`define RST 2'b00
`define SEND 2'b10
`define IDLE 2'b11

module TX (clk,
           rstn,
           start,
           data_in,
           channel_out);
    
    parameter BIT_LEN = 7;
    
    input clk, rstn, start;
    input [BIT_LEN - 1:0] data_in;
    output reg channel_out;
    
    reg [1:0] state;
    reg [BIT_LEN - 1:0] buffer;
    reg [$clog2(BIT_LEN + 1 + 1 + 1):0] send_idx;
    
    always @(posedge clk or negedge rstn) begin
        // $display("tx:%d", channel_out);
        if (!rstn) begin
            state <= `RST;
        end
        else begin
            case (state)
                `IDLE:
                begin
                    if (start) begin
                        state <= `SEND;
                    end
                end
                `SEND:
                begin
                    if (send_idx > BIT_LEN + 1) begin
                        state <= `IDLE;
                    end
                    else begin
                        send_idx <= send_idx + 1;
                    end
                end
                `RST:
                begin
                    if (start) begin
                        state <= `SEND;
                    end
                    else begin
                        state <= `IDLE;
                    end
                end
            endcase
        end
    end
    
    always @(state or send_idx) begin
        case (state)
            `IDLE:
            begin
                // do nothing
            end
            `SEND:
            begin
                if (send_idx == 0) begin
                    buffer      <= data_in;
                    channel_out <= 1;
                end
                else if (0 < send_idx && send_idx <= BIT_LEN) begin
                    channel_out <= buffer[send_idx - 1];
                end
                else if (send_idx == BIT_LEN + 1) begin
                    channel_out <= ^buffer;
                end
                else if (send_idx == BIT_LEN + 2) begin
                    channel_out <= 1;
                    send_idx    <= 0;
                end
            end
            `RST:
            begin
                buffer      <= 0;
                send_idx    <= 0;
                channel_out <= 0;
            end
        endcase
    end
    
endmodule

AZ7/UART.v
module UART(clk,
            rstn,
            tx_start,
            tx_data_in,
            tx_channel_out,
            rx_channel_in,
            rx_data_out,
            rx_out_vaild);
    
    parameter BIT_LEN = 7;
    
    input clk, rstn, tx_start, rx_channel_in;
    input [BIT_LEN-1:0] tx_data_in;
    output tx_channel_out, rx_out_vaild;
    output [BIT_LEN-1:0] rx_data_out;
    
    TX #(.BIT_LEN(BIT_LEN)) tx (
    .clk(clk),
    .rstn(rstn),
    .start(tx_start),
    .data_in(tx_data_in),
    .channel_out(tx_channel_out)
    );
    
    RX #(.BIT_LEN(BIT_LEN)) rx (
    .clk(clk),
    .rstn(rstn),
    .channel_in(rx_channel_in),
    .data_out(rx_data_out),
    .is_valid(rx_out_vaild)
    );
    
    
endmodule

AZ7/testbench.v
`define NULL 0
module testbench();
    
    parameter BIT_LEN = 7;
    parameter clk_c   = 10;
    
    reg clk, u0_rstn, u1_rstn, u0_start, u1_start;
    reg [BIT_LEN - 1:0] u0_in, u1_in;
    wire [BIT_LEN - 1:0] u0_out, u1_out;
    wire u01_channel, u10_channel, u0_valid, u1_vaild;
    
    UART #(.BIT_LEN(BIT_LEN)) uart0(
    .clk(clk),
    .rstn(u0_rstn),
    .tx_start(u0_start),
    .tx_data_in(u0_in),
    .tx_channel_out(u01_channel),
    .rx_channel_in(u10_channel),
    .rx_data_out(u0_out),
    .rx_out_vaild(u0_valid)
    );
    
    UART #(.BIT_LEN(BIT_LEN)) uart1(
    .clk(clk),
    .rstn(u1_rstn),
    .tx_start(u1_start),
    .tx_data_in(u1_in),
    .tx_channel_out(u10_channel),
    .rx_channel_in(u01_channel),
    .rx_data_out(u1_out),
    .rx_out_vaild(u1_valid)
    );
    
    
    initial begin
        $dumpfile("report/waveform.vcd");
        $dumpvars(0,uart0, uart1);
    end
    
    initial begin
        clk         = 0;
        forever clk = #(clk_c/2) ~clk;
    end
    
    integer data_file;
    integer scan_file;
    integer seed;
    initial begin
        data_file = $fopen("seed.dat", "r");
        if (data_file == `NULL) begin
            $display("data_file handle was NULL");
            $finish;
        end
        scan_file = $fscanf(data_file, "%d", seed);
        if (scan_file == `NULL) begin
            $display("integer read error");
            $finish;
        end
    end
    
    initial begin
        u0_rstn = 0;
        u1_rstn = 0;
        #clk_c
        u0_rstn  = 1;
        u1_rstn  = 1;
        u0_start = 1;
        u0_in    = {BIT_LEN{$random(seed)}};
        #200
        $finish;
    end
    
    initial
        $monitor($time, "\t u0:%b -> u1-v:%b(%b), u0_state:%d, u1_state:%d, u0_counter:%d, u1_counter:%d, channel:%b", u0_in, u1_out, uart1.rx.is_valid, uart0.tx.state, uart1.rx.state, uart0.tx.send_idx, uart1.rx.fetch_idx, u01_channel);
    
endmodule

AZ7/report/waveform.vcd
$date
	Mon May  3 01:43:33 2021
$end
$version
	Icarus Verilog
$end
$timescale
	1s
$end
$scope module testbench $end
$scope module uart0 $end
$var wire 1 ! clk $end
$var wire 1 " rstn $end
$var wire 7 # tx_data_in [6:0] $end
$var wire 1 $ tx_start $end
$var wire 1 % tx_channel_out $end
$var wire 1 & rx_out_vaild $end
$var wire 7 ' rx_data_out [6:0] $end
$var wire 1 ( rx_channel_in $end
$scope module rx $end
$var wire 1 ! clk $end
$var wire 1 " rstn $end
$var wire 1 ( channel_in $end
$var reg 7 ) buffer [6:0] $end
$var reg 7 * data_out [6:0] $end
$var reg 5 + fetch_idx [4:0] $end
$var reg 1 & is_valid $end
$var reg 1 , parity $end
$var reg 2 - state [1:0] $end
$upscope $end
$scope module tx $end
$var wire 1 ! clk $end
$var wire 7 . data_in [6:0] $end
$var wire 1 " rstn $end
$var wire 1 $ start $end
$var reg 7 / buffer [6:0] $end
$var reg 1 % channel_out $end
$var reg 5 0 send_idx [4:0] $end
$var reg 2 1 state [1:0] $end
$upscope $end
$upscope $end
$upscope $end
$scope module testbench $end
$scope module uart1 $end
$var wire 1 ! clk $end
$var wire 1 2 rstn $end
$var wire 1 % rx_channel_in $end
$var wire 7 3 tx_data_in [6:0] $end
$var wire 1 4 tx_start $end
$var wire 1 ( tx_channel_out $end
$var wire 1 5 rx_out_vaild $end
$var wire 7 6 rx_data_out [6:0] $end
$scope module rx $end
$var wire 1 % channel_in $end
$var wire 1 ! clk $end
$var wire 1 2 rstn $end
$var reg 7 7 buffer [6:0] $end
$var reg 7 8 data_out [6:0] $end
$var reg 5 9 fetch_idx [4:0] $end
$var reg 1 5 is_valid $end
$var reg 1 : parity $end
$var reg 2 ; state [1:0] $end
$upscope $end
$scope module tx $end
$var wire 1 ! clk $end
$var wire 7 < data_in [6:0] $end
$var wire 1 2 rstn $end
$var wire 1 4 start $end
$var reg 7 = buffer [6:0] $end
$var reg 1 ( channel_out $end
$var reg 5 > send_idx [4:0] $end
$var reg 2 ? state [1:0] $end
$upscope $end
$upscope $end
$upscope $end
$enddefinitions $end
#0
$dumpvars
b0 ?
b0 >
b0 =
bx <
b0 ;
0:
b0 9
bz 8
b0 7
bz 6
05
x4
bx 3
02
b0 1
b0 0
b0 /
bx .
b0 -
0,
b0 +
bz *
b0 )
0(
bz '
0&
0%
x$
bx #
0"
0!
$end
#5
1!
#10
0!
b1100001 #
b1100001 .
1$
12
1"
#15
1%
b1100001 /
b10 1
b11 -
b11 ?
b11 ;
1!
#20
0!
#25
b1 0
b1 ;
1!
#30
0!
#35
0%
b1 7
b10 0
b1 9
1!
#40
0!
#45
b11 0
b10 9
1!
#50
0!
#55
b100 0
b11 9
1!
#60
0!
#65
b101 0
b100 9
1!
#70
0!
#75
1%
b110 0
b101 9
1!
#80
0!
#85
b100001 7
b111 0
b110 9
1!
#90
0!
#95
b1100001 7
b1000 0
b111 9
1!
#100
0!
#105
1:
b0 0
b1000 9
1!
#110
0!
#115
15
b1100001 6
b1100001 8
b1 0
b0 9
1!
#120
0!
#125
0%
b10 0
b1 9
1!
#130
0!
#135
b11 0
b10 9
1!
#140
0!
#145
b100 0
b11 9
1!
#150
0!
#155
b101 0
b100 9
1!
#160
0!
#165
1%
b110 0
b101 9
1!
#170
0!
#175
b111 0
b110 9
1!
#180
0!
#185
b1000 0
b111 9
1!
#190
0!
#195
b0 0
b1000 9
1!
#200
0!
#205
b1 0
b0 9
1!
