AZ7/noise_gen.v
module NOISE_GENERATOR(clk,
                       sig_in,
                       en,
                       sig_out);
    
    input clk, sig_in, en;
    output sig_out;
    
    integer counter;
    
    assign sig_out = (en) ? ((counter == 5) || sig_in) : sig_in;
    
    always @(posedge clk) begin
        if (counter < 10) begin
            counter = counter + 1;
        end
        else begin
            counter = 0;
        end
    end
endmodule

AZ7/RX.v
`define RST 1'b0
`define RECV 1'b1

module RX (clk,
           rstn,
           channel_in,
           data_out,
           is_valid);
    
    parameter BIT_LEN = 7;
    
    input clk, rstn, channel_in;
    output reg is_valid;
    output reg [BIT_LEN - 1:0] data_out;
    
    reg state, parity;
    reg [BIT_LEN - 1:0] buffer;
    reg [$clog2(BIT_LEN + 1 + 1 + 1):0] fetch_idx;
    
    always @(posedge clk or negedge rstn) begin
        if (!rstn) begin
            state <= `RST;
        end
        else begin
            case (state)
                `RECV:
                begin
                    if (channel_in && fetch_idx > BIT_LEN + 1) begin
                        state <= `RST;
                    end
                    else if (fetch_idx < BIT_LEN + 2) begin
                        fetch_idx <= fetch_idx + 1;
                    end
                end
                `RST:
                begin
                    if (channel_in) begin
                        state <= `RECV;
                    end
                end
            endcase
        end
    end
    
    always @(state or fetch_idx) begin
        case (state)
            `RECV:
            begin
                if (fetch_idx <= BIT_LEN && fetch_idx > 0) begin
                    buffer[fetch_idx - 1] <= channel_in;
                end
                else if (fetch_idx == BIT_LEN + 1) begin
                    parity <= channel_in;
                end
                else if (channel_in && fetch_idx == BIT_LEN + 2) begin
                    data_out <= buffer;
                    is_valid <= (^buffer == parity);
                end
            end
            `RST:
            begin
                parity    <= 0;
                buffer    <= 0;
                fetch_idx <= 0;
            end
        endcase
    end
    
endmodule

AZ7/TX.v
`define RST 1'b0
`define SEND 1'b1

module TX (clk,
           rstn,
           start,
           data_in,
           channel_out);
    
    parameter BIT_LEN = 7;
    
    input clk, rstn, start;
    input [BIT_LEN - 1:0] data_in;
    output reg channel_out;
    
    reg state;
    reg [BIT_LEN - 1:0] buffer;
    reg [$clog2(BIT_LEN + 1 + 1 + 1):0] send_idx;
    
    always @(posedge clk or negedge rstn) begin
        if (!rstn) begin
            state <= `RST;
        end
        else begin
            case (state)
                `SEND:
                begin
                    if (send_idx > BIT_LEN + 2) begin
                        state <= `RST;
                    end
                    else begin
                        send_idx <= send_idx + 1;
                    end
                end
                `RST:
                begin
                    if (start) begin
                        state <= `SEND;
                    end
                end
            endcase
        end
    end
    
    always @(state or send_idx) begin
        case (state)
            `SEND:
            begin
                if (send_idx == 0) begin
                    buffer      <= data_in;
                    channel_out <= 1;
                end
                else if (0 < send_idx && send_idx <= BIT_LEN) begin
                    channel_out <= buffer[send_idx - 1];
                end
                else if (send_idx == BIT_LEN + 1) begin
                    channel_out <= ^buffer;
                end
                else if (send_idx > BIT_LEN + 1) begin
                    channel_out <= 1;
                end
            end
            `RST:
            begin
                buffer      <= 0;
                send_idx    <= 0;
                channel_out <= 0;
            end
        endcase
    end
    
endmodule

AZ7/UART.v
module UART(clk,
            rstn,
            tx_start,
            tx_data_in,
            tx_channel_out,
            rx_channel_in,
            rx_data_out,
            rx_out_vaild);
    
    parameter BIT_LEN = 7;
    
    input clk, rstn, tx_start, rx_channel_in;
    input [BIT_LEN-1:0] tx_data_in;
    output tx_channel_out, rx_out_vaild;
    output [BIT_LEN-1:0] rx_data_out;
    
    TX #(.BIT_LEN(BIT_LEN)) tx (
    .clk(clk),
    .rstn(rstn),
    .start(tx_start),
    .data_in(tx_data_in),
    .channel_out(tx_channel_out)
    );
    
    RX #(.BIT_LEN(BIT_LEN)) rx (
    .clk(clk),
    .rstn(rstn),
    .channel_in(rx_channel_in),
    .data_out(rx_data_out),
    .is_valid(rx_out_vaild)
    );
    
    
endmodule

AZ7/testbench.v
`define NULL 0
module testbench();
    
    parameter BIT_LEN = 7;
    parameter clk_c   = 10;
    
    reg clk, u0_rstn, u1_rstn, u0_start, u1_start, ng0_en, ng1_en;
    reg [BIT_LEN - 1:0] u0_in, u1_in;
    wire [BIT_LEN - 1:0] u0_out, u1_out;
    wire u0_rx_channel, u0_tx_channel, u1_rx_channel, u1_tx_channel, u0_valid, u1_vaild;
    
    UART #(.BIT_LEN(BIT_LEN)) uart0(
    .clk(clk),
    .rstn(u0_rstn),
    .tx_start(u0_start),
    .tx_data_in(u0_in),
    .tx_channel_out(u0_tx_channel),
    .rx_channel_in(u0_rx_channel),
    .rx_data_out(u0_out),
    .rx_out_vaild(u0_valid)
    );
    
    UART #(.BIT_LEN(BIT_LEN)) uart1(
    .clk(clk),
    .rstn(u1_rstn),
    .tx_start(u1_start),
    .tx_data_in(u1_in),
    .tx_channel_out(u1_tx_channel),
    .rx_channel_in(u1_rx_channel),
    .rx_data_out(u1_out),
    .rx_out_vaild(u1_valid)
    );
    
    NOISE_GENERATOR ng0 (
    .clk(clk),
    .sig_in(u0_tx_channel),
    .en(ng0_en),
    .sig_out(u1_rx_channel)
    );
    
    NOISE_GENERATOR ng1 (
    .clk(clk),
    .sig_in(u1_tx_channel),
    .en(ng1_en),
    .sig_out(u0_rx_channel)
    );
    
    initial begin
        $dumpfile("report/waveform.vcd");
        $dumpvars(0,uart0, uart1);
    end
    
    initial begin
        clk         = 0;
        forever clk = #(clk_c/2) ~clk;
    end
    
    integer data_file;
    integer scan_file;
    integer seed;
    initial begin
        data_file = $fopen("seed.dat", "r");
        if (data_file == `NULL) begin
            $display("data_file handle was NULL");
            $finish;
        end
        scan_file = $fscanf(data_file, "%d", seed);
        if (scan_file == `NULL) begin
            $display("integer read error");
            $finish;
        end
    end
    
    integer i;
    integer n;
    initial begin
        u0_rstn = 0;
        u1_rstn = 0;
        ng1_en  = 0;
        ng0_en  = 0;
        #clk_c;
        u0_rstn = 1;
        u1_rstn = 1;
        n       = 50;
        
        $display("test connection uart0 -> uart1");
        for (i = 0; i < n; i++) begin
            u0_start = 1;
            u0_in    = {BIT_LEN{$random(seed)}};
            #clk_c
            u0_start = 0;
            while(uart1.rx.state || uart0.tx.state) begin
                #clk_c;
            end
            if (u0_in == u1_out) begin
                $display("#%d (u0:%b -> u1-v:%b(%b)) test passed", i, u0_in, u1_out, u1_valid);
            end
            else begin
                $display("#%d (u0:%b -> u1-v:%b(%b)) test failed", i, u0_in, u1_out, u1_valid);
            end
        end
        
        $display("test connection uart1 -> uart0");
        for (i = 0; i < n; i++) begin
            u1_start = 1;
            u1_in    = {BIT_LEN{$random(seed)}};
            #clk_c
            u1_start = 0;
            while(uart0.rx.state || uart1.tx.state) begin
                #clk_c;
            end
            if (u1_in == u0_out) begin
                $display("#%d (u1:%b -> u0-v:%b(%b)) test passed", i, u1_in, u0_out, u0_valid);
            end
            else begin
                $display("#%d (u1:%b -> u0-v:%b(%b)) test failed", i, u1_in, u0_out, u0_valid);
            end
        end
        
        // n      = 10;
        // ng0_en = 1;
        // #clk_c
        // $display("test connection with error uart0 -> uart1");
        // for (i = 0; i < n; i++) begin
        //     u0_start = 1;
        //     u0_in    = {BIT_LEN{$random(seed)}};
        //     #clk_c
        //     u0_start = 0;
        //     while(uart1.rx.state || uart0.tx.state) begin
        //         #clk_c;
        //     end
        //     if (u0_in == u1_out) begin
        //         $display("#%d (u0:%b -> u1-v:%b(%b)) test passed", i, u0_in, u1_out, u1_valid);
        //     end
        //     else begin
        //         $display("#%d (u0:%b -> u1-v:%b(%b)) test failed", i, u0_in, u1_out, u1_valid);
        //     end
        // end
        
        // ng1_en = 1;
        // #clk_c;
        // $display("test connection with error uart0 -> uart1");
        // for (i = 0; i < n; i++) begin
        //     u1_start = 1;
        //     u1_in    = {BIT_LEN{$random(seed)}};
        //     #clk_c
        //     u1_start = 0;
        //     while(uart0.rx.state || uart1.tx.state) begin
        //         #clk_c;
        //     end
        //     if (u1_in == u0_out) begin
        //         $display("#%d (u1:%b -> u0-v:%b(%b)) test passed", i, u1_in, u0_out, u0_valid);
        //     end
        //     else begin
        //         $display("#%d (u1:%b -> u0-v:%b(%b)) test failed", i, u1_in, u0_out, u0_valid);
        //     end
        // end
        $finish;
    end
    
    
    // initial
    //     $monitor($time, "\t u0:%b -> u1-v:%b(%b), u0_state:%d, u1_state:%d, u0_counter:%d, u1_counter:%d, channel:%b", u0_in, u1_out, uart1.rx.is_valid, uart0.tx.state, uart1.rx.state, uart0.tx.send_idx, uart1.rx.fetch_idx, u01_channel);
    
endmodule

AZ7/report/waveform.vcd
$date
	Mon May  3 12:05:15 2021
$end
$version
	Icarus Verilog
$end
$timescale
	1s
$end
$scope module testbench $end
$scope module uart0 $end
$var wire 1 ! clk $end
$var wire 1 " rstn $end
$var wire 1 # rx_channel_in $end
$var wire 7 $ tx_data_in [6:0] $end
$var wire 1 % tx_start $end
$var wire 1 & tx_channel_out $end
$var wire 1 ' rx_out_vaild $end
$var wire 7 ( rx_data_out [6:0] $end
$scope module rx $end
$var wire 1 # channel_in $end
$var wire 1 ! clk $end
$var wire 1 " rstn $end
$var reg 7 ) buffer [6:0] $end
$var reg 7 * data_out [6:0] $end
$var reg 5 + fetch_idx [4:0] $end
$var reg 1 ' is_valid $end
$var reg 1 , parity $end
$var reg 1 - state $end
$upscope $end
$scope module tx $end
$var wire 1 ! clk $end
$var wire 7 . data_in [6:0] $end
$var wire 1 " rstn $end
$var wire 1 % start $end
$var reg 7 / buffer [6:0] $end
$var reg 1 & channel_out $end
$var reg 5 0 send_idx [4:0] $end
$var reg 1 1 state $end
$upscope $end
$upscope $end
$upscope $end
$scope module testbench $end
$scope module uart1 $end
$var wire 1 ! clk $end
$var wire 1 2 rstn $end
$var wire 1 3 rx_channel_in $end
$var wire 7 4 tx_data_in [6:0] $end
$var wire 1 5 tx_start $end
$var wire 1 6 tx_channel_out $end
$var wire 1 7 rx_out_vaild $end
$var wire 7 8 rx_data_out [6:0] $end
$scope module rx $end
$var wire 1 3 channel_in $end
$var wire 1 ! clk $end
$var wire 1 2 rstn $end
$var reg 7 9 buffer [6:0] $end
$var reg 7 : data_out [6:0] $end
$var reg 5 ; fetch_idx [4:0] $end
$var reg 1 7 is_valid $end
$var reg 1 < parity $end
$var reg 1 = state $end
$upscope $end
$scope module tx $end
$var wire 1 ! clk $end
$var wire 7 > data_in [6:0] $end
$var wire 1 2 rstn $end
$var wire 1 5 start $end
$var reg 7 ? buffer [6:0] $end
$var reg 1 6 channel_out $end
$var reg 5 @ send_idx [4:0] $end
$var reg 1 A state $end
$upscope $end
$upscope $end
$upscope $end
$enddefinitions $end
#0
$dumpvars
0A
b0 @
b0 ?
bx >
0=
0<
b0 ;
bx :
b0 9
bx 8
x7
06
x5
bx 4
03
02
01
b0 0
b0 /
bx .
0-
0,
b0 +
bx *
b0 )
bx (
x'
0&
x%
bx $
0#
0"
0!
$end
#5
1!
#10
0!
b1000001 $
b1000001 .
1%
12
1"
#15
13
1&
b1000001 /
11
1!
#20
0!
0%
#25
b1 0
1=
1!
#30
0!
#35
03
0&
b1 9
b10 0
b1 ;
1!
#40
0!
#45
b11 0
b10 ;
1!
#50
0!
#55
b100 0
b11 ;
1!
#60
0!
#65
b101 0
b100 ;
1!
#70
0!
#75
b110 0
b101 ;
1!
#80
0!
#85
13
1&
b111 0
b110 ;
1!
#90
0!
#95
03
0&
b1000001 9
b1000 0
b111 ;
1!
#100
0!
#105
13
1&
b1001 0
b1000 ;
1!
#110
0!
#115
17
b1000001 8
b1000001 :
b1010 0
b1001 ;
1!
#120
0!
#125
03
0&
b0 0
b0 /
b0 ;
b0 9
01
0=
1!
#130
0!
b10000 $
b10000 .
1%
#135
13
1&
b10000 /
11
1!
#140
0!
0%
#145
03
0&
b1 0
1=
1!
#150
0!
#155
b10 0
b1 ;
1!
#160
0!
#165
b11 0
b10 ;
1!
#170
0!
#175
b100 0
b11 ;
1!
#180
0!
#185
13
1&
b101 0
b100 ;
1!
#190
0!
#195
03
0&
b10000 9
b110 0
b101 ;
1!
#200
0!
#205
b111 0
b110 ;
1!
#210
0!
#215
13
1&
b1000 0
b111 ;
1!
#220
0!
#225
1<
b1001 0
b1000 ;
1!
#230
0!
#235
b10000 8
b10000 :
b1010 0
b1001 ;
1!
#240
0!
#245
03
0&
b0 0
b0 /
b0 ;
b0 9
0<
01
0=
1!
#250
0!
b1111100 $
b1111100 .
1%
#255
13
1&
b1111100 /
11
1!
#260
0!
0%
#265
03
0&
b1 0
1=
1!
#270
0!
#275
b10 0
b1 ;
1!
#280
0!
#285
13
1&
b11 0
b10 ;
1!
#290
0!
#295
b100 9
b100 0
b11 ;
1!
#300
0!
#305
b1100 9
b101 0
b100 ;
1!
#310
0!
#315
b11100 9
b110 0
b101 ;
1!
#320
0!
#325
b111100 9
b111 0
b110 ;
1!
#330
0!
#335
b1111100 9
b1000 0
b111 ;
1!
#340
0!
#345
1<
b1001 0
b1000 ;
1!
#350
0!
#355
b1111100 8
b1111100 :
b1010 0
b1001 ;
1!
#360
0!
#365
03
0&
b0 0
b0 /
b0 ;
b0 9
0<
01
0=
1!
#370
0!
b11011 $
b11011 .
1%
#375
13
1&
b11011 /
11
1!
#380
0!
0%
#385
b1 0
1=
1!
#390
0!
#395
b1 9
b10 0
b1 ;
1!
#400
0!
#405
03
0&
b11 9
b11 0
b10 ;
1!
#410
0!
#415
13
1&
b100 0
b11 ;
1!
#420
0!
#425
b1011 9
b101 0
b100 ;
1!
#430
0!
#435
03
0&
b11011 9
b110 0
b101 ;
1!
#440
0!
#445
b111 0
b110 ;
1!
#450
0!
#455
b1000 0
b111 ;
1!
#460
0!
#465
13
1&
b1001 0
b1000 ;
1!
#470
0!
#475
b11011 8
b11011 :
b1010 0
b1001 ;
1!
#480
0!
#485
03
0&
b0 0
b0 /
b0 ;
b0 9
01
0=
1!
#490
0!
b1011 $
b1011 .
1%
#495
13
1&
b1011 /
11
1!
#500
0!
0%
#505
b1 0
1=
1!
#510
0!
#515
b1 9
b10 0
b1 ;
1!
#520
0!
#525
03
0&
b11 9
b11 0
b10 ;
1!
#530
0!
#535
13
1&
b100 0
b11 ;
1!
#540
0!
#545
03
0&
b1011 9
b101 0
b100 ;
1!
#550
0!
#555
b110 0
b101 ;
1!
#560
0!
#565
b111 0
b110 ;
1!
#570
0!
#575
13
1&
b1000 0
b111 ;
1!
#580
0!
#585
1<
b1001 0
b1000 ;
1!
#590
0!
#595
b1011 8
b1011 :
b1010 0
b1001 ;
1!
#600
0!
#605
03
0&
b0 0
b0 /
b0 ;
b0 9
0<
01
0=
1!
#610
0!
b1111000 $
b1111000 .
1%
#615
13
1&
b1111000 /
11
1!
#620
0!
0%
#625
03
0&
b1 0
1=
1!
#630
0!
#635
b10 0
b1 ;
1!
#640
0!
#645
b11 0
b10 ;
1!
#650
0!
#655
13
1&
b100 0
b11 ;
1!
#660
0!
#665
b1000 9
b101 0
b100 ;
1!
#670
0!
#675
b11000 9
b110 0
b101 ;
1!
#680
0!
#685
b111000 9
b111 0
b110 ;
1!
#690
0!
#695
03
0&
b1111000 9
b1000 0
b111 ;
1!
#700
0!
#705
13
1&
b1001 0
b1000 ;
1!
#710
0!
#715
b1111000 8
b1111000 :
b1010 0
b1001 ;
1!
#720
0!
#725
03
0&
b0 0
b0 /
b0 ;
b0 9
01
0=
1!
#730
0!
b1111100 $
b1111100 .
1%
#735
13
1&
b1111100 /
11
1!
#740
0!
0%
#745
03
0&
b1 0
1=
1!
#750
0!
#755
b10 0
b1 ;
1!
#760
0!
#765
13
1&
b11 0
b10 ;
1!
#770
0!
#775
b100 9
b100 0
b11 ;
1!
#780
0!
#785
b1100 9
b101 0
b100 ;
1!
#790
0!
#795
b11100 9
b110 0
b101 ;
1!
#800
0!
#805
b111100 9
b111 0
b110 ;
1!
#810
0!
#815
b1111100 9
b1000 0
b111 ;
1!
#820
0!
#825
1<
b1001 0
b1000 ;
1!
#830
0!
#835
b1111100 8
b1111100 :
b1010 0
b1001 ;
1!
#840
0!
#845
03
0&
b0 0
b0 /
b0 ;
b0 9
0<
01
0=
1!
#850
0!
b1001101 $
b1001101 .
1%
#855
13
1&
b1001101 /
11
1!
#860
0!
0%
#865
b1 0
1=
1!
#870
0!
#875
03
0&
b1 9
b10 0
b1 ;
1!
#880
0!
#885
13
1&
b11 0
b10 ;
1!
#890
0!
#895
b101 9
b100 0
b11 ;
1!
#900
0!
#905
03
0&
b1101 9
b101 0
b100 ;
1!
#910
0!
#915
b110 0
b101 ;
1!
#920
0!
#925
13
1&
b111 0
b110 ;
1!
#930
0!
#935
03
0&
b1001101 9
b1000 0
b111 ;
1!
#940
0!
#945
13
1&
b1001 0
b1000 ;
1!
#950
0!
#955
b1001101 8
b1001101 :
b1010 0
b1001 ;
1!
#960
0!
#965
03
0&
b0 0
b0 /
b0 ;
b0 9
01
0=
1!
#970
0!
b1001001 $
b1001001 .
1%
#975
13
1&
b1001001 /
11
1!
#980
0!
0%
#985
b1 0
1=
1!
#990
0!
#995
03
0&
b1 9
b10 0
b1 ;
1!
#1000
0!
#1005
b11 0
b10 ;
1!
#1010
0!
#1015
13
1&
b100 0
b11 ;
1!
#1020
0!
#1025
03
0&
b1001 9
b101 0
b100 ;
1!
#1030
0!
#1035
b110 0
b101 ;
1!
#1040
0!
#1045
13
1&
b111 0
b110 ;
1!
#1050
0!
#1055
b1001001 9
b1000 0
b111 ;
1!
#1060
0!
#1065
1<
b1001 0
b1000 ;
1!
#1070
0!
#1075
b1001001 8
b1001001 :
b1010 0
b1001 ;
1!
#1080
0!
#1085
03
0&
b0 0
b0 /
b0 ;
b0 9
0<
01
0=
1!
#1090
0!
b1110 $
b1110 .
1%
#1095
13
1&
b1110 /
11
1!
#1100
0!
0%
#1105
03
0&
b1 0
1=
1!
#1110
0!
#1115
13
1&
b10 0
b1 ;
1!
#1120
0!
#1125
b10 9
b11 0
b10 ;
1!
#1130
0!
#1135
b110 9
b100 0
b11 ;
1!
#1140
0!
#1145
03
0&
b1110 9
b101 0
b100 ;
1!
#1150
0!
#1155
b110 0
b101 ;
1!
#1160
0!
#1165
b111 0
b110 ;
1!
#1170
0!
#1175
13
1&
b1000 0
b111 ;
1!
#1180
0!
#1185
1<
b1001 0
b1000 ;
1!
#1190
0!
#1195
b1110 8
b1110 :
b1010 0
b1001 ;
1!
#1200
0!
#1205
03
0&
b0 0
b0 /
b0 ;
b0 9
0<
01
0=
1!
#1210
0!
b110011 $
b110011 .
1%
#1215
13
1&
b110011 /
11
1!
#1220
0!
0%
#1225
b1 0
1=
1!
#1230
0!
#1235
b1 9
b10 0
b1 ;
1!
#1240
0!
#1245
03
0&
b11 9
b11 0
b10 ;
1!
#1250
0!
#1255
b100 0
b11 ;
1!
#1260
0!
#1265
13
1&
b101 0
b100 ;
1!
#1270
0!
#1275
b10011 9
b110 0
b101 ;
1!
#1280
0!
#1285
03
0&
b110011 9
b111 0
b110 ;
1!
#1290
0!
#1295
b1000 0
b111 ;
1!
#1300
0!
#1305
13
1&
b1001 0
b1000 ;
1!
#1310
0!
#1315
b110011 8
b110011 :
b1010 0
b1001 ;
1!
#1320
0!
#1325
03
0&
b0 0
b0 /
b0 ;
b0 9
01
0=
1!
#1330
0!
b1001111 $
b1001111 .
1%
#1335
13
1&
b1001111 /
11
1!
#1340
0!
0%
#1345
b1 0
1=
1!
#1350
0!
#1355
b1 9
b10 0
b1 ;
1!
#1360
0!
#1365
b11 9
b11 0
b10 ;
1!
#1370
0!
#1375
b111 9
b100 0
b11 ;
1!
#1380
0!
#1385
03
0&
b1111 9
b101 0
b100 ;
1!
#1390
0!
#1395
b110 0
b101 ;
1!
#1400
0!
#1405
13
1&
b111 0
b110 ;
1!
#1410
0!
#1415
b1001111 9
b1000 0
b111 ;
1!
#1420
0!
#1425
1<
b1001 0
b1000 ;
1!
#1430
0!
#1435
b1001111 8
b1001111 :
b1010 0
b1001 ;
1!
#1440
0!
#1445
03
0&
b0 0
b0 /
b0 ;
b0 9
0<
01
0=
1!
#1450
0!
b101110 $
b101110 .
1%
#1455
13
1&
b101110 /
11
1!
#1460
0!
0%
#1465
03
0&
b1 0
1=
1!
#1470
0!
#1475
13
1&
b10 0
b1 ;
1!
#1480
0!
#1485
b10 9
b11 0
b10 ;
1!
#1490
0!
#1495
b110 9
b100 0
b11 ;
1!
#1500
0!
#1505
03
0&
b1110 9
b101 0
b100 ;
1!
#1510
0!
#1515
13
1&
b110 0
b101 ;
1!
#1520
0!
#1525
03
0&
b101110 9
b111 0
b110 ;
1!
#1530
0!
#1535
b1000 0
b111 ;
1!
#1540
0!
#1545
13
1&
b1001 0
b1000 ;
1!
#1550
0!
#1555
b101110 8
b101110 :
b1010 0
b1001 ;
1!
#1560
0!
#1565
03
0&
b0 0
b0 /
b0 ;
b0 9
01
0=
1!
#1570
0!
b1111000 $
b1111000 .
1%
#1575
13
1&
b1111000 /
11
1!
#1580
0!
0%
#1585
03
0&
b1 0
1=
1!
#1590
0!
#1595
b10 0
b1 ;
1!
#1600
0!
#1605
b11 0
b10 ;
1!
#1610
0!
#1615
13
1&
b100 0
b11 ;
1!
#1620
0!
#1625
b1000 9
b101 0
b100 ;
1!
#1630
0!
#1635
b11000 9
b110 0
b101 ;
1!
#1640
0!
#1645
b111000 9
b111 0
b110 ;
1!
#1650
0!
#1655
03
0&
b1111000 9
b1000 0
b111 ;
1!
#1660
0!
#1665
13
1&
b1001 0
b1000 ;
1!
#1670
0!
#1675
b1111000 8
b1111000 :
b1010 0
b1001 ;
1!
#1680
0!
#1685
03
0&
b0 0
b0 /
b0 ;
b0 9
01
0=
1!
#1690
0!
b1110000 $
b1110000 .
1%
#1695
13
1&
b1110000 /
11
1!
#1700
0!
0%
#1705
03
0&
b1 0
1=
1!
#1710
0!
#1715
b10 0
b1 ;
1!
#1720
0!
#1725
b11 0
b10 ;
1!
#1730
0!
#1735
b100 0
b11 ;
1!
#1740
0!
#1745
13
1&
b101 0
b100 ;
1!
#1750
0!
#1755
b10000 9
b110 0
b101 ;
1!
#1760
0!
#1765
b110000 9
b111 0
b110 ;
1!
#1770
0!
#1775
b1110000 9
b1000 0
b111 ;
1!
#1780
0!
#1785
1<
b1001 0
b1000 ;
1!
#1790
0!
#1795
b1110000 8
b1110000 :
b1010 0
b1001 ;
1!
#1800
0!
#1805
03
0&
b0 0
b0 /
b0 ;
b0 9
0<
01
0=
1!
#1810
0!
b1 $
b1 .
1%
#1815
13
1&
b1 /
11
1!
#1820
0!
0%
#1825
b1 0
1=
1!
#1830
0!
#1835
03
0&
b1 9
b10 0
b1 ;
1!
#1840
0!
#1845
b11 0
b10 ;
1!
#1850
0!
#1855
b100 0
b11 ;
1!
#1860
0!
#1865
b101 0
b100 ;
1!
#1870
0!
#1875
b110 0
b101 ;
1!
#1880
0!
#1885
b111 0
b110 ;
1!
#1890
0!
#1895
13
1&
b1000 0
b111 ;
1!
#1900
0!
#1905
1<
b1001 0
b1000 ;
1!
#1910
0!
#1915
b1 8
b1 :
b1010 0
b1001 ;
1!
#1920
0!
#1925
03
0&
b0 0
b0 /
b0 ;
b0 9
0<
01
0=
1!
#1930
0!
b1011100 $
b1011100 .
1%
#1935
13
1&
b1011100 /
11
1!
#1940
0!
0%
#1945
03
0&
b1 0
1=
1!
#1950
0!
#1955
b10 0
b1 ;
1!
#1960
0!
#1965
13
1&
b11 0
b10 ;
1!
#1970
0!
#1975
b100 9
b100 0
b11 ;
1!
#1980
0!
#1985
b1100 9
b101 0
b100 ;
1!
#1990
0!
#1995
03
0&
b11100 9
b110 0
b101 ;
1!
#2000
0!
#2005
13
1&
b111 0
b110 ;
1!
#2010
0!
#2015
03
0&
b1011100 9
b1000 0
b111 ;
1!
#2020
0!
#2025
13
1&
b1001 0
b1000 ;
1!
#2030
0!
#2035
b1011100 8
b1011100 :
b1010 0
b1001 ;
1!
#2040
0!
#2045
03
0&
b0 0
b0 /
b0 ;
b0 9
01
0=
1!
#2050
0!
b111 $
b111 .
1%
#2055
13
1&
b111 /
11
1!
#2060
0!
0%
#2065
b1 0
1=
1!
#2070
0!
#2075
b1 9
b10 0
b1 ;
1!
#2080
0!
#2085
b11 9
b11 0
b10 ;
1!
#2090
0!
#2095
03
0&
b111 9
b100 0
b11 ;
1!
#2100
0!
#2105
b101 0
b100 ;
1!
#2110
0!
#2115
b110 0
b101 ;
1!
#2120
0!
#2125
b111 0
b110 ;
1!
#2130
0!
#2135
13
1&
b1000 0
b111 ;
1!
#2140
0!
#2145
1<
b1001 0
b1000 ;
1!
#2150
0!
#2155
b111 8
b111 :
b1010 0
b1001 ;
1!
#2160
0!
#2165
03
0&
b0 0
b0 /
b0 ;
b0 9
0<
01
0=
1!
#2170
0!
b111101 $
b111101 .
1%
#2175
13
1&
b111101 /
11
1!
#2180
0!
0%
#2185
b1 0
1=
1!
#2190
0!
#2195
03
0&
b1 9
b10 0
b1 ;
1!
#2200
0!
#2205
13
1&
b11 0
b10 ;
1!
#2210
0!
#2215
b101 9
b100 0
b11 ;
1!
#2220
0!
#2225
b1101 9
b101 0
b100 ;
1!
#2230
0!
#2235
b11101 9
b110 0
b101 ;
1!
#2240
0!
#2245
03
0&
b111101 9
b111 0
b110 ;
1!
#2250
0!
#2255
13
1&
b1000 0
b111 ;
1!
#2260
0!
#2265
1<
b1001 0
b1000 ;
1!
#2270
0!
#2275
b111101 8
b111101 :
b1010 0
b1001 ;
1!
#2280
0!
#2285
03
0&
b0 0
b0 /
b0 ;
b0 9
0<
01
0=
1!
#2290
0!
b1000000 $
b1000000 .
1%
#2295
13
1&
b1000000 /
11
1!
#2300
0!
0%
#2305
03
0&
b1 0
1=
1!
#2310
0!
#2315
b10 0
b1 ;
1!
#2320
0!
#2325
b11 0
b10 ;
1!
#2330
0!
#2335
b100 0
b11 ;
1!
#2340
0!
#2345
b101 0
b100 ;
1!
#2350
0!
#2355
b110 0
b101 ;
1!
#2360
0!
#2365
13
1&
b111 0
b110 ;
1!
#2370
0!
#2375
b1000000 9
b1000 0
b111 ;
1!
#2380
0!
#2385
1<
b1001 0
b1000 ;
1!
#2390
0!
#2395
b1000000 8
b1000000 :
b1010 0
b1001 ;
1!
#2400
0!
#2405
03
0&
b0 0
b0 /
b0 ;
b0 9
0<
01
0=
1!
#2410
0!
b1011000 $
b1011000 .
1%
#2415
13
1&
b1011000 /
11
1!
#2420
0!
0%
#2425
03
0&
b1 0
1=
1!
#2430
0!
#2435
b10 0
b1 ;
1!
#2440
0!
#2445
b11 0
b10 ;
1!
#2450
0!
#2455
13
1&
b100 0
b11 ;
1!
#2460
0!
#2465
b1000 9
b101 0
b100 ;
1!
#2470
0!
#2475
03
0&
b11000 9
b110 0
b101 ;
1!
#2480
0!
#2485
13
1&
b111 0
b110 ;
1!
#2490
0!
#2495
b1011000 9
b1000 0
b111 ;
1!
#2500
0!
#2505
1<
b1001 0
b1000 ;
1!
#2510
0!
#2515
b1011000 8
b1011000 :
b1010 0
b1001 ;
1!
#2520
0!
#2525
03
0&
b0 0
b0 /
b0 ;
b0 9
0<
01
0=
1!
#2530
0!
b1001011 $
b1001011 .
1%
#2535
13
1&
b1001011 /
11
1!
#2540
0!
0%
#2545
b1 0
1=
1!
#2550
0!
#2555
b1 9
b10 0
b1 ;
1!
#2560
0!
#2565
03
0&
b11 9
b11 0
b10 ;
1!
#2570
0!
#2575
13
1&
b100 0
b11 ;
1!
#2580
0!
#2585
03
0&
b1011 9
b101 0
b100 ;
1!
#2590
0!
#2595
b110 0
b101 ;
1!
#2600
0!
#2605
13
1&
b111 0
b110 ;
1!
#2610
0!
#2615
03
0&
b1001011 9
b1000 0
b111 ;
1!
#2620
0!
#2625
13
1&
b1001 0
b1000 ;
1!
#2630
0!
#2635
b1001011 8
b1001011 :
b1010 0
b1001 ;
1!
#2640
0!
#2645
03
0&
b0 0
b0 /
b0 ;
b0 9
01
0=
1!
#2650
0!
b1000000 $
b1000000 .
1%
#2655
13
1&
b1000000 /
11
1!
#2660
0!
0%
#2665
03
0&
b1 0
1=
1!
#2670
0!
#2675
b10 0
b1 ;
1!
#2680
0!
#2685
b11 0
b10 ;
1!
#2690
0!
#2695
b100 0
b11 ;
1!
#2700
0!
#2705
b101 0
b100 ;
1!
#2710
0!
#2715
b110 0
b101 ;
1!
#2720
0!
#2725
13
1&
b111 0
b110 ;
1!
#2730
0!
#2735
b1000000 9
b1000 0
b111 ;
1!
#2740
0!
#2745
1<
b1001 0
b1000 ;
1!
#2750
0!
#2755
b1000000 8
b1000000 :
b1010 0
b1001 ;
1!
#2760
0!
#2765
03
0&
b0 0
b0 /
b0 ;
b0 9
0<
01
0=
1!
#2770
0!
b1000101 $
b1000101 .
1%
#2775
13
1&
b1000101 /
11
1!
#2780
0!
0%
#2785
b1 0
1=
1!
#2790
0!
#2795
03
0&
b1 9
b10 0
b1 ;
1!
#2800
0!
#2805
13
1&
b11 0
b10 ;
1!
#2810
0!
#2815
03
0&
b101 9
b100 0
b11 ;
1!
#2820
0!
#2825
b101 0
b100 ;
1!
#2830
0!
#2835
b110 0
b101 ;
1!
#2840
0!
#2845
13
1&
b111 0
b110 ;
1!
#2850
0!
#2855
b1000101 9
b1000 0
b111 ;
1!
#2860
0!
#2865
1<
b1001 0
b1000 ;
1!
#2870
0!
#2875
b1000101 8
b1000101 :
b1010 0
b1001 ;
1!
#2880
0!
#2885
03
0&
b0 0
b0 /
b0 ;
b0 9
0<
01
0=
1!
#2890
0!
b1110101 $
b1110101 .
1%
#2895
13
1&
b1110101 /
11
1!
#2900
0!
0%
#2905
b1 0
1=
1!
#2910
0!
#2915
03
0&
b1 9
b10 0
b1 ;
1!
#2920
0!
#2925
13
1&
b11 0
b10 ;
1!
#2930
0!
#2935
03
0&
b101 9
b100 0
b11 ;
1!
#2940
0!
#2945
13
1&
b101 0
b100 ;
1!
#2950
0!
