AZ6/Fan.v
`define OUT 2'b00
`define S1 2'b01
`define S2 2'b10
`define S3 2'b11

module Fan(clk,
          sensor,
          rstn,
          CRS_o,
          );
    input clk, rstn;
    input signed [7:0] sensor;
    output [3:0] CRS_o;
    
    reg [1:0] state;
    reg [3:0] CRS;
    
    assign CRS_o = CRS;
    
    always @(posedge clk or negedge rstn) begin
        if (!rstn)begin
            state <= `OUT;
            CRS   <= 0;
        end
        else begin
            case (state)
                `OUT:
                begin
                    CRS                    <= 0;
                    if (sensor > 35) state <= `S1;
                end
                `S1:
                begin
                    CRS                    <= 4;
                    if (sensor > 40) state <= `S2;
                    if (sensor < 25) state <= `OUT;
                end
                `S2:
                begin
                    CRS                    <= 6;
                    if (sensor > 45) state <= `S3;
                    if (sensor < 35) state <= `S1;
                    
                end
                `S3:
                begin
                    CRS                    <= 8;
                    if (sensor < 40) state <= `S2;
                end
            endcase
        end
    end
endmodule

AZ6/AC.v
`define S1 2'b01
`define S2 2'b10
`define S3 2'b11

module AC(clk,
          sensor,
          rstn,
          cool_o,
          heat_o);
    input clk, rstn;
    input signed [7:0] sensor;
    output cool_o,heat_o;
    
    reg [1:0] state;
    reg cooler,heater;
    
    assign cool_o = cooler;
    assign heat_o = heater;
    
    always @(posedge clk or negedge rstn) begin
        if (!rstn)begin
            state  <= `S1;
            cooler <= 0;
            heater <= 0;
        end
        else begin
            case (state)
                `S1:
                begin
                    cooler                <= 0;
                    heater                <= 0;
                    if (sensor > 35)state <= `S2;
                    if (sensor < 15)state <= `S3;
                end
                `S2:
                begin
                    heater                 <= 0;
                    cooler                 <= 1;
                    if (sensor < 25) state <= `S1;
                end
                `S3:
                begin
                    heater                 <= 1;
                    cooler                 <= 0;
                    if (sensor > 30) state <= `S1;
                end
            endcase
            
        end
    end
endmodule

AZ6/Incubator.v
module Incubator (clk,
                  sensor,
                  rstn,
                  heater,
                  cooler,
                  CRS);
    
    input clk,rstn;
    input signed [7:0]sensor;
    output heater,cooler;
    output [3:0] CRS;
    
    
    AC ac (
    .clk(clk),
    .sensor(sensor),
    .rstn(rstn),
    .cool_o(cooler),
    .heat_o(heater)
    );
    
    Fan fan (
    .clk(clk),
    .sensor(sensor),
    .rstn(rstn),
    .CRS_o(CRS)
    );
    
    
endmodule

AZ6/testbench.v
`define NULL 0
module testbench;

    parameter clk_c = 10;
    reg clk, rstn;
    reg signed [7:0] sensor;
    wire heater, cooler;
    wire [3:0] CRS;

    Incubator inc (
    .clk(clk),
    .sensor(sensor),
    .rstn(rstn),
    .heater(heater),
    .cooler(cooler),
    .CRS(CRS)
    );
       
   initial begin
        $dumpfile("report/waveform.vcd");
        $dumpvars(0,inc);
    end

    initial begin
        clk         = 0;
        forever clk = #(clk_c/2) ~clk;
    end

    integer i;
    initial begin
        rstn = 0;
        sensor = -10; 
        #clk_c rstn = 1;
        
        for (i=-10;i<61;i=i+1)begin
            #clk_c sensor = i;
        end
        for (i=60;i>=-10;i=i-1)begin
            #clk_c sensor = i;
        end
        $finish;
    end
    
    initial
        $monitor($time,"\ttempreture:%d, AC_state=%d, Fan_state=%d, HEAT=%b, COOL=%b, CRS=%d",sensor,inc.ac.state, inc.fan.state,heater,cooler,CRS);

endmodule

AZ6/report/waveform.vcd
$date
	Wed Apr 21 10:34:01 2021
$end
$version
	Icarus Verilog
$end
$timescale
	1s
$end
$scope module testbench $end
$scope module inc $end
$var wire 1 ! clk $end
$var wire 1 " rstn $end
$var wire 8 # sensor [7:0] $end
$var wire 1 $ heater $end
$var wire 1 % cooler $end
$var wire 4 & CRS [3:0] $end
$scope module ac $end
$var wire 1 ! clk $end
$var wire 1 % cool_o $end
$var wire 1 $ heat_o $end
$var wire 1 " rstn $end
$var wire 8 ' sensor [7:0] $end
$var reg 1 ( cooler $end
$var reg 1 ) heater $end
$var reg 2 * state [1:0] $end
$upscope $end
$scope module fan $end
$var wire 4 + CRS_o [3:0] $end
$var wire 1 ! clk $end
$var wire 1 " rstn $end
$var wire 8 , sensor [7:0] $end
$var reg 4 - CRS [3:0] $end
$var reg 2 . state [1:0] $end
$upscope $end
$upscope $end
$upscope $end
$enddefinitions $end
#0
$dumpvars
b0 .
b0 -
b11110110 ,
b0 +
b1 *
0)
0(
b11110110 '
b0 &
0%
0$
b11110110 #
0"
0!
$end
#5
1!
#10
0!
1"
#15
b11 *
1!
#20
0!
#25
1$
1)
1!
#30
0!
b11110111 #
b11110111 '
b11110111 ,
#35
1!
#40
0!
b11111000 #
b11111000 '
b11111000 ,
#45
1!
#50
0!
b11111001 #
b11111001 '
b11111001 ,
#55
1!
#60
0!
b11111010 #
b11111010 '
b11111010 ,
#65
1!
#70
0!
b11111011 #
b11111011 '
b11111011 ,
#75
1!
#80
0!
b11111100 #
b11111100 '
b11111100 ,
#85
1!
#90
0!
b11111101 #
b11111101 '
b11111101 ,
#95
1!
#100
0!
b11111110 #
b11111110 '
b11111110 ,
#105
1!
#110
0!
b11111111 #
b11111111 '
b11111111 ,
#115
1!
#120
0!
b0 #
b0 '
b0 ,
#125
1!
#130
0!
b1 #
b1 '
b1 ,
#135
1!
#140
0!
b10 #
b10 '
b10 ,
#145
1!
#150
0!
b11 #
b11 '
b11 ,
#155
1!
#160
0!
b100 #
b100 '
b100 ,
#165
1!
#170
0!
b101 #
b101 '
b101 ,
#175
1!
#180
0!
b110 #
b110 '
b110 ,
#185
1!
#190
0!
b111 #
b111 '
b111 ,
#195
1!
#200
0!
b1000 #
b1000 '
b1000 ,
#205
1!
#210
0!
b1001 #
b1001 '
b1001 ,
#215
1!
#220
0!
b1010 #
b1010 '
b1010 ,
#225
1!
#230
0!
b1011 #
b1011 '
b1011 ,
#235
1!
#240
0!
b1100 #
b1100 '
b1100 ,
#245
1!
#250
0!
b1101 #
b1101 '
b1101 ,
#255
1!
#260
0!
b1110 #
b1110 '
b1110 ,
#265
1!
#270
0!
b1111 #
b1111 '
b1111 ,
#275
1!
#280
0!
b10000 #
b10000 '
b10000 ,
#285
1!
#290
0!
b10001 #
b10001 '
b10001 ,
#295
1!
#300
0!
b10010 #
b10010 '
b10010 ,
#305
1!
#310
0!
b10011 #
b10011 '
b10011 ,
#315
1!
#320
0!
b10100 #
b10100 '
b10100 ,
#325
1!
#330
0!
b10101 #
b10101 '
b10101 ,
#335
1!
#340
0!
b10110 #
b10110 '
b10110 ,
#345
1!
#350
0!
b10111 #
b10111 '
b10111 ,
#355
1!
#360
0!
b11000 #
b11000 '
b11000 ,
#365
1!
#370
0!
b11001 #
b11001 '
b11001 ,
#375
1!
#380
0!
b11010 #
b11010 '
b11010 ,
#385
1!
#390
0!
b11011 #
b11011 '
b11011 ,
#395
1!
#400
0!
b11100 #
b11100 '
b11100 ,
#405
1!
#410
0!
b11101 #
b11101 '
b11101 ,
#415
1!
#420
0!
b11110 #
b11110 '
b11110 ,
#425
1!
#430
0!
b11111 #
b11111 '
b11111 ,
#435
b1 *
1!
#440
0!
b100000 #
b100000 '
b100000 ,
#445
0$
0)
1!
#450
0!
b100001 #
b100001 '
b100001 ,
#455
1!
#460
0!
b100010 #
b100010 '
b100010 ,
#465
1!
#470
0!
b100011 #
b100011 '
b100011 ,
#475
1!
#480
0!
b100100 #
b100100 '
b100100 ,
#485
b1 .
b10 *
1!
#490
0!
b100101 #
b100101 '
b100101 ,
#495
1%
1(
b100 &
b100 +
b100 -
1!
#500
0!
b100110 #
b100110 '
b100110 ,
#505
1!
#510
0!
b100111 #
b100111 '
b100111 ,
#515
1!
#520
0!
b101000 #
b101000 '
b101000 ,
#525
1!
#530
0!
b101001 #
b101001 '
b101001 ,
#535
b10 .
1!
#540
0!
b101010 #
b101010 '
b101010 ,
#545
b110 &
b110 +
b110 -
1!
#550
0!
b101011 #
b101011 '
b101011 ,
#555
1!
#560
0!
b101100 #
b101100 '
b101100 ,
#565
1!
#570
0!
b101101 #
b101101 '
b101101 ,
#575
1!
#580
0!
b101110 #
b101110 '
b101110 ,
#585
b11 .
1!
#590
0!
b101111 #
b101111 '
b101111 ,
#595
b1000 &
b1000 +
b1000 -
1!
#600
0!
b110000 #
b110000 '
b110000 ,
#605
1!
#610
0!
b110001 #
b110001 '
b110001 ,
#615
1!
#620
0!
b110010 #
b110010 '
b110010 ,
#625
1!
#630
0!
b110011 #
b110011 '
b110011 ,
#635
1!
#640
0!
b110100 #
b110100 '
b110100 ,
#645
1!
#650
0!
b110101 #
b110101 '
b110101 ,
#655
1!
#660
0!
b110110 #
b110110 '
b110110 ,
#665
1!
#670
0!
b110111 #
b110111 '
b110111 ,
#675
1!
#680
0!
b111000 #
b111000 '
b111000 ,
#685
1!
#690
0!
b111001 #
b111001 '
b111001 ,
#695
1!
#700
0!
b111010 #
b111010 '
b111010 ,
#705
1!
#710
0!
b111011 #
b111011 '
b111011 ,
#715
1!
#720
0!
b111100 #
b111100 '
b111100 ,
#725
1!
#730
0!
#735
1!
#740
0!
b111011 #
b111011 '
b111011 ,
#745
1!
#750
0!
b111010 #
b111010 '
b111010 ,
#755
1!
#760
0!
b111001 #
b111001 '
b111001 ,
#765
1!
#770
0!
b111000 #
b111000 '
b111000 ,
#775
1!
#780
0!
b110111 #
b110111 '
b110111 ,
#785
1!
#790
0!
b110110 #
b110110 '
b110110 ,
#795
1!
#800
0!
b110101 #
b110101 '
b110101 ,
#805
1!
#810
0!
b110100 #
b110100 '
b110100 ,
#815
1!
#820
0!
b110011 #
b110011 '
b110011 ,
#825
1!
#830
0!
b110010 #
b110010 '
b110010 ,
#835
1!
#840
0!
b110001 #
b110001 '
b110001 ,
#845
1!
#850
0!
b110000 #
b110000 '
b110000 ,
#855
1!
#860
0!
b101111 #
b101111 '
b101111 ,
#865
1!
#870
0!
b101110 #
b101110 '
b101110 ,
#875
1!
#880
0!
b101101 #
b101101 '
b101101 ,
#885
1!
#890
0!
b101100 #
b101100 '
b101100 ,
#895
1!
#900
0!
b101011 #
b101011 '
b101011 ,
#905
1!
#910
0!
b101010 #
b101010 '
b101010 ,
#915
1!
#920
0!
b101001 #
b101001 '
b101001 ,
#925
1!
#930
0!
b101000 #
b101000 '
b101000 ,
#935
1!
#940
0!
b100111 #
b100111 '
b100111 ,
#945
b10 .
1!
#950
0!
b100110 #
b100110 '
b100110 ,
#955
b110 &
b110 +
b110 -
1!
#960
0!
b100101 #
b100101 '
b100101 ,
#965
1!
#970
0!
b100100 #
b100100 '
b100100 ,
#975
1!
#980
0!
b100011 #
b100011 '
b100011 ,
#985
1!
#990
0!
b100010 #
b100010 '
b100010 ,
#995
b1 .
1!
#1000
0!
b100001 #
b100001 '
b100001 ,
#1005
b100 &
b100 +
b100 -
1!
#1010
0!
b100000 #
b100000 '
b100000 ,
#1015
1!
#1020
0!
b11111 #
b11111 '
b11111 ,
#1025
1!
#1030
0!
b11110 #
b11110 '
b11110 ,
#1035
1!
#1040
0!
b11101 #
b11101 '
b11101 ,
#1045
1!
#1050
0!
b11100 #
b11100 '
b11100 ,
#1055
1!
#1060
0!
b11011 #
b11011 '
b11011 ,
#1065
1!
#1070
0!
b11010 #
b11010 '
b11010 ,
#1075
1!
#1080
0!
b11001 #
b11001 '
b11001 ,
#1085
1!
#1090
0!
b11000 #
b11000 '
b11000 ,
#1095
b1 *
b0 .
1!
#1100
0!
b10111 #
b10111 '
b10111 ,
#1105
b0 &
b0 +
b0 -
0%
0(
1!
#1110
0!
b10110 #
b10110 '
b10110 ,
#1115
1!
#1120
0!
b10101 #
b10101 '
b10101 ,
#1125
1!
#1130
0!
b10100 #
b10100 '
b10100 ,
#1135
1!
#1140
0!
b10011 #
b10011 '
b10011 ,
#1145
1!
#1150
0!
b10010 #
b10010 '
b10010 ,
#1155
1!
#1160
0!
b10001 #
b10001 '
b10001 ,
#1165
1!
#1170
0!
b10000 #
b10000 '
b10000 ,
#1175
1!
#1180
0!
b1111 #
b1111 '
b1111 ,
#1185
1!
#1190
0!
b1110 #
b1110 '
b1110 ,
#1195
b11 *
1!
#1200
0!
b1101 #
b1101 '
b1101 ,
#1205
1$
1)
1!
#1210
0!
b1100 #
b1100 '
b1100 ,
#1215
1!
#1220
0!
b1011 #
b1011 '
b1011 ,
#1225
1!
#1230
0!
b1010 #
b1010 '
b1010 ,
#1235
1!
#1240
0!
b1001 #
b1001 '
b1001 ,
#1245
1!
#1250
0!
b1000 #
b1000 '
b1000 ,
#1255
1!
#1260
0!
b111 #
b111 '
b111 ,
#1265
1!
#1270
0!
b110 #
b110 '
b110 ,
#1275
1!
#1280
0!
b101 #
b101 '
b101 ,
#1285
1!
#1290
0!
b100 #
b100 '
b100 ,
#1295
1!
#1300
0!
b11 #
b11 '
b11 ,
#1305
1!
#1310
0!
b10 #
b10 '
b10 ,
#1315
1!
#1320
0!
b1 #
b1 '
b1 ,
#1325
1!
#1330
0!
b0 #
b0 '
b0 ,
#1335
1!
#1340
0!
b11111111 #
b11111111 '
b11111111 ,
#1345
1!
#1350
0!
b11111110 #
b11111110 '
b11111110 ,
#1355
1!
#1360
0!
b11111101 #
b11111101 '
b11111101 ,
#1365
1!
#1370
0!
b11111100 #
b11111100 '
b11111100 ,
#1375
1!
#1380
0!
b11111011 #
b11111011 '
b11111011 ,
#1385
1!
#1390
0!
b11111010 #
b11111010 '
b11111010 ,
#1395
1!
#1400
0!
b11111001 #
b11111001 '
b11111001 ,
#1405
1!
#1410
0!
b11111000 #
b11111000 '
b11111000 ,
#1415
1!
#1420
0!
b11110111 #
b11110111 '
b11110111 ,
#1425
1!
#1430
0!
b11110110 #
b11110110 '
b11110110 ,
